Workbook

Sheet 24-25雪季收入汇总
A1: 24-25雪季易龙雪聚收入汇总
A2: 总收入 | C2: ==C3+C4+C5 -> 2647931.6
A3: 租赁收入 | C3: ==C9+L9+U9 -> 820840
A4: 养护收入 | C4: ==F9+O9+X9 -> 620672
A5: 零售收入 | C5: ==I9+R9+AA9 -> 1206419.6
A6: 门店名称 | C6: 万龙店 | L6: 崇礼旗舰店 | U6: 南山店 | AD6: 儿童成长计划押金 | AE6: 儿童成长计划租金 | AF6: 客户姓名 | AG6: 收款方式
A7: 各门店收入 | C7: ==C9+F9+I9 -> 1618610.6 | L7: ==L9+O9+R9 -> 427221.01 | U7: ==U9+X9+AA9 -> 602100
A8: 业务名称 | C8: 租赁 | F8: 养护 | I8: 零售 | L8: 租赁 | O8: 养护 | R8: 零售 | U8: 租赁 | X8: 养护 | AA8: 零售
A9: 收款合计 | C9: ==SUM(C10:E15) -> 713407 | F9: ==SUM(F10:H15) -> 608042 | I9: ==SUM(I10:K15) -> 297161.6 | L9: ==SUM(L10:N15) -> 61259 | O9: ==SUM(O10:Q15) -> 2280 | R9: ==SUM(R10:T15) -> 363682.01 | U9: ==SUM(U10:W15) -> 46174 | X9: ==SUM(X10:Z15) -> 10350 | AA9: ==SUM(AA10:AC15) -> 545576 | AD9: ==SUM(AD10:AD15) -> 24260 | AE9: ==SUM(AE10:AE15) -> 4300
A10: 11月收款合计 | C10: =='24-25雪季收入明细'!C7+'24-25雪季收入明细'!D7+'24-25雪季收入明细'!E7 -> 63617 | F10: =='24-25雪季收入明细'!F7+'24-25雪季收入明细'!G7+'24-25雪季收入明细'!H7 -> 74760 | I10: =='24-25雪季收入明细'!I7+'24-25雪季收入明细'!J7+'24-25雪季收入明细'!K7 -> 5419 | L10: =='24-25雪季收入明细'!L7+'24-25雪季收入明细'!M7+'24-25雪季收入明细'!N7 -> 1460 | O10: =='24-25雪季收入明细'!O7+'24-25雪季收入明细'!P7+'24-25雪季收入明细'!Q7 -> 0 | R10: =='24-25雪季收入明细'!R7+'24-25雪季收入明细'!S7+'24-25雪季收入明细'!T7 -> 35737.01 | U10: =='24-25雪季收入明细'!U7+'24-25雪季收入明细'!V7+'24-25雪季收入明细'!W7 -> 0 | X10: =='24-25雪季收入明细'!X7+'24-25雪季收入明细'!Y7+'24-25雪季收入明细'!Z7 -> 0 | AA10: =='24-25雪季收入明细'!AA7+'24-25雪季收入明细'!AB7+'24-25雪季收入明细'!AC7+'24-25雪季收入明细'!AD7 -> 4764 | AD10: =='24-25雪季收入明细'!AE7 -> 11140 | AE10: =='24-25雪季收入明细'!AF7 -> 2300 | AF10: 陈美红 | AG10: 万龙微信4775收款
A11: 12月收款合计 | C11: =='24-25雪季收入明细'!C8+'24-25雪季收入明细'!D8+'24-25雪季收入明细'!E8 -> 236127 | F11: =='24-25雪季收入明细'!F8+'24-25雪季收入明细'!G8+'24-25雪季收入明细'!H8 -> 153180 | I11: =='24-25雪季收入明细'!I8+'24-25雪季收入明细'!J8+'24-25雪季收入明细'!K8 -> 54608.6 | L11: =='24-25雪季收入明细'!L8+'24-25雪季收入明细'!M8+'24-25雪季收入明细'!N8 -> 5430 | O11: =='24-25雪季收入明细'!O8+'24-25雪季收入明细'!P8+'24-25雪季收入明细'!Q8 -> 200 | R11: =='24-25雪季收入明细'!R8+'24-25雪季收入明细'!S8+'24-25雪季收入明细'!T8 -> 57629 | U11: =='24-25雪季收入明细'!U8+'24-25雪季收入明细'!V8+'24-25雪季收入明细'!W8 -> 6580 | X11: =='24-25雪季收入明细'!X8+'24-25雪季收入明细'!Y8+'24-25雪季收入明细'!Z8 -> 5070 | AA11: =='24-25雪季收入明细'!AA8+'24-25雪季收入明细'!AB8+'24-25雪季收入明细'!AC8+'24-25雪季收入明细'!AD8 -> 165081 | AD11: =='24-25雪季收入明细'!AE8 -> 6560 | AE11: =='24-25雪季收入明细'!AF8 -> 1000
A12: 01月收款合计 | C12: =='24-25雪季收入明细'!C9+'24-25雪季收入明细'!D9+'24-25雪季收入明细'!E9 -> 168875 | F12: =='24-25雪季收入明细'!F9+'24-25雪季收入明细'!G9+'24-25雪季收入明细'!H9 -> 135472 | I12: =='24-25雪季收入明细'!I9+'24-25雪季收入明细'!J9+'24-25雪季收入明细'!K9 -> 63554 | L12: =='24-25雪季收入明细'!L9+'24-25雪季收入明细'!M9+'24-25雪季收入明细'!N9 -> 18940 | O12: =='24-25雪季收入明细'!O9+'24-25雪季收入明细'!P9+'24-25雪季收入明细'!Q9 -> 800 | R12: =='24-25雪季收入明细'!R9+'24-25雪季收入明细'!S9+'24-25雪季收入明细'!T9 -> 105472 | U12: =='24-25雪季收入明细'!U9+'24-25雪季收入明细'!V9+'24-25雪季收入明细'!W9 -> 19824 | X12: =='24-25雪季收入明细'!X9+'24-25雪季收入明细'!Y9+'24-25雪季收入明细'!Z9 -> 3160 | AA12: =='24-25雪季收入明细'!AA9+'24-25雪季收入明细'!AB9+'24-25雪季收入明细'!AC9+'24-25雪季收入明细'!AD9 -> 230573 | AD12: =='24-25雪季收入明细'!AE9 -> 6560 | AE12: =='24-25雪季收入明细'!AF9 -> 1000
A13: 02月收款合计 | C13: =='24-25雪季收入明细'!C10+'24-25雪季收入明细'!D10+'24-25雪季收入明细'!E10 -> 138719 | F13: =='24-25雪季收入明细'!F10+'24-25雪季收入明细'!G10+'24-25雪季收入明细'!H10 -> 117155 | I13: =='24-25雪季收入明细'!I10+'24-25雪季收入明细'!J10+'24-25雪季收入明细'!K10 -> 82893 | L13: =='24-25雪季收入明细'!L10+'24-25雪季收入明细'!M10+'24-25雪季收入明细'!N10 -> 27385 | O13: =='24-25雪季收入明细'!O10+'24-25雪季收入明细'!P10+'24-25雪季收入明细'!Q10 -> 480 | R13: =='24-25雪季收入明细'!R10+'24-25雪季收入明细'!S10+'24-25雪季收入明细'!T10 -> 133184 | U13: =='24-25雪季收入明细'!U10+'24-25雪季收入明细'!V10+'24-25雪季收入明细'!W10 -> 19410 | X13: =='24-25雪季收入明细'!X10+'24-25雪季收入明细'!Y10+'24-25雪季收入明细'!Z10 -> 1720 | AA13: =='24-25雪季收入明细'!AA10+'24-25雪季收入明细'!AB10+'24-25雪季收入明细'!AC10+'24-25雪季收入明细'!AD10 -> 135457 | AD13: =='24-25雪季收入明细'!AE10 -> 0 | AE13: =='24-25雪季收入明细'!AF10 -> 0
A14: 03月收款合计 | C14: =='24-25雪季收入明细'!C11+'24-25雪季收入明细'!D11+'24-25雪季收入明细'!E11 -> 98438 | F14: =='24-25雪季收入明细'!F11 -> 110995 | I14: =='24-25雪季收入明细'!I11+'24-25雪季收入明细'!J11+'24-25雪季收入明细'!K11 -> 83051 | L14: =='24-25雪季收入明细'!L11 -> 7444 | O14: =='24-25雪季收入明细'!O11+'24-25雪季收入明细'!P11+'24-25雪季收入明细'!Q11 -> 600 | R14: =='24-25雪季收入明细'!R11+'24-25雪季收入明细'!S11+'24-25雪季收入明细'!T11 -> 30852 | U14: =='24-25雪季收入明细'!U11+'24-25雪季收入明细'!V11+'24-25雪季收入明细'!W11 -> 360 | X14: =='24-25雪季收入明细'!X11+'24-25雪季收入明细'!Y11+'24-25雪季收入明细'!Z11 -> 400 | AA14: =='24-25雪季收入明细'!AA11+'24-25雪季收入明细'!AB11+'24-25雪季收入明细'!AC11+'24-25雪季收入明细'!AD11 -> 9701 | AD14: =='24-25雪季收入明细'!AE11 -> 0 | AE14: =='24-25雪季收入明细'!AF11 -> 0
A15: 04月收款合计 | C15: =='24-25雪季收入明细'!C12+'24-25雪季收入明细'!D12+'24-25雪季收入明细'!E12 -> 7631 | F15: =='24-25雪季收入明细'!F12 -> 16480 | I15: =='24-25雪季收入明细'!I12 -> 7636 | L15: =='24-25雪季收入明细'!L12 -> 600 | O15: =='24-25雪季收入明细'!O12+'24-25雪季收入明细'!P12+'24-25雪季收入明细'!Q12 -> 200 | R15: =='24-25雪季收入明细'!R12+'24-25雪季收入明细'!S12+'24-25雪季收入明细'!T12 -> 808 | U15: =='24-25雪季收入明细'!U12+'24-25雪季收入明细'!V12+'24-25雪季收入明细'!W12 -> 0 | X15: =='24-25雪季收入明细'!X12+'24-25雪季收入明细'!Y12+'24-25雪季收入明细'!Z12 -> 0 | AA15: =='24-25雪季收入明细'!AA12+'24-25雪季收入明细'!AB12+'24-25雪季收入明细'!AC12+'24-25雪季收入明细'!AD12 -> 0 | AD15: =='24-25雪季收入明细'!AE12 -> 0 | AE15: =='24-25雪季收入明细'!AF12 -> 0
A17: 1、万龙租赁1.9客人将板丢失，押金5000做为雪板赔偿，故收入做到万龙零售中
A18: 2、旗舰零售12.17收款4200实际为南山店零售，故调出，收入做到南山店中
M20: 万龙 | N20: 0.61538462
M21: 旗舰 | N21: 0.15384615
M22: 南山 | N22: 0.23076923

Sheet 24-25雪季收入明细
A1: 24-25雪季易龙雪聚收入明细
A2: 门店名称 | C2: 万龙店 | L2: 崇礼旗舰店 | U2: 南山店
A3: 业务名称 | C3: 租赁 | F3: 养护 | I3: 零售 | L3: 租赁 | O3: 养护 | R3: 零售 | U3: 租赁 | X3: 养护 | AA3: 零售
A4: 收款方式 | C4: 微信 | D4: 京东收银 | E4: 招行 | F4: 微信 | G4: 京东收银 | H4: 招行 | I4: 微信 | J4: 京东收银 | K4: 招行 | L4: 微信 | M4: 京东收银 | N4: 招行 | O4: 微信 | P4: 京东收银 | Q4: 招行 | R4: 微信 | S4: 京东收银 | T4: 招行 | U4: 微信 | V4: 京东收银 | W4: 招行 | X4: 微信 | Y4: 京东收银 | Z4: 招行 | AA4: 微信 | AB4: 京东收银 | AC4: 招行 | AD4: 现金 | AE4: 儿童成长押金 | AF4: 儿童成长计划租金 | AG4: 客户姓名 | AH4: 收款方式
C5: 6346 | E5: 8997 | F5: 5183 | H5: 8997 | I5: 4775 | K5: 8997 | L5: 3350 | N5: 8997 | O5: 5482 | Q5: 8997 | R5: 1865 | U5: 9791 | W5: 8997 | X5: 258 | Z5: 8997 | AA5: 3448 | AC5: 8997
A6: 收款合计 | C6: ==SUM(C7:C12) -> 707857 | D6: ==SUM(D7:D12) -> 1440 | E6: ==SUM(E7:E12) -> 4110 | F6: ==SUM(F7:F12) -> 604142 | G6: ==SUM(G7:G12) -> 0 | H6: ==SUM(H7:H12) -> 3900 | I6: ==SUM(I7:I12) -> 259980.6 | J6: ==SUM(J7:J12) -> 20247 | ... AF6: ==SUM(AF7:AF12) -> 4300
A7: 11月收款合计 | C7: ==SUM(C13:C36) -> 59067 | D7: ==SUM(D13:D36) -> 1440 | E7: ==SUM(E13:E36) -> 3110 | F7: ==SUM(F13:F36) -> 74760 | G7: ==SUM(G13:G36) -> 0 | H7: ==SUM(H13:H36) -> 0 | I7: ==SUM(I13:I36) -> 5419 | J7: ==SUM(J13:J36) -> 0 | ... AF7: ==SUM(AF13:AF36) -> 2300
A8: 12月收款合计 | C8: ==SUM(C37:C67) -> 236127 | D8: ==SUM(D37:D67) -> 0 | E8: ==SUM(E37:E67) -> 0 | F8: ==SUM(F37:F67) -> 150180 | G8: ==SUM(G37:G67) -> 0 | H8: ==SUM(H37:H67) -> 3000 | I8: ==SUM(I37:I67) -> 39074.6 | J8: ==SUM(J37:J67) -> 0 | ... AF8: ==SUM(AF37:AF67) -> 1000
A9: 01月收款合计 | C9: ==SUM(C68:C98) -> 167875 | D9: ==SUM(D68:D98) -> 0 | E9: ==SUM(E68:E98) -> 1000 | F9: ==SUM(F68:F98) -> 135472 | G9: ==SUM(G68:G98) -> 0 | H9: ==SUM(H68:H98) -> 0 | I9: ==SUM(I68:I98) -> 49506 | J9: ==SUM(J68:J98) -> 14048 | ... AF9: ==SUM(AF68:AF98) -> 1000
A10: 02月收款合计 | C10: ==SUM(C99:C126) -> 138719 | D10: ==SUM(D99:D126) -> 0 | E10: ==SUM(E99:E126) -> 0 | F10: ==SUM(F99:F126) -> 116255 | G10: ==SUM(G99:G126) -> 0 | H10: ==SUM(H99:H126) -> 900 | I10: ==SUM(I99:I126) -> 76694 | J10: ==SUM(J99:J126) -> 6199 | ... AF10: ==SUM(AF99:AF126) -> 0
A11: 03月收款合计 | C11: ==SUM(C127:C157) -> 98438 | D11: ==SUM(D127:D157) -> 0 | E11: ==SUM(E127:E157) -> 0 | F11: ==SUM(F127:F157) -> 110995 | G11: ==SUM(G127:G157) -> 0 | H11: ==SUM(H127:H157) -> 0 | I11: ==SUM(I127:I157) -> 81651 | J11: ==SUM(J127:J157) -> 0 | ... AF11: ==SUM(AF127:AF157) -> 0
A12: 04月收款合计 | C12: ==SUM(C158:C177) -> 7631 | D12: ==SUM(D158:D177) -> 0 | E12: ==SUM(E158:E177) -> 0 | F12: ==SUM(F158:F177) -> 16480 | G12: ==SUM(G158:G177) -> 0 | H12: ==SUM(H158:H177) -> 0 | I12: ==SUM(I158:I177) -> 7636 | J12: ==SUM(J158:J177) -> 0 | ... AF12: ==SUM(AF158:AF177) -> 0
A13: 2024.11.07 | B13: 周四 | C13: 0 | F13: 280 | S13: 10479.01
A14: 2024.11.08 | B14: 周五 | C14: 100 | F14: 1380
A15: 2024.11.09 | B15: 周六 | C15: 3160 | F15: 4510 | I15: 790 | T15: 4650
A16: 2024.11.10 | B16: 周日 | C16: 580 | D16: 360 | F16: 3880 | N16: 1300
A17: 2024.11.11 | B17: 周一 | C17: 0 | E17: 500 | F17: 700 | AE17: 3280 | AF17: 500 | AG17: 陈美红 | AH17: 万龙零售4775收款
A18: 2024.11.12 | B18: 周二 | C18: 0 | F18: 1450
A19: 2024.11.13 | B19: 周三 | C19: 130 | F19: 1990
A20: 2024.11.14 | B20: 周四 | C20: 120 | F20: 1620 | R20: 2400
A21: 2024.11.15 | B21: 周五 | C21: 820 | F21: 2250
A22: 2024.11.16 | B22: 周六 | C22: 4431 | F22: 7310 | I22: 860
A23: 2024.11.17 | B23: 周日 | C23: 4680 | F23: 6790 | I23: 258 | L23: 160
A24: 2024.11.18 | B24: 周一 | C24: 1340 | F24: 2430 | I24: 30
A25: 2024.11.19 | B25: 周二 | C25: 1110 | F25: 1580
A26: 2024.11.20 | B26: 周三 | C26: 3040 | F26: 1050
A27: 2024.11.21 | B27: 周四 | C27: 1509 | F27: 1180
A28: 2024.11.22 | B28: 周五 | C28: 1705 | F28: 2710
A29: 2024.11.23 | B29: 周六 | C29: 4690 | D29: 1080 | E29: 610 | F29: 7010 | I29: 588 | T29: 2244
A30: 2024.11.24 | B30: 周日 | C30: 3111 | E30: 500 | F30: 5140 | R30: 445 | AE30: 3280 | AF30: 500 | AG30: 王婧婧 | AH30: 万龙零售4775收款
A31: 2024.11.25 | B31: 周一 | C31: 3390 | F31: 2130 | I31: 146 | T31: 4100
A32: 2024.11.26 | B32: 周二 | C32: 2370 | F32: 4320
A33: 2024.11.27 | B33: 周三 | C33: 300 | F33: 2570
A34: 2024.11.28 | B34: 周四 | C34: ==2965-720 -> 2245 | F34: 1910 | R34: 3080 | AC34: 474
A35: 2024.11.29 | B35: 周五 | C35: 2961 | F35: 2200 | I35: 1732
A36: 2024.11.30 | B36: 周六 | C36: 17275 | E36: 1500 | F36: 8370 | I36: 1015 | R36: 1180 | T36: 7159 | AD36: 4290 | AE36: 4580 | AF36: 1300 | AG36: 李聪 | AH36: 万龙零售4775收款
A37: 2024.12.01 | B37: 周日 | C37: 11487 | F37: 4390 | I37: 784
A38: 2024.12.02 | B38: 周一 | C38: 5070 | F38: 3150 | I38: 1201 | K38: 359 | R38: 1180
A39: 2024.12.03 | B39: 周二 | C39: 3650 | F39: 3320 | I39: 289
A40: 2024.12.04 | B40: 周三 | C40: 2010 | F40: 3260 | I40: 336
A41: 2024.12.05 | B41: 周四 | C41: 5046 | F41: 3320 | I41: 262 | X41: 200 | AA41: 1612
A42: 2024.12.06 | B42: 周五 | C42: 1730 | F42: 5430 | I42: 358 | R42: 688 | X42: 200 | AA42: 4757 | AB42: 69
A43: 2024.12.07 | B43: 周六 | C43: 11469 | F43: 13890 | I43: ==14925-3100 -> 11825 | R43: 588 | AA43: 1033 | AB43: 387 | AD43: 5180
A44: 2024.12.08 | B44: 周日 | C44: 11794 | F44: 5690 | I44: 3100 | L44: 80 | X44: 250 | AA44: 954 | AB44: 6992
A45: 2024.12.09 | B45: 周一 | C45: 1954 | F45: 3790 | S45: 724 | X45: 400 | AA45: 258 | AB45: 2959 | AD45: 130
A46: 2024.12.10 | B46: 周二 | C46: 2400 | F46: 4780 | I46: 754 | K46: 359 | X46: 200 | AA46: 168
A47: 2024.12.11 | B47: 周三 | C47: 4870 | F47: 2410 | I47: 30 | K47: 359 | L47: 300 | R47: 5130 | X47: 500 | AA47: 30 | AB47: 1141 | AC47: 560
A48: 2024.12.12 | B48: 周四 | C48: 2100 | F48: 2530 | R48: -588 | U48: 80 | X48: 1200 | AA48: 368 | AB48: 1220
A49: 2024.12.13 | B49: 周五 | C49: 10420 | F49: 3220 | AA49: 8513 | AB49: 99 | AD49: 2100
A50: 2024.12.14 | B50: 周六 | C50: 11272 | F50: 10795 | I50: 2131 | K50: 180 | L50: 500 | U50: 200 | V50: 50 | X50: 750 | AA50: 3566 | AB50: 8211 | AE50: 3280 | AF50: 500 | AG50: 刘女士 | AH50: 崇礼旗舰零售1865收款
A51: 2024.12.15 | B51: 周日 | C51: 14785 | F51: 7145 | I51: 1025 | K51: 1077 | U51: 260 | AA51: 2433 | AB51: 3269 | AD51: 99
A52: 2024.12.16 | B52: 周一 | C52: 3240 | F52: 3740 | I52: 199 | L52: 350 | U52: 30 | X52: 190 | AA52: 228 | AB52: 267
A53: 2024.12.17 | B53: 周二 | C53: 5170 | F53: 4300 | I53: 198 | R53: 3700 | S53: 5300 | X53: 300 | AA53: ==4200+1590 -> 5790 | AB53: 523
A54: 2024.12.18 | B54: 周三 | C54: 6030 | F54: 5430 | H54: 3000 | I54: 327 | X54: 100 | AA54: 527 | AB54: 7791 | AH54: 南山微信4200，收款为旗舰微信
A55: 2024.12.19 | B55: 周四 | C55: 11220 | F55: 2720 | I55: 687 | U55: 150 | AA55: 1780 | AB55: 10379
A56: 2024.12.20 | B56: 周五 | C56: 4900 | F56: 3870 | I56: 0 | L56: ==1100+500 -> 1600 | R56: 3403 | U56: 580 | AA56: 5821 | AB56: 723 | AE56: 3280 | AF56: 500 | AG56: 王一顺 | AH56: 旗舰微信3350，收款
A57: 2024.12.21 | B57: 周六 | C57: 10070 | F57: 7520 | I57: 4206 | L57: 800 | R57: 944 | U57: 590 | V57: 250 | AA57: 5108 | AB57: ==2202-250 -> 1952
A58: 2024.12.22 | B58: 周日 | C58: 8350 | F58: 5780 | I58: 658 | K58: 13200 | T58: 6300 | U58: 520 | AA58: 981 | AB58: 1327
A59: 2024.12.23 | B59: 周一 | C59: 990 | F59: 5120 | R59: 524 | U59: 200 | AA59: 6152 | AB59: 763
A60: 2024.12.24 | B60: 周二 | C60: 5980 | F60: 2410 | I60: 915 | R60: 900 | S60: 1650 | U60: 360 | AA60: 168 | AB60: 1965
A61: 2024.12.25 | B61: 周三 | C61: 5540 | F61: 2550 | I61: 509 | R61: 4456 | S61: 3000 | T61: 1000 | U61: 160 | AA61: 297 | AB61: 15047
A62: 2024.12.26 | B62: 周四 | C62: 12280 | F62: 2590 | I62: 827 | T62: 796 | U62: 1100 | X62: 50 | AA62: 7671 | AB62: 9049
A63: 2024.12.27 | B63: 周五 | C63: 7680 | F63: 2500 | I63: 2274 | U63: 40 | X63: 430 | AA63: 2805 | AB63: 1464
A64: 2024.12.28 | B64: 周六 | C64: 9770 | F64: 11090 | I64: 657 | L64: 300 | R64: 4130 | U64: 680 | X64: 300 | AA64: 5214 | AB64: 2177 | AD64: 4336
A65: 2024.12.29 | B65: 周日 | C65: 18420 | F65: 7330 | I65: 5057.6 | R65: 180 | U65: 440 | AA65: 1856 | AB65: 2325
A66: 2024.12.30 | B66: 周一 | C66: 21630 | F66: 3140 | I66: 407 | L66: 1500 | O66: 200 | R66: 13365 | U66: 120 | AA66: 1201 | AB66: 1165
A67: 2024.12.31 | B67: 周二 | C67: 4800 | F67: 2970 | I67: 58 | S67: 259 | U67: 770 | AA67: 1734 | AB67: 387
A68: 2025.01.01 | B68: 周三 | C68: 8320 | F68: 5565 | I68: 714 | L68: 740 | S68: 330 | U68: 240 | X68: ==300 -> 300 | AA68: 2364 | AB68: 2653
A69: 2025.01.02 | B69: 周四 | C69: 2150 | F69: 4700 | I69: 7713 | L69: 750 | U69: 120 | AA69: 2033 | AB69: 993
A70: 2025.01.03 | B70: 周五 | C70: 5550 | F70: 4590 | I70: 1036 | L70: 1380 | R70: 17166 | AA70: 7311 | AB70: 801
A71: 2025.01.04 | B71: 周六 | C71: ==10390+200 -> 10590 | F71: 11030 | I71: 1948 | U71: 1220 | X71: 250 | AA71: 8683 | AB71: 775
A72: 2025.01.05 | B72: 周日 | C72: ==8680+500 -> 9180 | F72: 5200 | I72: 6134 | L72: 1680 | R72: 588 | S72: 165 | U72: 240 | AA72: 2834 | AB72: 168
A73: 2025.01.06 | B73: 周一 | C73: 1490 | F73: 4010 | I73: 1578 | L73: 280 | R73: 560 | X73: 200 | AA73: 158 | AB73: 525
A74: 2025.01.07 | B74: 周二 | C74: 5670 | F74: 2320 | I74: 3357 | J74: 1950 | L74: -280 | R74: 258 | S74: 2999 | U74: 110 | X74: 200 | AA74: 4265 | AB74: 3239
A75: 2025.01.08 | B75: 周三 | C75: 3860 | F75: 3560 | I75: 858 | R75: 846 | U75: 340 | AA75: 3456 | AB75: 188
A76: 2025.01.09 | B76: 周四 | C76: 1630 | F76: 2540 | I76: ==1419+5000 -> 6419 | L76: 440 | S76: 450 | U76: 320 | X76: 100 | AA76: 1181 | AB76: 853
A77: 2025.01.10 | B77: 周五 | C77: 4970 | F77: 4250 | I77: 499 | L77: 1090 | R77: 2399 | U77: 510 | X77: 100 | AA77: 6903 | AB77: 428
A78: 2025.01.11 | B78: 周六 | C78: 10570 | E78: 500 | F78: 12400 | I78: 1529 | L78: 280 | R78: 620 | U78: 1020 | AA78: 9553 | AB78: 1699 | AE78: 3280 | AF78: 500 | AG78: 刘雅萱 | AH78: 万龙微信4775收款
A79: 2025.01.12 | B79: 周日 | C79: 5040 | F79: 4540 | I79: 777 | L79: 100 | R79: 1096 | U79: 860 | X79: 120 | AA79: 7432 | AB79: 883
A80: 2025.01.13 | B80: 周一 | C80: 2570 | F80: 1750 | I80: 714 | L80: 100 | R80: 9088 | U80: 550 | X80: 200 | AA80: 8488 | AB80: 7778
A81: 2025.01.14 | B81: 周二 | C81: 5630 | F81: 2175 | I81: 464 | O81: 400 | R81: 3418 | S81: 17923 | U81: 80 | AA81: 13335 | AB81: 15589
A82: 2025.01.15 | B82: 周三 | C82: 400 | F82: 4000 | L82: 800 | S82: 100 | U82: 470 | AA82: 3746 | AD82: 198
A83: 2025.01.16 | B83: 周四 | C83: 1450 | F83: 2660 | I83: 149 | L83: 1860 | T83: 100 | U83: 290 | W83: 460 | AA83: 723 | AB83: 2661 | AD83: 100
A84: 2025.01.17 | B84: 周五 | C84: 9760 | F84: 3710 | L84: 160 | R84: 6809 | U84: 1020 | AA84: 3695 | AB84: 277
A85: 2025.01.18 | B85: 周六 | C85: 8540 | F85: 10710 | I85: 753 | L85: 3000 | R85: 856 | T85: 1670 | U85: 1340 | X85: 200 | AA85: 21747 | AB85: 445
A86: 2025.01.19 | B86: 周日 | C86: 6240 | F86: 4690 | I86: 516 | L86: 430 | R86: 898 | S86: 2700 | U86: 1064 | AA86: 3113 | AB86: 2416
A87: 2025.01.20 | B87: 周一 | C87: ==6760+300 -> 7060 | F87: 3680 | I87: 199 | R87: 1017 | U87: 530 | AA87: 4906 | AB87: 870
A88: 2025.01.21 | B88: 周二 | C88: 2080 | F88: 2600 | I88: 199 | J88: 6899 | R88: 1067 | U88: 200 | X88: 250 | AB88: 874
A89: 2025.01.22 | B89: 周三 | C89: 4580 | F89: 4170 | I89: 636 | L89: 1260 | R89: 1600 | U89: 390 | X89: 200 | AA89: 6936 | AB89: 466
A90: 2025.01.23 | B90: 周四 | C90: 1980 | F90: 3780 | I90: 773 | O90: 400 | R90: 218 | U90: 600 | AA90: 336 | AB90: 168
A91: 2025.01.24 | B91: 周五 | C91: 14750 | F91: 5210 | I91: 1729 | L91: 480 | R91: 4254 | U91: 1470 | V91: 50 | X91: 240 | AA91: 1160 | AB91: ==3433-50 -> 3383
A92: 2025.01.25 | B92: 周六 | C92: 12520 | F92: 4760 | I92: 8949 | R92: 14430 | U92: 1550 | X92: 400 | AA92: 9478 | AB92: 7548
A93: 2025.01.26 | B93: 周日 | C93: 6170 | F93: 2060 | L93: 850 | R93: 963 | U93: 1210 | AA93: 435 | AB93: 771
A94: 2025.01.27 | B94: 周一 | C94: 2150 | E94: 500 | F94: 970 | I94: 159 | L94: 2110 | R94: 168 | U94: 1360 | X94: 400 | AA94: 3670 | AB94: 1899 | AE94: 3280 | AF94: 500 | AH94: 万龙微信4775收款
A95: 2025.01.28 | B95: 周二 | C95: 640 | F95: 380 | R95: 2130 | AA95: 267 | AB95: 672
A96: 2025.01.29 | B96: 周三 | C96: 970 | F96: 2680 | I96: 199 | R96: 366 | U96: 260 | AA96: 328 | AB96: 336
A97: 2025.01.30 | B97: 周四 | C97: 2630 | F97: 4640 | I97: 624 | J97: 5199 | L97: 1430 | R97: 8220 | U97: 790 | W97: 80 | AA97: 9100 | AB97: 8706 | AD97: 600
A98: 2025.01.31 | B98: 周五 | C98: 8735 | F98: 6142 | I98: 881 | R98: 0 | U98: 1080 | AA98: 8686 | AB98: 3589 | AD98: 1700
A99: 2025.02.01 | B99: 周六 | C99: 13930 | F99: 7775 | I99: 614 | L99: 120 | R99: 2744 | T99: 100 | U99: 1490 | X99: 250 | AA99: 6744 | AB99: 5468 | AD99: 3735
A100: 2025.02.02 | B100: 周日 | C100: 8650 | F100: 6445 | I100: 9378 | L100: 4960 | R100: 6100 | U100: 920 | AA100: 1344 | AB100: 2052
...

Sheet 万龙租赁
C1: 业务门店 | D1: 开单门店 | E1: 订单ID | F1: 门店 | G1: 姓名 | H1: 电话 | I1: 押金 | J1: 退款 | K1: 结余 | L1: 损坏赔偿 | M1: 租金 | N1: 支付方式 | O1: 日期 | P1: 时间 | Q1: 接待 | R1: 员工
A2: 1 | B2: 系统订单 | C2: 万龙 | D2: 万龙 | E2: 4798 | F2: 万龙体验中心 | G2: 肖志强（个人） 先生 | H2: 15838200977 | I2: 100 | J2: 0 | K2: 100 | L2: 0 | M2: 100 | N2: 微信支付 | O2: 45605 | P2: 0.86050926 | Q2: 肖志强（工作号） | R2: 肖志强
A3: 2 | B3: 系统订单 | C3: 万龙 | D3: 万龙 | E3: 4801 | F3: 万龙体验中心 | H3: 13488805747 | I3: 4400 | J3: 3845 | K3: 555 | L3: 0 | M3: 555 | N3: 微信支付 | O3: 45605 | P3: 0.6884375 | Q3: 肖志强（工作号） | R3: 肖志强
B4: 系统订单 | C4: 万龙 | D4: 万龙 | E4: 4802 | F4: 万龙体验中心 | G4: 张 先生 | H4: 13810012539 | I4: 3000 | J4: 2850 | K4: 150 | L4: 0 | M4: 150 | N4: 微信支付 | O4: 45605 | P4: 0.85915509 | Q4: 肖志强（工作号） | R4: 肖志强
B5: 系统订单 | C5: 万龙 | D5: 万龙 | E5: 4803 | F5: 万龙体验中心 | G5: 王 女士 | H5: 15933571552 | I5: 1000 | J5: 900 | K5: 100 | L5: 0 | M5: 100 | N5: 微信支付 | O5: 45605 | P5: 0.51715278 | Q5: 肖志强（工作号） | R5: 肖志强
B6: 系统订单 | C6: 万龙 | D6: 万龙 | E6: 4804 | F6: 万龙体验中心 | G6: 边 女士 | H6: 18622485396 | I6: 5000 | J6: 4520 | K6: 480 | L6: 0 | M6: 480 | N6: 微信支付 | O6: 45605 | P6: 0.71063657 | Q6: 肖志强（工作号） | R6: 肖志强
B7: 系统订单 | C7: 万龙 | D7: 万龙 | E7: 4807 | F7: 万龙体验中心 | G7: 贾 女士 | H7: 13911055600 | I7: 3000 | J7: 2820 | K7: 180 | L7: 0 | M7: 180 | N7: 微信支付 | O7: 45606 | P7: 0.37611111 | Q7: 修姜山（个人） | R7: 修姜山
B8: 系统订单 | C8: 万龙 | D8: 万龙 | E8: 4808 | F8: 万龙体验中心 | G8: 胡 女士 | H8: 13601008796 | I8: 1000 | J8: 880 | K8: 120 | L8: 0 | M8: 120 | N8: 微信支付 | O8: 45605 | P8: 0.78667824 | Q8: 修姜山（个人） | R8: 修姜山
B9: 系统订单 | C9: 万龙 | D9: 万龙 | E9: 4811 | F9: 万龙体验中心 | G9: 郑 先生 | H9: 18920043297 | I9: 4000 | J9: 3580 | K9: 420 | L9: 0 | M9: 420 | N9: 微信支付 | O9: 45605 | P9: 0.66454861 | Q9: 肖志强（工作号） | R9: 肖志强
B10: 系统订单 | C10: 万龙 | D10: 万龙 | E10: 4812 | F10: 万龙体验中心 | G10: 孟 先生 | H10: 16620464110 | I10: 5000 | J10: 3930 | K10: 1070 | L10: 0 | M10: 1070 | N10: 微信支付 | O10: 45605 | P10: 0.72135417 | Q10: 修姜山（个人） | R10: 修姜山
B11: 系统订单 | C11: 万龙 | D11: 万龙 | E11: 4813 | F11: 万龙体验中心 | G11: 范 先生 | H11: 15133330377 | I11: 1000 | J11: 945 | K11: 55 | L11: 0 | M11: 55 | N11: 微信支付 | O11: 45605 | P11: 0.87210648 | Q11: 肖志强（工作号） | R11: 肖志强
B12: 系统订单 | C12: 万龙 | D12: 万龙 | E12: 4814 | F12: 万龙体验中心 | G12: 赵 先生 | H12: 18034018073 | I12: 5000 | J12: 4790 | K12: 210 | L12: 0 | M12: 210 | N12: 微信支付 | O12: 45605 | P12: 0.88186343 | Q12: 肖志强（工作号） | R12: 肖志强
B13: 系统订单 | C13: 万龙 | D13: 万龙 | E13: 4815 | F13: 万龙体验中心 | G13: 倪 先生 | H13: 15001130086 | I13: 3000 | J13: 2820 | K13: 180 | L13: 0 | M13: 180 | N13: 微信支付 | O13: 45606 | P13: 0.50959491 | Q13: 肖志强（工作号） | R13: 肖志强
B14: 系统订单 | C14: 万龙 | D14: 万龙 | E14: 4816 | F14: 万龙体验中心 | G14: 先生 | H14: 18941347398 | I14: 5000 | J14: 4780 | K14: 220 | L14: 0 | M14: 220 | N14: 微信支付 | O14: 45606 | P14: 0.60344907 | Q14: 肖志强（工作号） | R14: 肖志强
B15: 系统订单 | C15: 万龙 | D15: 万龙 | E15: 4819 | F15: 万龙体验中心 | G15: 刘 先生 | H15: 17610855261 | I15: 200 | J15: 170 | K15: 30 | L15: 0 | M15: 30 | N15: 微信支付 | O15: 45609 | P15: 0.66787037 | Q15: 肖志强（工作号） | R15: 肖志强
... B111: 系统订单 | C111: 万龙 | D111: 万龙 | E111: 4951 | F111: 万龙体验中心 | G111: 陆 先生 | H111: 13910839831 | I111: 200 | J111: 150 | K111: 50 | L111: 0 | M111: 50 | N111: 微信支付 | O111: 45618 | P111: 0.66090278 | Q111: 张小飞 | R111: 张小飞
B112: 人工订单 | D112: 万龙 | E112: 【-】 | F112: 万龙体验中心 | G112: 【-】 | H112: 【-】 | I112: 【-】 | J112: 【-】 | K112: 【-】 | L112: 【-】 | M112: 610 | N112: 崔洋（微信） | O112: 45619 | P112: 【-】 | Q112: 崔洋 | R112: 崔洋
B113: 系统订单 | C113: 万龙 | D113: 万龙 | E113: 4952 | F113: 万龙体验中心 | G113: 王 先生 | H113: 13911285423 | I113: 5000 | J113: 4780 | K113: 220 | L113: 0 | M113: 220 | N113: 微信支付 | O113: 45619 | P113: 0.6747338 | Q113: 肖志强（工作号） | R113: 肖志强
B114: 系统订单 | C114: 万龙 | D114: 万龙 | E114: 4953 | F114: 万龙体验中心 | G114: 黄 女士 | H114: 13510860612 | I114: 1000 | J114: 760 | K114: 240 | L114: 0 | M114: 240 | N114: 微信支付 | O114: 45620 | P114: 0.61574074 | Q114: 许进升（个人） | R114: 许进升
B115: 系统订单 | C115: 万龙 | D115: 万龙 | E115: 4954 | F115: 万龙体验中心 | G115: 汪 先生 | H115: 13683137883 | I115: 8000 | J115: 7800 | K115: 200 | L115: 0 | M115: 200 | N115: 微信支付 | O115: 45619 | P115: 0.67327546 | Q115: 张 | R115: 张亮
B116: 系统订单 | C116: 万龙 | D116: 万龙 | E116: 4955 | F116: 万龙体验中心 | G116: 张 先生 | H116: 15864669981 | I116: 3000 | J116: 2640 | K116: 360 | L116: 0 | M116: 360 | N116: 微信支付 | O116: 45620 | P116: 0.51989583 | Q116: 肖志强（工作号） | R116: 肖志强
B117: 系统订单 | C117: 万龙 | D117: 万龙 | E117: 4956 | F117: 万龙体验中心 | G117: 33 女士 | H117: 15901402678 | I117: 3000 | J117: 2850 | K117: 150 | L117: 0 | M117: 150 | N117: 微信支付 | O117: 45619 | P117: 0.60678241 | Q117: 肖志强（工作号） | R117: 肖志强
B118: 系统订单 | C118: 万龙 | D118: 万龙 | E118: 4957 | F118: 万龙体验中心 | G118: 龚 女士 | H118: 18258157160 | I118: 1000 | J118: 760 | K118: 240 | L118: 0 | M118: 240 | N118: 微信支付 | O118: 45619 | P118: 0.49493056 | Q118: 肖志强（工作号） | R118: 肖志强
B119: 系统订单 | C119: 万龙 | D119: 万龙 | E119: 4958 | F119: 万龙体验中心 | G119: 魏 女士 | H119: 13510660342 | I119: 1000 | J119: 860 | K119: 140 | L119: 0 | M119: 140 | N119: 微信支付 | O119: 45619 | P119: 0.65559028 | Q119: 张小飞 | R119: 张小飞
B120: 系统订单 | C120: 万龙 | D120: 万龙 | E120: 4959 | F120: 万龙体验中心 | G120: 陈 女士 | H120: 18678419009 | I120: 200 | J120: 140 | K120: 60 | L120: 0 | M120: 60 | N120: 微信支付 | O120: 45619 | P120: 0.6871875 | Q120: 肖志强（工作号） | R120: 肖志强
B121: 系统订单 | C121: 万龙 | D121: 万龙 | E121: 4960 | F121: 万龙体验中心 | G121: 王 先生 | H121: 18618151709 | I121: 500 | J121: 380 | K121: 120 | L121: 0 | M121: 120 | N121: 微信支付 | O121: 45619 | P121: 0.7965162 | Q121: 修姜山（个人） | R121: 修姜山
B122: 系统订单 | C122: 万龙 | D122: 万龙 | E122: 4961 | F122: 万龙体验中心 | G122: 孙 先生 | H122: 13466365627 | I122: 3500 | J122: 3230 | K122: 270 | L122: 0 | M122: 270 | N122: 微信支付 | O122: 45619 | P122: 0.66791667 | Q122: 张小飞 | R122: 张小飞
B123: 系统订单 | C123: 万龙 | D123: 万龙 | E123: 4962 | F123: 万龙体验中心 | G123: 袁 先生 | H123: 13926153716 | I123: 2800 | J123: 2440 | K123: 360 | L123: 0 | M123: 360 | N123: 微信支付 | O123: 45619 | P123: 0.58991898 | Q123: 鲁延盼（个人） | R123: 鲁延盼
B124: 系统订单 | C124: 万龙 | D124: 万龙 | E124: 4963 | F124: 万龙体验中心 | G124: 吴 女士 | H124: 18322703739 | I124: 200 | J124: 200 | K124: 0 | L124: 0 | M124: 0 | N124: 微信支付 | O124: 45619 | P124: 0.51774306 | Q124: 鲁延盼（个人） | R124: 鲁延盼
... B130: 系统订单 | C130: 万龙 | D130: 万龙 | E130: 4971 | F130: 万龙体验中心 | G130: 沈 女士 | H130: 13522755246 | I130: 3000 | J130: 2870 | K130: 130 | L130: 0 | M130: 130 | N130: 微信支付 | O130: 45619 | P130: 0.66469907 | Q130: 王政（个人） | R130: 王政
B131: 系统订单 | C131: 万龙 | D131: 万龙 | E131: 4972 | F131: 万龙体验中心 | G131: 崔 女士 | H131: 15028333199 | I131: 1000 | J131: 880 | K131: 120 | L131: 0 | M131: 120 | N131: 微信支付 | O131: 45619 | P131: 0.57304398 | Q131: 肖志强（工作号） | R131: 肖志强 | S131: 61117
B132: 系统订单 | C132: 万龙 | D132: 万龙 | E132: 4973 | F132: 万龙体验中心 | G132: 毕 女士 | H132: 13264376996 | I132: 3000 | J132: 2820 | K132: 180 | L132: 0 | M132: 180 | N132: 微信支付 | O132: 45619 | P132: 0.68400463 | Q132: 许进升（个人） | R132: 许进升 | S132: 60147
B133: 系统订单 | C133: 万龙 | D133: 万龙 | E133: 4974 | F133: 万龙体验中心 | G133: 王 先生 | H133: 18511266606 | I133: 3000 | J133: 2490 | K133: 510 | L133: 0 | M133: 510 | N133: 微信支付 | O133: 45620 | P133: 0.65547454 | Q133: 肖志强（工作号） | R133: 肖志强 | S133: ==S131-S132 -> 970
B134: 系统订单 | C134: 万龙 | D134: 万龙 | E134: 4975 | F134: 万龙体验中心 | G134: 焦教练 先生 | H134: 18846049897 | I134: 200 | J134: 200 | K134: 0 | L134: 0 | M134: 0 | N134: 微信支付 | O134: 45619 | P134: 0.58065972 | Q134: 肖志强（工作号） | R134: 肖志强
B135: 系统订单 | C135: 万龙 | D135: 万龙 | E135: 4976 | F135: 万龙体验中心 | G135: 徐 先生 | H135: 13461035455 | I135: 5500 | J135: 5130 | K135: 370 | L135: 0 | M135: 370 | N135: 微信支付 | O135: 45619 | P135: 0.66722222 | Q135: 张小飞 | R135: 张小飞
B136: 系统订单 | C136: 万龙 | D136: 万龙 | E136: 4977 | F136: 万龙体验中心 | G136: 郭 先生 | H136: 13810355958 | I136: 1000 | J136: 880 | K136: 120 | L136: 0 | M136: 120 | N136: 微信支付 | O136: 45619 | P136: 0.70693287 | Q136: 肖志强（工作号） | R136: 肖志强
B137: 系统订单 | C137: 万龙 | D137: 万龙 | E137: 4978 | F137: 万龙体验中心 | G137: 高 先生 | H137: 17736520626 | I137: 1000 | J137: 920 | K137: 80 | L137: 0 | M137: 80 | N137: 微信支付 | O137: 45619 | P137: 0.6409375 | Q137: 肖志强（工作号） | R137: 肖志强
B138: 系统订单 | C138: 万龙 | D138: 万龙 | E138: 4979 | F138: 万龙体验中心 | G138: 张 女士 | H138: 13178258227 | I138: 200 | J138: 150 | K138: 50 | L138: 0 | M138: 50 | N138: 微信支付 | O138: 45619 | P138: 0.69318287 | Q138: 修姜山（个人） | R138: 修姜山
B139: 系统订单 | C139: 万龙 | D139: 万龙 | E139: 4980 | F139: 万龙体验中心 | G139: 叶 女士 | H139: 18813075146 | I139: 3000 | J139: 2260 | K139: 740 | L139: 0 | M139: 740 | O139: 45619 | P139: 0.74555556 | Q139: 张小飞（个人） | R139: 张小飞
B140: 系统订单 | C140: 万龙 | D140: 万龙 | E140: 4981 | F140: 万龙体验中心 | G140: 孙先生（个人） 先生 | H140: 13070943844 | I140: 7500 | J140: 6280 | K140: 1220 | L140: 0 | M140: 1220 | O140: 45620 | P140: 0.67061343 | Q140: 韩冬垚（个人） | R140: 韩冬垚
B141: 系统订单 | C141: 万龙 | D141: 万龙 | E141: 4982 | F141: 万龙体验中心 | G141: 赵 先生 | H141: 18611106799 | I141: 200 | J141: 200 | K141: 0 | L141: 0 | M141: 0 | O141: 45619 | P141: 0.70633102 | Q141: 张小飞（个人） | R141: 张小飞
B142: 系统订单 | C142: 万龙 | D142: 万龙 | E142: 4983 | F142: 万龙体验中心 | G142: 艾 先生 | H142: 18609288595 | I142: 5000 | J142: 5000 | K142: 0 | L142: 0 | M142: 0 | O142: 45619 | P142: 0.66722222 | Q142: 姜山（工作号） | R142: 修姜山
B143: 系统订单 | C143: 万龙 | D143: 万龙 | E143: 4985 | F143: 万龙体验中心 | G143: 李 先生 | H143: 18601018786 | I143: 5000 | J143: 5000 | K143: 0 | L143: 0 | M143: 0 | O143: 45619 | P143: 0.6727662 | Q143: 姜山（工作号） | R143: 修姜山
B144: 系统订单 | C144: 万龙 | D144: 万龙 | E144: 4986 | F144: 万龙体验中心 | G144: 姚 先生 | H144: 15643525257 | I144: 200 | J144: 140 | K144: 60 | L144: 0 | M144: 60 | O144: 45619 | P144: 0.68070602 | Q144: 肖志强（工作号） | R144: 肖志强
B145: 系统订单 | C145: 万龙 | D145: 万龙 | E145: 4987 | F145: 万龙体验中心 | G145: 霍 先生 | H145: 18731122388 | I145: 5000 | J145: 5000 | K145: 0 | L145: 0 | M145: 0 | O145: 45619 | P145: 0.67506944 | Q145: 姜山（工作号） | R145: 修姜山
B146: 系统订单 | C146: 万龙 | D146: 万龙 | E146: 4988 | F146: 万龙体验中心 | G146: 吴 先生 | H146: 18903468020 | I146: 5000 | J146: 5000 | K146: 0 | L146: 0 | M146: 0 | O146: 45619 | P146: 0.67627315 | Q146: 姜山（工作号） | R146: 修姜山
B147: 系统订单 | C147: 万龙 | D147: 万龙 | E147: 4989 | F147: 万龙体验中心 | G147: 黄 女士 | H147: 15810729266 | I147: 4000 | J147: 4000 | K147: 0 | L147: 0 | M147: 0 | O147: 45619 | P147: 0.67893519 | Q147: 姜山（工作号） | R147: 修姜山
B148: 系统订单 | C148: 万龙 | D148: 万龙 | E148: 4991 | F148: 万龙体验中心 | G148: 杜 女士 | H148: 13146887342 | I148: 50 | J148: 0 | K148: 50 | L148: 0 | M148: 50 | O148: 45619 | P148: 0.6803588 | Q148: 张小飞（个人） | R148: 张小飞
B149: 系统订单 | C149: 万龙 | D149: 万龙 | E149: 4992 | F149: 万龙体验中心 | G149: 肖志强（个人） 先生 | H149: 18612317853 | I149: 360 | J149: 0 | K149: 360 | L149: 0 | M149: 360 | O149: 45619 | P149: 0.68451389 | Q149: 肖志强（工作号） | R149: 肖志强
B150: 系统订单 | C150: 万龙 | D150: 万龙 | E150: 4993 | F150: 万龙体验中心 | G150: 温 先生 | H150: 15169646310 | I150: 1000 | J150: 890 | K150: 110 | L150: 0 | M150: 110 | O150: 45619 | P150: 0.8800463 | Q150: 肖志强（工作号） | R150: 肖志强
... B284: 系统订单 | C284: 万龙 | D284: 万龙 | E284: 5171 | F284: 万龙体验中心 | G284: 李 女士 | H284: 13401001422 | I284: 500 | J284: 451 | K284: 49 | L284: 0 | M284: 49 | O284: 45626 | P284: 0.908125 | Q284: 肖志强（工作号） | R284: 肖志强
B285: 系统订单 | D285: 万龙 | E285: 5068 | F285: 万龙体验中心 | G285: 周 先生 | H285: 15501006090 | I285: 1000 | J285: 720 | K285: 280 | L285: 0 | M285: 280 | O285: 45627 | P285: 0.48274306 | Q285: 肖志强（工作号） | R285: 肖志强
B286: 系统订单 | D286: 万龙 | E286: 5086 | F286: 万龙体验中心 | G286: 连 先生 | H286: 17717396484 | I286: 1000 | J286: 760 | K286: 240 | L286: 0 | M286: 240 | O286: 45627 | P286: 0.5987037 | Q286: 张小飞（个人） | R286: 张小飞
B287: 系统订单 | D287: 万龙 | E287: 5088 | F287: 万龙体验中心 | G287: 高 先生 | H287: 18630188684 | I287: 2000 | J287: 1900 | K287: 100 | L287: 0 | M287: 100 | O287: 45627 | P287: 0.70320602 | Q287: 姜山（工作号） | R287: 修姜山
B288: 系统订单 | D288: 万龙 | E288: 5090 | F288: 万龙体验中心 | G288: 高 先生 | H288: 18510001992 | I288: 5000 | J288: 4640 | K288: 360 | L288: 0 | M288: 360 | O288: 45627 | P288: 0.61847222 | Q288: 王政 | R288: 王政
B289: 系统订单 | D289: 万龙 | E289: 5091 | F289: 万龙体验中心 | G289: 马 女士 | H289: 18512498630 | I289: 5000 | J289: 4640 | K289: 360 | L289: 0 | M289: 360 | O289: 45627 | P289: 0.61888889 | Q289: 王政 | R289: 王政
B290: 系统订单 | D290: 万龙 | E290: 5092 | F290: 万龙体验中心 | G290: 宋 女士 | H290: 18616261763 | I290: 15000 | J290: 13920 | K290: 1080 | L290: 0 | M290: 1080 | O290: 45627 | P290: 0.62002315 | Q290: 王政 | R290: 王政
B291: 系统订单 | D291: 万龙 | E291: 5108 | F291: 万龙体验中心 | G291: 曹 女士 | H291: 18810916935 | I291: 5000 | J291: 4120 | K291: 880 | L291: 0 | M291: 880 | O291: 45628 | P291: 0.67005787 | Q291: 肖志强（工作号） | R291: 肖志强
B292: 系统订单 | D292: 万龙 | E292: 5113 | F292: 万龙体验中心 | G292: 李 先生 | H292: 18600200943 | I292: 3000 | J292: 2570 | K292: 430 | L292: 0 | M292: 430 | O292: 45627 | P292: 0.67395833 | Q292: 肖志强（工作号） | R292: 肖志强
B293: 系统订单 | D293: 万龙 | E293: 5120 | F293: 万龙体验中心 | G293: 韦 女士 | H293: 13915962710 | I293: 6000 | J293: 4990 | K293: 1010 | L293: 0 | M293: 1010 | O293: 45627 | P293: 0.67260417 | Q293: 张小飞（个人） | R293: 张小飞
B294: 系统订单 | D294: 万龙 | E294: 5131 | F294: 万龙体验中心 | G294: 林 先生 | H294: 18500648167 | I294: 300 | J294: 200 | K294: 100 | L294: 0 | M294: 100 | O294: 45627 | P294: 0.64608796 | Q294: 张小飞（个人） | R294: 张小飞
B295: 系统订单 | D295: 万龙 | E295: 5133 | F295: 万龙体验中心 | G295: 曲 女士 | H295: 18704456257 | I295: 500 | J295: 360 | K295: 140 | L295: 0 | M295: 140 | O295: 45627 | P295: 0.6065625 | Q295: 张小飞（个人） | R295: 张小飞
B296: 系统订单 | D296: 万龙 | E296: 5141 | F296: 万龙体验中心 | G296: 钱 先生 | H296: 18921352899 | I296: 500 | J296: 370 | K296: 130 | L296: 0 | M296: 130 | O296: 45627 | P296: 0.56085648 | Q296: 白雪景（工作号） | R296: 白雪景
... B1623: 系统订单 | D1623: 万龙 | E1623: 8125 | F1623: 万龙体验中心 | G1623: 肖 先生 | H1623: 16619854041 | I1623: 1500 | J1623: 1350 | K1623: 150 | L1623: 0 | M1623: 150 | O1623: 45689 | P1623: 0.89840278 | Q1623: 肖志强（工作号） | R1623: 肖志强
B1624: 系统订单 | D1624: 万龙 | E1624: 8070 | F1624: 万龙体验中心 | H1624: 16631122389 | I1624: 2000 | J1624: 1870 | K1624: 130 | L1624: 0 | M1624: 130 | O1624: 45689 | P1624: 0.71347222 | Q1624: 张小飞 | R1624: 张小飞
B1625: 系统订单 | D1625: 万龙 | E1625: 8091 | F1625: 万龙体验中心 | G1625: 刘 女士 | H1625: 15001058795 | I1625: 3000 | J1625: 2770 | K1625: 230 | L1625: 0 | M1625: 230 | O1625: 45689 | P1625: 0.69725694 | Q1625: 肖志强（工作号） | R1625: 肖志强
B1626: 系统订单 | D1626: 万龙 | E1626: 8071 | F1626: 万龙体验中心 | G1626: 王 先生 | H1626: 13811320137 | I1626: 300 | J1626: 250 | K1626: 50 | L1626: 0 | M1626: 50 | O1626: 45689 | P1626: 0.7159375 | Q1626: 张小飞 | R1626: 张小飞
B1627: 系统订单 | D1627: 万龙 | E1627: 8111 | F1627: 万龙体验中心 | G1627: 时 先生 | H1627: 18647064000 | I1627: 5000 | J1627: 4770 | K1627: 230 | L1627: 0 | M1627: 230 | O1627: 45689 | P1627: 0.7006713 | Q1627: 王政 | R1627: 王政
B1628: 系统订单 | D1628: 万龙 | E1628: 8088 | F1628: 万龙体验中心 | G1628: 杨 先生 | H1628: 15932360376 | I1628: 200 | J1628: 135 | K1628: 65 | L1628: 0 | M1628: 65 | O1628: 45689 | P1628: 0.74210648 | Q1628: 肖志强（工作号） | R1628: 肖志强
B1629: 系统订单 | D1629: 万龙 | E1629: 8094 | F1629: 万龙体验中心 | G1629: 宋 先生 | H1629: 13601198897 | I1629: 3000 | J1629: 2830 | K1629: 170 | L1629: 0 | M1629: 170 | O1629: 45689 | P1629: 0.67905093 | Q1629: 肖志强（工作号） | R1629: 肖志强
B1630: 系统订单 | D1630: 万龙 | E1630: 8048 | F1630: 万龙体验中心 | G1630: 贺 先生 | H1630: 13717871592 | I1630: 11500 | J1630: 9400 | K1630: 2100 | L1630: 0 | M1630: 2100 | O1630: 45689 | P1630: 0.54936343 | Q1630: 张小飞 | R1630: 张小飞
B1631: 系统订单 | D1631: 万龙 | E1631: 8112 | F1631: 万龙体验中心 | G1631: 凯 先生 | H1631: 18611667889 | I1631: 5000 | J1631: 5000 | K1631: 0 | L1631: 0 | M1631: 0 | O1631: 45689 | P1631: 0.68211806 | Q1631: 韩冬垚(工作) | R1631: 韩冬垚
B1632: 系统订单 | D1632: 万龙 | E1632: 8069 | F1632: 万龙体验中心 | G1632: 张 先生 | H1632: 13612006548 | I1632: 200 | J1632: 120 | K1632: 80 | L1632: 0 | M1632: 80 | O1632: 45689 | P1632: 0.53826389 | Q1632: 张小飞 | R1632: 张小飞
B1633: 系统订单 | D1633: 万龙 | E1633: 8123 | F1633: 万龙体验中心 | G1633: 宋 女士 | H1633: 13521444416 | I1633: 6000 | J1633: 5580 | K1633: 420 | L1633: 0 | M1633: 420 | O1633: 45689 | P1633: 0.91024306 | Q1633: 肖志强（工作号） | R1633: 肖志强
B1634: 系统订单 | D1634: 万龙 | E1634: 7860 | F1634: 万龙体验中心 | G1634: 王 先生 | H1634: 18001305771 | I1634: 10000 | J1634: 5320 | K1634: 4680 | L1634: 0 | M1634: 4680 | O1634: 45689 | P1634: 0.6402662 | Q1634: 张亮 | R1634: 张亮
B1635: 系统订单 | D1635: 万龙 | E1635: 8066 | F1635: 万龙体验中心 | G1635: 于 女士 | H1635: 18205193176 | I1635: 3000 | J1635: 2770 | K1635: 230 | L1635: 0 | M1635: 230 | O1635: 45689 | P1635: 0.71936343 | Q1635: 肖志强（工作号） | R1635: 肖志强
B1636: 系统订单 | D1636: 万龙 | E1636: 8181 | F1636: 万龙体验中心 | G1636: 贾 女士 | H1636: 18931217880 | I1636: 6200 | J1636: 5700 | K1636: 500 | L1636: 0 | M1636: 500 | O1636: 45690 | P1636: 0.87336806 | Q1636: 张凯（工作） | R1636: 张凯
... B1694: 系统订单 | D1694: 万龙 | E1694: 8246 | F1694: 万龙体验中心 | G1694: 李 先生 | H1694: 13801285361 | I1694: 5000 | J1694: 4650 | K1694: 350 | L1694: 0 | M1694: 350 | O1694: 45692 | P1694: 0.70292824 | Q1694: 肖志强（工作号） | R1694: 肖志强
B1695: 系统订单 | D1695: 万龙 | E1695: 8017 | F1695: 万龙体验中心 | H1695: 13728868717 | I1695: 3000 | J1695: 1560 | K1695: 1440 | L1695: 0 | M1695: 1440 | O1695: 45692 | P1695: 0.76125 | Q1695: 肖志强（工作号） | R1695: 肖志强
B1696: 系统订单 | D1696: 万龙 | E1696: 8241 | F1696: 万龙体验中心 | G1696: 杨 先生 | H1696: 18600233577 | I1696: 1000 | J1696: 840 | K1696: 160 | L1696: 0 | M1696: 160 | O1696: 45692 | P1696: 0.60310185 | Q1696: 张小飞 | R1696: 张小飞
B1697: 系统订单 | D1697: 万龙 | E1697: 8126 | F1697: 万龙体验中心 | G1697: 孙先生（个人） 先生 | H1697: 13070943844 | I1697: 5000 | J1697: 4810 | K1697: 190 | L1697: 0 | M1697: 190 | O1697: 45692 | P1697: 0.9300463 | Q1697: 韩冬垚 | R1697: 韩冬垚
B1698: 系统订单 | D1698: 万龙 | E1698: 8212 | F1698: 万龙体验中心 | G1698: 王 先生 | H1698: 13520331723 | I1698: 3000 | J1698: 2660 | K1698: 340 | L1698: 0 | M1698: 340 | O1698: 45692 | P1698: 0.47033565 | Q1698: 肖志强（工作号） | R1698: 肖志强
B1699: 系统订单 | D1699: 万龙 | E1699: 8232 | F1699: 万龙体验中心 | G1699: 秦 先生 | H1699: 18801073911 | I1699: 3000 | J1699: 2480 | K1699: 520 | L1699: 0 | M1699: 520 | O1699: 45692 | P1699: 0.56238426 | Q1699: 张小飞 | R1699: 张小飞
B1700: 系统订单 | D1700: 万龙 | E1700: 8132 | F1700: 万龙体验中心 | G1700: 任 先生 | H1700: 18647220720 | I1700: 5000 | J1700: 3950 | K1700: 1050 | L1700: 0 | M1700: 1050 | O1700: 45692 | P1700: 0.5231713 | Q1700: 张小飞 | R1700: 张小飞
B1701: 系统订单 | D1701: 万龙 | E1701: 8273 | F1701: 万龙体验中心 | G1701: 张 女士 | H1701: 13730661859 | I1701: 2000 | J1701: 1900 | K1701: 100 | L1701: 0 | M1701: 100 | O1701: 45693 | P1701: 0.64356481 | Q1701: 张小飞 | R1701: 张小飞
B1702: 系统订单 | D1702: 万龙 | E1702: 8267 | F1702: 万龙体验中心 | G1702: 孙 先生 | H1702: 13910721823 | I1702: 3000 | J1702: 2820 | K1702: 180 | L1702: 0 | M1702: 180 | O1702: 45693 | P1702: 0.67793981 | Q1702: 张小飞 | R1702: 张小飞
B1703: 系统订单 | D1703: 万龙 | E1703: 8207 | F1703: 万龙体验中心 | G1703: 张 先生 | H1703: 15120001280 | I1703: 3000 | J1703: 2380 | K1703: 620 | L1703: 0 | M1703: 620 | O1703: 45693 | P1703: 0.49524306 | Q1703: 肖志强（工作号） | R1703: 肖志强
B1704: 系统订单 | D1704: 万龙 | E1704: 8138 | F1704: 万龙体验中心 | G1704: 李天乐 先生 | H1704: 18310006347 | I1704: 6000 | J1704: 4100 | K1704: 1900 | L1704: 0 | M1704: 1900 | O1704: 45693 | P1704: 0.67414352 | Q1704: 张小飞 | R1704: 张小飞
B1705: 系统订单 | D1705: 万龙 | E1705: 8270 | F1705: 万龙体验中心 | G1705: 黄 先生 | H1705: 13888737544 | I1705: 800 | J1705: 570 | K1705: 230 | L1705: 0 | M1705: 230 | O1705: 45693 | P1705: 0.74594907 | Q1705: 张小飞 | R1705: 张小飞
B1706: 系统订单 | D1706: 万龙 | E1706: 8264 | F1706: 万龙体验中心 | G1706: 初 女士 | H1706: 13910009420 | I1706: 3000 | J1706: 2820 | K1706: 180 | L1706: 0 | M1706: 180 | O1706: 45693 | P1706: 0.64383102 | Q1706: 肖志强（工作号） | R1706: 肖志强
B1707: 系统订单 | D1707: 万龙 | E1707: 8268 | F1707: 万龙体验中心 | G1707: 何 先生 | H1707: 18610817930 | I1707: 3000 | J1707: 2800 | K1707: 200 | L1707: 0 | M1707: 200 | O1707: 45693 | P1707: 0.67996528 | Q1707: 张小飞 | R1707: 张小飞
... B1749: 系统订单 | D1749: 万龙 | E1749: 8332 | F1749: 万龙体验中心 | G1749: 吴 先生 | H1749: 13681550852 | I1749: 5000 | J1749: 4780 | K1749: 220 | L1749: 0 | M1749: 220 | O1749: 45696 | P1749: 0.71158565 | Q1749: 张亮 | R1749: 张亮
B1750: 系统订单 | D1750: 万龙 | E1750: 8396 | F1750: 万龙体验中心 | H1750: 13564367737 | I1750: 5000 | J1750: 4740 | K1750: 260 | L1750: 0 | M1750: 260 | O1750: 45697 | P1750: 0.86274306 | Q1750: 张小飞 | R1750: 张小飞
B1751: 系统订单 | D1751: 万龙 | E1751: 8350 | F1751: 万龙体验中心 | G1751: 蓝 先生 | H1751: 18610097557 | I1751: 5000 | J1751: 4630 | K1751: 370 | L1751: 0 | M1751: 370 | O1751: 45697 | P1751: 0.7074537 | Q1751: 王政 | R1751: 王政
B1752: 系统订单 | D1752: 万龙 | E1752: 8310 | F1752: 万龙体验中心 | G1752: 郑 先生 | H1752: 15859273696 | I1752: 5000 | J1752: 3800 | K1752: 1200 | L1752: 0 | M1752: 1200 | O1752: 45697 | P1752: 0.70643519 | Q1752: 肖志强（工作号） | R1752: 肖志强
B1753: 系统订单 | D1753: 万龙 | E1753: 8316 | F1753: 万龙体验中心 | G1753: 林 先生 | H1753: 18750260539 | I1753: 4000 | J1753: 3100 | K1753: 900 | L1753: 0 | M1753: 900 | O1753: 45697 | P1753: 0.69886574 | Q1753: 张小飞 | R1753: 张小飞
B1754: 系统订单 | D1754: 万龙 | E1754: 8347 | F1754: 万龙体验中心 | G1754: 刘 先生 | H1754: 15844022230 | I1754: 3000 | J1754: 2850 | K1754: 150 | L1754: 0 | M1754: 150 | O1754: 45697 | P1754: 0.65554398 | Q1754: 张小飞 | R1754: 张小飞
B1755: 系统订单 | D1755: 万龙 | E1755: 8370 | F1755: 万龙体验中心 | G1755: 李 女士 | H1755: 18633767345 | I1755: 3000 | J1755: 2640 | K1755: 360 | L1755: 0 | M1755: 360 | O1755: 45697 | P1755: 0.67195602 | Q1755: 张小飞 | R1755: 张小飞
B1756: 系统订单 | D1756: 万龙 | E1756: 8348 | F1756: 万龙体验中心 | G1756: 吴 先生 | H1756: 13681550852 | I1756: 5000 | J1756: 4820 | K1756: 180 | L1756: 0 | M1756: 180 | O1756: 45697 | P1756: 0.69517361 | Q1756: 王政 | R1756: 王政
B1757: 系统订单 | D1757: 万龙 | E1757: 8302 | F1757: 万龙体验中心 | G1757: 先生 | H1757: 13922836379 | I1757: 5000 | J1757: 4200 | K1757: 800 | L1757: 0 | M1757: 800 | O1757: 45697 | P1757: 0.65974537 | Q1757: 王政 | R1757: 王政
...

Sheet 旗舰租赁
A1: 订单ID | B1: 门店 | C1: 姓名 | D1: 电话 | E1: 押金 | F1: 退款 | G1: 结余 | H1: 损坏赔偿 | I1: 租金 | J1: 支付方式 | K1: 日期 | L1: 时间 | M1: 接待
A2: 4831 | B2: 崇礼旗舰店 | C2: 段 先生 | D2: 18614055589 | E2: 3000 | F2: 2840 | G2: 160 | H2: 0 | I2: 160 | J2: 微信支付 | K2: 45613 | L2: 0.8084838 | M2: 崔洋（个人）
A3: 5350 | B3: 崇礼旗舰店 | C3: 徐 先生 | D3: 15198919768 | E3: 400 | F3: 320 | G3: 80 | H3: 0 | I3: 80 | K3: 45634 | L3: 0.58872685 | M3: 姜山（工作号）
A4: 5397 | B4: 崇礼旗舰店 | C4: 张 先生 | D4: 18611380822 | E4: 3000 | F4: 2700 | G4: 300 | H4: 0 | I4: 300 | K4: 45637 | L4: 0.50078704 | M4: 白雪景（工作号）
A5: 5417 | B5: 崇礼旗舰店 | C5: 崔 先生 | D5: 13357737705 | E5: 6000 | F5: 4900 | G5: 1100 | H5: 0 | I5: 1100 | K5: 45646 | L5: 0.71668981 | M5: 肖志强（工作号）
A6: 5436 | B6: 崇礼旗舰店 | C6: 李哥 先生 | D6: 13581616818 | E6: 3000 | F6: 3000 | G6: 0 | H6: 0 | I6: 0 | K6: 45637 | L6: 0.48346065 | M6: 姜山（工作号）
A7: 5454 | B7: 崇礼旗舰店 | C7: 魏 先生 | D7: 13323031637 | E7: 2500 | F7: 2150 | G7: 350 | H7: 0 | I7: 350 | K7: 45642 | L7: 0.4124537 | M7: 姜山（工作号）
A8: 5701 | B8: 崇礼旗舰店 | C8: 胡 先生 | D8: 15001229880 | E8: 2000 | F8: 1760 | G8: 240 | H8: 0 | I8: 240 | K8: 45648 | L8: 0.71395833 | M8: 肖志强（工作号）
A9: 5705 | B9: 崇礼旗舰店 | C9: 曹 女士 | D9: 13811145027 | E9: 12000 | F9: 11540 | G9: 460 | H9: 0 | I9: 460 | K9: 45648 | L9: 0.77423611 | M9: 姜山（工作号）
A10: 5707 | B10: 崇礼旗舰店 | C10: 王一顺 先生 | D10: 18001263600 | E10: 3780 | F10: 0 | G10: 3780 | H10: 0 | I10: 3780 | K10: 45650 | L10: 0.46759259 | M10: 姜山（工作号）
A11: 5774 | B11: 崇礼旗舰店 | C11: 于洋 先生 | D11: 15810752278 | E11: 3000 | F11: 2900 | G11: 100 | H11: 0 | I11: 100 | K11: 45648 | L11: 0.53292824 | M11: 姜山（工作号）
A12: 5783 | B12: 崇礼旗舰店 | C12: 杨 先生 | D12: 13002386145 | E12: 5000 | F12: 3650 | G12: 1350 | H12: 0 | I12: 1350 | K12: 45656 | L12: 0.59790509 | M12: 姜山（工作号）
A13: 5965 | B13: 崇礼旗舰店 | C13: 王 女士 | D13: 13810103141 | E13: 8000 | F13: 7700 | G13: 300 | H13: 0 | I13: 300 | K13: 45654 | L13: 0.69934028 | M13: 姜山（工作号）
A14: 6021 | B14: 崇礼旗舰店 | C14: 张 先生 | D14: 13161872447 | E14: 1000 | F14: 0 | G14: 1000 | H14: 0 | I14: 900 | J14: 现金 | K14: 45658 | L14: 0.67986111 | M14: 崔洋（个人）
A15: 6037 | B15: 崇礼旗舰店 | C15: 张浩 先生 | D15: 13663235345 | E15: 3000 | F15: 2250 | G15: 750 | H15: 0 | I15: 750 | K15: 45659 | L15: 0.78086806 | M15: 姜山（工作号）
A16: 6102 | B16: 崇礼旗舰店 | C16: 王 先生 | D16: 18518021266 | E16: 4500 | F16: 4350 | G16: 150 | H16: 0 | I16: 150 | K16: 45656 | L16: 0.59400463 | M16: 张凯
A17: 6103 | B17: 崇礼旗舰店 | C17: 郭 女士 | D17: 18666290357 | E17: 9000 | F17: 8460 | G17: 540 | H17: 0 | I17: 540 | K17: 45658 | L17: 0.36126157 | M17: 崔洋（个人）
A18: 6131 | B18: 崇礼旗舰店 | C18: 赵 女士 | D18: 18618237080 | E18: 3000 | F18: 2800 | G18: 200 | H18: 0 | I18: 200 | K18: 45658 | L18: 0.54975694 | M18: 韩冬垚
A19: 6155 | B19: 崇礼旗舰店 | C19: 张浩 先生 | D19: 13663235345 | E19: 3000 | F19: 2400 | G19: 600 | H19: 0 | I19: 600 | K19: 45661 | L19: 0.83329861 | M19: 姜山（工作号）
A20: 6176 | B20: 崇礼旗舰店 | C20: 丁丁 女士 | D20: 15921485281 | E20: 5000 | F20: 4400 | G20: 600 | H20: 0 | I20: 600 | K20: 45661 | L20: 0.87024306 | M20: 姜山（工作号）
A21: 6177 | B21: 崇礼旗舰店 | C21: 陈 女士 | D21: 13524724162 | E21: 3000 | F21: 2820 | G21: 180 | H21: 0 | I21: 180 | K21: 45661 | L21: 0.87135417 | M21: 姜山（工作号）
A22: 6191 | B22: 崇礼旗舰店 | C22: 王 先生 | D22: 18519119280 | E22: 5000 | F22: 4700 | G22: 300 | H22: 0 | I22: 300 | K22: 45662 | L22: 0.69733796 | M22: 姜山（工作号）
A23: 6212 | B23: 崇礼旗舰店 | C23: 刘 先生 | D23: 18611616181 | E23: 3000 | F23: 2740 | G23: 260 | H23: 0 | I23: 260 | K23: 45662 | L23: 0.63516204 | M23: 姜山（工作号）
A24: 6214 | B24: 崇礼旗舰店 | C24: 张 先生 | D24: 15647775777 | E24: 6000 | F24: 5760 | G24: 240 | H24: 0 | I24: 240 | K24: 45664 | L24: 0.41541667 | M24: 姜山（工作号）
A25: 6225 | B25: 崇礼旗舰店 | C25: 孙 先生 | D25: 15602131444 | E25: 4000 | F25: 3600 | G25: 400 | H25: 0 | I25: 400 | K25: 45662 | L25: 0.71466435 | M25: 张凯（工作）
A26: 6345 | B26: 崇礼旗舰店 | C26: 张 女士 | D26: 18734136185 | E26: 5200 | F26: 4920 | G26: 280 | H26: 0 | I26: 280 | K26: 45663 | L26: 0.72829861 | M26: 姜山（工作号）
... A61: 8028 | B61: 崇礼旗舰店 | C61: 王 先生 | D61: 13910814974 | E61: 11000 | F61: 10620 | G61: 380 | H61: 0 | I61: 380 | K61: 45688 | L61: 0.75177083 | M61: 姜山（工作号）

Sheet 南山租赁
A1: 订单ID | B1: 门店 | C1: 姓名 | D1: 电话 | E1: 押金 | F1: 退款 | G1: 结余 | H1: 损坏赔偿 | I1: 租金 | J1: 支付方式 | K1: 日期 | L1: 时间 | M1: 接待
A2: 5466 | B2: 南山 | C2: 王 女士 | D2: 18500557654 | E2: 300 | F2: 220 | G2: 80 | H2: 0 | I2: 80 | K2: 45638 | L2: 0.91570602 | M2: 孙亚先（个人）
A3: 5500 | B3: 南山 | C3: 杨 女士 | D3: 13801234117 | E3: 5000 | F3: 4850 | G3: 150 | H3: 0 | I3: 75 | K3: 45640 | L3: 0.69530093 | M3: 张新健
A4: 5532 | B4: 南山 | C4: 阮 女士 | D4: 18612441206 | E4: 300 | F4: 250 | G4: 50 | H4: 0 | I4: 50 | K4: 45640 | L4: 0.68665509 | M4: 孙亚先（个人）
A5: 5583 | B5: 南山 | C5: 李 女士 | D5: 18810793067 | E5: 300 | F5: 240 | G5: 60 | H5: 0 | I5: 30 | K5: 45641 | L5: 0.86107639 | M5: 孙亚先（个人）
A6: 5596 | B6: 南山 | C6: 先生 | D6: 13621077659 | E6: 3000 | F6: 2800 | G6: 200 | H6: 0 | I6: 200 | K6: 45641 | L6: 0.72863426 | M6: 孙亚先（个人）
A7: 5630 | B7: 南山 | C7: 刘 先生 | D7: 18519890880 | E7: 200 | F7: 170 | G7: 30 | H7: 0 | I7: 30 | K7: 45642 | L7: 0.89711806 | M7: 孙亚先（个人）
A8: 5675 | B8: 南山 | C8: 张 先生 | D8: 13911461009 | E8: 600 | F8: 450 | G8: 150 | H8: 0 | I8: 75 | K8: 45645 | L8: 0.68017361 | M8: 孙亚先（个人）
A9: 5703 | B9: 南山 | C9: 1 先生 | D9: 13581809847 | E9: 200 | F9: 170 | G9: 30 | H9: 0 | I9: 30 | K9: 45646 | L9: 0.89909722 | M9: 孙亚先（个人）
A10: 5739 | B10: 南山 | C10: 张 女士 | D10: 13810852246 | E10: 1000 | F10: 880 | G10: 120 | H10: 0 | I10: 120 | K10: 45647 | L10: 0.73878472 | M10: 孙亚先（个人）
A11: 5785 | B11: 南山 | C11: 刘 先生 | D11: 13910524531 | E11: 5000 | F11: 4600 | G11: 400 | H11: 0 | I11: 400 | K11: 45647 | L11: 0.92333333 | M11: 孙亚先（个人）
A12: 5788 | B12: 南山 | C12: 王倩 女士 | D12: 18228644679 | E12: 30 | F12: 0 | G12: 30 | H12: 0 | I12: 30 | K12: 45647 | L12: 0.83635417 | M12: 孙亚先（个人）
A13: 5802 | B13: 南山 | C13: 胡 先生 | D13: 15160025952 | E13: 200 | F13: 160 | G13: 40 | H13: 0 | I13: 40 | K13: 45648 | L13: 0.57892361 | M13: 张新健
... A39: 6154 | B39: 南山 | C39: 蔡 先生 | D39: 13860718782 | E39: 6000 | F39: 5720 | G39: 280 | H39: 0 | I39: 280 | K39: 45657 | L39: 0.83783565 | M39: 张新健
A40: 5881 | B40: 南山 | C40: 王 女士 | D40: 15268360035 | E40: 80 | F40: 0 | G40: 80 | H40: 0 | I40: 80 | K40: 45673 | L40: 0.66427083 | M40: 王倩 | N40: 此订单租金为80
A41: 6167 | B41: 南山 | C41: 王 先生 | D41: 13811598328 | E41: 5000 | F41: 5000 | G41: 0 | H41: 0 | I41: 0 | K41: 45658 | L41: 0.58311343 | M41: 张新健
A42: 6175 | B42: 南山 | C42: 孔 先生 | D42: 15697842637 | E42: 3000 | F42: 2760 | G42: 240 | H42: 0 | I42: 240 | K42: 45658 | L42: 0.92145833 | M42: 孙亚先（个人）
A43: 6188 | B43: 南山 | C43: 邓 女士 | D43: 15652093999 | E43: 3000 | F43: 2880 | G43: 120 | H43: 0 | I43: 120 | K43: 45659 | L43: 0.90428241 | M43: 王倩
A44: 6246 | B44: 南山 | C44: 赵旻鹏 先生 | D44: 13821177163 | E44: 2000 | F44: 1880 | G44: 120 | H44: 0 | I44: 120 | K44: 45661 | L44: 0.71747685 | M44: 张新健
A45: 6249 | B45: 南山 | C45: 赵 先生 | D45: 18210238697 | E45: 600 | F45: 520 | G45: 80 | H45: 0 | I45: 80 | K45: 45661 | L45: 0.64953704 | M45: 孙亚先（个人）
A46: 6271 | B46: 南山 | C46: 俞 先生 | D46: 13701681552 | E46: 10000 | F46: 9540 | G46: 460 | H46: 0 | I46: 460 | K46: 45661 | L46: 0.87943287 | M46: 张新健
A47: 6287 | B47: 南山 | C47: 杨 先生 | D47: 15100678165 | E47: 7000 | F47: 6440 | G47: 560 | H47: 0 | I47: 560 | K47: 45661 | L47: 0.87818287 | M47: 孙亚先（个人）
A48: 6316 | B48: 南山 | C48: 邱 女士 | D48: 18552254527 | E48: 3000 | F48: 2880 | G48: 120 | H48: 0 | I48: 120 | K48: 45662 | L48: 0.72413194 | M48: 孙亚先（个人）
A49: 6337 | B49: 南山 | C49: 叶 女士 | D49: 15077408044 | E49: 3000 | F49: 2880 | G49: 120 | H49: 0 | I49: 120 | K49: 45662 | L49: 0.62234954 | M49: 孙亚先（个人）
A50: 6369 | B50: 南山 | C50: 徐 先生 | D50: 18101254910 | E50: 600 | F50: 520 | G50: 80 | H50: 0 | I50: 80 | K50: 45664 | L50: 0.7047338 | M50: 孙亚先（个人）
A51: 6377 | B51: 南山 | C51: 徐 先生 | D51: 17600834429 | E51: 200 | F51: 170 | G51: 30 | H51: 0 | I51: 30 | K51: 45664 | L51: 0.71868056 | M51: 张新健
A52: 6393 | B52: 南山 | C52: 关 先生 | D52: 13121928108 | E52: 121 | F52: 1 | G52: 120 | H52: 0 | I52: 120 | K52: 45665 | L52: 0.67960648 | M52: 张新健
... A82: 6612 | B82: 南山 | C82: 赵 先生 | D82: 13701256865 | E82: 5000 | F82: 4850 | G82: 150 | H82: 0 | I82: 150 | K82: 45673 | L82: 0.62446759 | M82: 张新健
A83: 6616 | B83: 南山 | C83: 张新健 先生 | D83: 18612472341 | E83: 460 | F83: 0 | G83: 460 | H83: 0 | I83: 460 | J83: 现金 | K83: 45673 | L83: 0.48877315 | M83: 张新健
A84: 6620 | B84: 南山 | C84: 李 女士 | D84: 19818321219 | E84: 300 | F84: 260 | G84: 40 | H84: 0 | I84: 40 | K84: 45673 | L84: 0.8696875 | M84: 孙亚先（个人）
A85: 6621 | B85: 南山 | C85: 安 女士 | D85: 13329363952 | E85: 1000 | F85: 900 | G85: 100 | H85: 0 | I85: 100 | K85: 45673 | L85: 0.93425926 | M85: 孙亚先（个人）
A86: 6629 | B86: 南山 | C86: 杨 女士 | D86: 18604886880 | E86: 8000 | F86: 7630 | G86: 370 | H86: 0 | I86: 370 | K86: 45674 | L86: 0.70803241 | M86: 张新健
A87: 6630 | B87: 南山 | C87: 罗 女士 | D87: 18179143711 | E87: 3000 | F87: 2920 | G87: 80 | H87: 0 | I87: 80 | K87: 45682 | L87: 0.56457176 | M87: 张新健
A88: 6641 | B88: 南山 | C88: 俞 先生 | D88: 13701681552 | E88: 3000 | F88: 2470 | G88: 530 | H88: 0 | I88: 530 | K88: 45674 | L88: 0.89797454 | M88: 孙亚先（个人）
A89: 6648 | B89: 南山 | C89: 王倩 女士 | D89: 18228644679 | E89: 121 | F89: 1 | G89: 120 | H89: 0 | I89: 120 | K89: 45674 | L89: 0.93800926 | M89: 王倩
A90: 6685 | B90: 南山 | C90: 杨 女士 | D90: 18301069131 | E90: 500 | F90: 380 | G90: 120 | H90: 0 | I90: 120 | K90: 45675 | L90: 0.59622685 | M90: 王倩
A91: 6688 | B91: 南山 | C91: 刘 先生 | D91: 18249100567 | E91: 5000 | F91: 4850 | G91: 150 | H91: 0 | I91: 150 | K91: 45675 | L91: 0.92549769 | M91: 张新健
A92: 6694 | B92: 南山 | C92: 俞 先生 | D92: 13701681552 | E92: 2000 | F92: 1700 | G92: 300 | H92: 0 | I92: 300 | K92: 45675 | L92: 0.70971065 | M92: 孙亚先（个人）
A93: 6698 | B93: 南山 | C93: 李 先生 | D93: 15831600748 | E93: 200 | F93: 170 | G93: 30 | H93: 0 | I93: 30 | K93: 45675 | L93: 0.66015046 | M93: 张新健
A94: 6704 | B94: 南山 | C94: 刘梓宸 先生 | D94: 15901371387 | E94: 201 | F94: 1 | G94: 200 | H94: 0 | I94: 200 | K94: 45675 | L94: 0.74517361 | M94: 张新健
A95: 6708 | B95: 南山 | C95: 陈 先生 | D95: 15076920055 | E95: 5000 | F95: 4900 | G95: 100 | H95: 0 | I95: 100 | K95: 45675 | L95: 0.92434028 | M95: 张新健
... A121: 7883 | B121: 南山 | C121: 陈 女士 | D121: 13750830785 | E121: 5000 | F121: 4650 | G121: 350 | H121: 0 | I121: 350 | K121: 45682 | L121: 0.72986111 | M121: 张新健
A122: 7897 | B122: 南山 | D122: 18810505022 | E122: 50 | F122: 40 | G122: 10 | H122: 0 | I122: 10 | K122: 45682 | L122: 0.8684838 | M122: 孙亚先（个人）
A123: 7902 | B123: 南山 | C123: 谢 先生 | D123: 13811981446 | E123: 1000 | F123: 850 | G123: 150 | H123: 0 | I123: 150 | K123: 45682 | L123: 0.6994213 | M123: 孙亚先（个人）
A124: 7940 | B124: 南山 | C124: 舒武新 先生 | D124: 13693171170 | E124: 201 | F124: 1 | G124: 200 | H124: 0 | I124: 200 | K124: 45682 | L124: 0.73923611 | M124: 王倩
A125: 7947 | B125: 南山 | C125: 申申 女士 | D125: 15810868826 | E125: 1000 | F125: 680 | G125: 320 | H125: 0 | I125: 320 | K125: 45682 | L125: 0.90836806 | M125: 孙亚先（个人）
A126: 7948 | B126: 南山 | C126: 高 先生 | D126: 13811163891 | E126: 1000 | F126: 920 | G126: 80 | H126: 0 | I126: 80 | K126: 45682 | L126: 0.89866898 | M126: 孙亚先（个人）
A127: 7949 | B127: 南山 | C127: 张 先生 | D127: 18310327082 | E127: 500 | F127: 340 | G127: 160 | H127: 0 | I127: 160 | K127: 45683 | L127: 0.69196759 | M127: 张新健
A128: 7950 | B128: 南山 | C128: 冯霞 | D128: 13901187330 | E128: 361 | F128: 1 | G128: 360 | H128: 0 | I128: 360 | K128: 45682 | L128: 0.90256944 | M128: 张新健
A129: 7952 | B129: 南山 | C129: 陈 女士 | D129: 13750830785 | E129: 5000 | F129: 4650 | G129: 350 | H129: 0 | I129: 350 | K129: 45683 | L129: 0.73546296 | M129: 孙亚先（个人）
A130: 7958 | B130: 南山 | C130: 金 先生 | D130: 13811571806 | E130: 3000 | F130: 2770 | G130: 230 | H130: 0 | I130: 230 | K130: 45683 | L130: 0.69987269 | M130: 孙亚先（个人）
A131: 7966 | B131: 南山 | C131: 冯霞 | D131: 13901187330 | E131: 471 | F131: 1 | G131: 470 | H131: 0 | I131: 470 | K131: 45683 | L131: 0.89766204 | M131: 张新健
A132: 7967 | B132: 南山 | C132: 康 先生 | D132: 18810119302 | E132: 5000 | F132: 4850 | G132: 150 | H132: 0 | I132: 150 | K132: 45684 | L132: 0.71046296 | M132: 舒武新
A133: 7970 | B133: 南山 | C133: 陈 女士 | D133: 13527632175 | E133: 1000 | F133: 680 | G133: 320 | H133: 0 | I133: 320 | K133: 45684 | L133: 0.70103009 | M133: 王倩
A134: 7971 | B134: 南山 | C134: 赵 先生 | D134: 13683520585 | E134: 5000 | F134: 4850 | G134: 150 | H134: 0 | I134: 150 | K134: 45684 | L134: 0.53959491 | M134: 张新健
... A146: 8014 | B146: 南山 | C146: 杨 女士 | D146: 18010288756 | E146: 200 | F146: 160 | G146: 40 | H146: 0 | I146: 40 | K146: 45687 | L146: 0.86077546 | M146: 王倩
A147: 8015 | B147: 南山 | C147: 袁 先生 | D147: 13911125550 | E147: 500 | F147: 0 | G147: 500 | H147: 0 | I147: 80 | J147: 现金 | K147: 45688 | L147: 0.84886574 | M147: 张新健
A148: 8016 | B148: 南山 | C148: 袁 先生 | D148: 13911125550 | E148: 1500 | F148: 1260 | G148: 240 | H148: 0 | I148: 240 | K148: 45687 | L148: 0.90420139 | M148: 张新健
A149: 8051 | B149: 南山 | C149: 陈 女士 | D149: 13510612368 | E149: 6000 | F149: 5760 | G149: 240 | H149: 0 | I149: 240 | K149: 45688 | L149: 0.83774306 | M149: 张新健
A150: 8052 | B150: 南山 | C150: 袁 先生 | D150: 13910662633 | E150: 2000 | F150: 1760 | G150: 240 | H150: 0 | I150: 240 | K150: 45688 | L150: 0.91094907 | M150: 孙亚先（个人）
A151: 8053 | B151: 南山 | C151: 黄 先生 | D151: 18677013098 | E151: 1000 | F151: 640 | G151: 360 | H151: 0 | I151: 360 | K151: 45688 | L151: 0.80810185 | M151: 孙亚先（个人）
A152: 8055 | B152: 南山 | C152: 胡 女士 | D152: 18707921256 | E152: 2000 | F152: 1760 | G152: 240 | H152: 0 | I152: 240 | K152: 45688 | L152: 0.80849537 | M152: 张新健

Sheet 养护日报表
A1: 养护收入
A2: 门店 | B2: 流水号 | C2: 类型 | D2: 品牌 | E2: 长度 | F2: 角度 | G2: 修刃 | H2: 打蜡 | I2: 刮蜡 | J2: 其它 | K2: 备注 | L2: 维修技师 | M2: 附加费用 | N2: 接待 | O2: 日期 | P2: 时间 | Q2: 订单号 | R2: 金额
A3: 万龙服务中心 | B3: 241130-00048 | C3: 单板 | D3: Gray | E3: 148 | F3: 0 | G3: -- | H3: -- | I3: -- | J3: 其它,粘板面 | L3: (个人)张亮 | M3: 200 | N3: (个人)张亮 | O3: 45626 | P3: 0.89967593 | Q3: 41452 | R3: 200
A4: 万龙服务中心 | B4: 241130-00047 | C4: 双板 | D4: Ogasaka/小贺 | E4: 165 | F4: 0 | G4: -- | H4: (个人)张亮 | I4: (个人)张亮 | L4: -- | M4: 0 | N4: (个人)张亮 | O4: 45626 | P4: 0.85368056 | Q4: 41449 | R4: 150
A5: 万龙服务中心 | B5: 241130-00046 | C5: 单板 | D5: Gray | E5: 160 | F5: 0 | G5: -- | H5: 王政 | I5: 王政 | K5: 800元机打蜡卡消费 | L5: -- | M5: 0 | N5: (个人)王政 | O5: 45626 | P5: 0.75611111 | Q5: 0 | R5: 0
A6: 万龙服务中心 | B6: 241130-00045 | C6: 单板 | D6: Burton | E6: 153 | F6: 89 | G6: (个人)张亮 | H6: -- | I6: -- | J6: 其它 | K6: 2付板 | L6: (个人)张亮 | M6: 150 | N6: (个人)张亮 | O6: 45626 | P6: 0.72325231 | Q6: 41437 | R6: 300
A7: 万龙服务中心 | B7: 241130-00044 | C7: 双板 | D7: Volkl/沃克 | E7: 165 | F7: 0 | G7: -- | H7: -- | I7: -- | J7: 其它,粘板面 | L7: (个人)张亮 | M7: 100 | N7: (个人)张亮 | O7: 45626 | P7: 0.72188657 | Q7: 41436 | R7: 100
A8: 万龙服务中心 | B8: 241130-00043 | C8: 单板 | D8: 未知品牌/未知品牌 | E8: 140 | F8: 0 | G8: -- | H8: -- | I8: -- | J8: 粘板面 | L8: (个人)张亮 | M8: 200 | N8: 王政 | O8: 45626 | P8: 0.71025463 | Q8: 41435 | R8: 200
A9: 万龙服务中心 | B9: 241130-00042 | C9: 单板 | D9: 未知品牌/未知品牌 | E9: 165 | F9: 0 | G9: -- | H9: (个人)张亮 | I9: (个人)张亮 | L9: -- | M9: 0 | N9: (个人)张亮 | O9: 45626 | P9: 0.70548611 | Q9: 41433 | R9: 150
A10: 万龙服务中心 | B10: 241130-00041 | C10: 单板 | D10: Gray | E10: 170 | F10: 89 | G10: 张亮 | H10: 张亮 | I10: 张亮 | J10: 其它,粘板面 | L10: 张亮 | M10: 100 | N10: 张亮 | O10: 45626 | P10: 0.70438657 | Q10: 41432 | R10: 330
A11: 万龙服务中心 | B11: 241130-00040 | C11: 双板 | D11: Ogasaka/小贺 | E11: 165 | F11: 89 | G11: 王政 | H11: 王政 | I11: 王政 | L11: -- | M11: 0 | N11: 王政 | O11: 45626 | P11: 0.70128472 | Q11: 41431 | R11: 430
A12: 万龙服务中心 | B12: 241130-00039 | C12: 单板 | D12: Jones | E12: 155 | F12: 89 | G12: (个人)张亮 | H12: (个人)张亮 | I12: (个人)张亮 | L12: -- | M12: 0 | N12: 王政 | O12: 45626 | P12: 0.70034722
A13: 万龙服务中心 | B13: 241130-00038 | C13: 双板 | D13: Rossignol/金鸡 | E13: 157 | F13: 89 | G13: 王政 | H13: 王政 | I13: 王政 | L13: -- | M13: 0 | N13: 王政 | O13: 45626 | P13: 0.69173611 | Q13: 41430 | R13: 200
A14: 万龙服务中心 | B14: 241130-00037 | C14: 单板 | D14: 未知品牌/未知品牌 | E14: 150 | F14: 0 | G14: -- | H14: 王政 | I14: 王政 | L14: -- | M14: 0 | N14: 王政 | O14: 45626 | P14: 0.68127315 | Q14: 41429 | R14: 150
A15: 万龙服务中心 | B15: 241130-00036 | C15: 单板 | D15: 未知品牌/未知品牌 | E15: 155 | F15: 89 | G15: 张亮 | H15: 张亮 | I15: 张亮 | L15: -- | M15: 0 | N15: 王政 | O15: 45626 | P15: 0.67743056 | Q15: 41428 | R15: 230
A16: 万龙服务中心 | B16: 241130-00035 | C16: 单板 | D16: 未知品牌/未知品牌 | E16: 145 | F16: 0 | G16: -- | H16: 张亮 | I16: 张亮 | L16: -- | M16: 0 | N16: 张亮 | O16: 45626 | P16: 0.6693287 | Q16: 41427 | R16: 150
A17: 万龙服务中心 | B17: 241130-00034 | C17: 单板 | D17: Capita | E17: 150 | F17: 0 | G17: -- | H17: -- | I17: -- | J17: 粘板面,其它 | L17: 张亮 | M17: 100 | N17: 张亮 | O17: 45626 | P17: 0.65969907 | Q17: 41425 | R17: 100
A18: 万龙服务中心 | B18: 241130-00033 | C18: 双板 | D18: Faction | E18: 183 | F18: 0 | G18: -- | H18: 张亮 | I18: 张亮 | J18: 其它,补板底 | L18: 张亮 | M18: 100 | N18: 张亮 | O18: 45626 | P18: 0.65363426 | Q18: 41424 | R18: 270
A19: 万龙服务中心 | B19: 241130-00032 | C19: 单板 | D19: 未知品牌/未知品牌 | E19: 150 | F19: 89 | G19: 张亮 | H19: 张亮 | I19: 张亮 | L19: -- | M19: 0 | N19: 王政 | O19: 45626 | P19: 0.65148148 | Q19: 41423 | R19: 230
B20: 241130-00031 | C20: 双板 | D20: Volkl/沃克 | E20: 165 | F20: 87 | G20: -- | H20: -- | I20: -- | L20: -- | M20: 0 | N20: 张亮 | O20: 45626 | P20: 0.65056713 | Q20: 0 | R20: 0
A21: 万龙服务中心 | B21: 241130-00030 | C21: 双板 | D21: Volkl/沃克 | E21: 160 | F21: 88 | G21: 王政 | H21: 王政 | I21: 王政 | L21: -- | M21: 0 | N21: 张亮 | O21: 45626 | P21: 0.62155093 | Q21: 41420 | R21: 200
A22: 万龙服务中心 | B22: 241130-00029 | C22: 双板 | D22: Dynastar | E22: 162 | F22: 88 | G22: 王政 | H22: 王政 | I22: 王政 | L22: -- | M22: 0 | N22: 张亮 | O22: 45626 | P22: 0.61414352 | Q22: 41419 | R22: 200
A23: 万龙服务中心 | B23: 241130-00028 | C23: 单板 | D23: 未知品牌/未知品牌 | E23: 150 | F23: 0 | G23: -- | H23: -- | I23: -- | J23: 螺丝 | L23: 王政 | M23: 50 | N23: 王政 | O23: 45626 | P23: 0.6103588 | Q23: 41418 | R23: 50
A24: 万龙服务中心 | B24: 241130-00027 | C24: 双板 | D24: Fischer/费舍尔 | E24: 150 | F24: 88 | G24: 王政 | H24: -- | I24: -- | L24: -- | M24: 0 | N24: 张亮 | O24: 45626 | P24: 0.60677083 | Q24: 41416 | R24: 170
A25: 万龙服务中心 | B25: 241130-00026 | C25: 双板 | D25: Kessler | E25: 165 | F25: 88 | G25: 王政 | H25: -- | I25: -- | L25: -- | M25: 0 | N25: 王政 | O25: 45626 | P25: 0.60537037 | Q25: 41414 | R25: 150
A26: 万龙服务中心 | B26: 241130-00025 | C26: 单板 | D26: Burton | E26: 150 | F26: 0 | G26: -- | H26: 王政 | I26: 王政 | L26: -- | M26: 0 | N26: 王政 | O26: 45626 | P26: 0.59791667 | Q26: 41413 | R26: 170
A27: 万龙服务中心 | B27: 241130-00024 | C27: 单板 | D27: 未知品牌/未知品牌 | E27: 150 | F27: 0 | G27: -- | H27: 王政 | I27: 王政 | L27: -- | M27: 0 | N27: 王政 | O27: 45626 | P27: 0.59314815 | Q27: 41409 | R27: 170
A28: 万龙服务中心 | B28: 241130-00023 | C28: 双板 | D28: Head/海德 | E28: 165 | F28: 88 | G28: 张亮 | H28: -- | I28: -- | L28: -- | M28: 0 | N28: 张亮 | O28: 45626 | P28: 0.57115741 | Q28: 41407 | R28: 170
A29: 万龙服务中心 | B29: 241130-00022 | C29: 双板 | D29: Head/海德 | E29: 155 | F29: 89 | G29: -- | H29: -- | I29: -- | L29: -- | M29: 0 | N29: 张亮 | O29: 45626 | P29: 0.55364583 | Q29: 41401 | R29: 230
A30: 万龙服务中心 | B30: 241130-00021 | C30: 双板 | D30: Stockli/斯托克林 | E30: 165 | F30: 88 | G30: 王政 | H30: -- | I30: -- | L30: -- | M30: 0 | N30: 张亮 | O30: 45626 | P30: 0.52203704 | Q30: 41385 | R30: 170
A31: 万龙服务中心 | B31: 241130-00020 | C31: 双板 | D31: Fischer/费舍尔 | E31: 178 | F31: 87 | G31: 王政 | H31: 王政 | I31: 王政 | L31: -- | M31: 0 | N31: 张亮 | O31: 45626 | P31: 0.51486111 | Q31: 41380 | R31: 230
A32: 万龙服务中心 | B32: 241130-00019 | C32: 单板 | D32: Burton | E32: 157 | F32: 0 | G32: -- | H32: 张亮 | I32: 张亮 | L32: -- | M32: 0 | N32: 张亮 | O32: 45626 | P32: 0.51295139 | Q32: 41379 | R32: 150
A33: 万龙服务中心 | B33: 241130-00018 | C33: 双板 | D33: Ogasaka/小贺 | E33: 165 | F33: 88 | G33: 张亮 | H33: 张亮 | I33: 张亮 | L33: -- | M33: 0 | N33: 张亮 | O33: 45626 | P33: 0.50542824 | Q33: 41322 | R33: 200
A34: 万龙服务中心 | B34: 241130-00017 | C34: 单板 | D34: 未知品牌/未知品牌 | E34: 150 | F34: 0 | G34: -- | H34: 张亮 | I34: 张亮 | L34: -- | M34: 0 | N34: 张亮 | O34: 45626 | P34: 0.48871528 | Q34: 41318 | R34: 170
A35: 万龙服务中心 | B35: 241130-00016 | C35: 单板 | D35: Capita | E35: 165 | F35: 0 | G35: -- | H35: 张亮 | I35: 张亮 | L35: -- | M35: 0 | N35: 王政 | O35: 45626 | P35: 0.48408565 | Q35: 41316 | R35: 170
A36: 万龙服务中心 | B36: 241130-00015 | C36: 双板 | D36: Volkl/沃克 | E36: 165 | F36: 89 | G36: 王政 | H36: 王政 | I36: 王政 | L36: -- | M36: 0 | N36: 王政 | O36: 45626 | P36: 0.47818287 | Q36: 41314 | R36: 230
A37: 万龙服务中心 | B37: 241130-00014 | C37: 双板 | D37: Head/海德 | E37: 165 | F37: 0 | G37: -- | H37: -- | I37: -- | J37: 双板固定器 | L37: 张亮 | M37: 200 | N37: 王政 | O37: 45626 | P37: 0.4721412 | Q37: 41311 | R37: 200
A38: 万龙服务中心 | B38: 241130-00013 | C38: 单板 | D38: Gray | E38: 150 | F38: 0 | G38: -- | H38: -- | I38: -- | J38: 其它 | K38: 安固定器 | L38: 王政 | M38: 50 | N38: 王政 | O38: 45626 | P38: 0.46298611 | Q38: 41307 | R38: 50
A39: 万龙服务中心 | B39: 241130-00012 | C39: 单板 | D39: 未知品牌/未知品牌 | E39: 155 | F39: 0 | G39: -- | H39: -- | I39: -- | J39: 其它,螺丝 | L39: 张亮 | M39: 50 | N39: 张亮 | O39: 45626 | P39: 0.46238426 | Q39: 41305 | R39: 50
A40: 万龙服务中心 | B40: 241130-00011 | C40: 单板 | D40: 未知品牌/未知品牌 | E40: 150 | F40: 0 | G40: -- | H40: -- | I40: -- | J40: 其它,绑带 | L40: 张亮 | M40: 130 | N40: 张亮 | O40: 45626 | P40: 0.41085648 | Q40: 41283 | R40: 130
A41: 万龙服务中心 | B41: 241130-00010 | C41: 双板 | D41: Head/海德 | E41: 165 | F41: 88 | G41: 王政 | H41: 王政 | I41: 王政 | L41: -- | M41: 0 | N41: 王政 | O41: 45626 | P41: 0.41015046 | Q41: 41282 | R41: 230
A42: 万龙服务中心 | B42: 241130-00009 | C42: 单板 | D42: Burton | E42: 155 | F42: 0 | G42: -- | H42: 张亮 | I42: 张亮 | L42: -- | M42: 0 | N42: 张亮 | O42: 45626 | P42: 0.39444444 | Q42: 41275 | R42: 150
A43: 万龙服务中心 | B43: 241130-00008 | C43: 双板 | D43: 未知品牌/未知品牌 | E43: 150 | F43: 0 | G43: -- | H43: 王政 | I43: 王政 | L43: -- | M43: 0 | N43: 王政 | O43: 45626 | P43: 0.38722222 | Q43: 41271 | R43: 170
A44: 万龙服务中心 | B44: 241130-00007 | C44: 单板 | D44: 未知品牌/未知品牌 | E44: 141 | F44: 89 | G44: -- | H44: -- | I44: -- | L44: -- | M44: 0 | N44: 张亮 | O44: 45626 | P44: 0.38347222 | Q44: 41269 | R44: 230
A45: 万龙服务中心 | B45: 241130-00006 | C45: 单板 | D45: 未知品牌/未知品牌 | E45: 140 | F45: 89 | G45: 张亮 | H45: 张亮 | I45: 张亮 | L45: -- | M45: 0 | N45: 王政 | O45: 45626 | P45: 0.38081019 | Q45: 41267 | R45: 230
A46: 万龙服务中心 | B46: 241130-00005 | C46: 单板 | D46: Burton | E46: 157 | F46: 0 | G46: -- | H46: 张亮 | I46: 张亮 | L46: -- | M46: 0 | N46: 张亮 | O46: 45626 | P46: 0.37855324 | Q46: 41265 | R46: 170
A47: 万龙服务中心 | B47: 241130-00004 | C47: 单板 | D47: 未知品牌/未知品牌 | E47: 155 | F47: 89 | G47: 王政 | H47: 王政 | I47: 王政 | L47: -- | M47: 0 | N47: 王政 | O47: 45626 | P47: 0.37688657 | Q47: 41263 | R47: 200
A48: 万龙服务中心 | B48: 241130-00003 | C48: 单板 | D48: Jones | E48: 160 | F48: 0 | G48: -- | H48: 张亮 | I48: 张亮 | L48: -- | M48: 0 | N48: 张亮 | O48: 45626 | P48: 0.35216435 | Q48: 41252 | R48: 170
A49: 万龙服务中心 | B49: 241130-00002 | C49: 双板 | D49: Fischer/费舍尔 | E49: 165 | F49: 89 | G49: 王政 | H49: 王政 | I49: 王政 | L49: -- | M49: 0 | N49: 张亮 | O49: 45626 | P49: 0.31480324 | Q49: 41251 | R49: 200
A50: 万龙服务中心 | B50: 241130-00001 | C50: 单板 | D50: 未知品牌/未知品牌 | E50: 148 | F50: 0 | G50: -- | H50: 张亮 | I50: 张亮 | L50: -- | M50: 0 | N50: 张亮 | O50: 45626 | P50: 0.30939815 | Q50: 41250 | R50: 170
A51: 万龙服务中心 | B51: 241129-00017 | C51: 单板 | D51: 未知品牌/未知品牌 | E51: 155 | F51: 0 | G51: -- | H51: -- | I51: -- | L51: -- | M51: 0 | N51: 王政 | O51: 45625 | P51: 0.89121528 | Q51: 41249 | R51: 170
A52: 万龙服务中心 | B52: 241129-00016 | C52: 双板 | D52: Atomic/阿托米克 | E52: 165 | F52: 0 | G52: -- | H52: -- | I52: -- | L52: -- | M52: 0 | N52: 王政 | O52: 45625 | P52: 0.88034722 | Q52: 41247 | R52: 150
A53: 万龙服务中心 | B53: 241129-00015 | C53: 单板 | D53: 未知品牌/未知品牌 | E53: 150 | F53: 0 | G53: -- | H53: -- | I53: -- | J53: 螺丝,其它 | L53: -- | M53: 80 | N53: 王政 | O53: 45625 | P53: 0.85724537 | Q53: 41246 | R53: 80
A54: 万龙服务中心 | B54: 241129-00014 | C54: 双板 | D54: Salomon/索罗门 | E54: 165 | F54: 89 | G54: -- | H54: 王政 | I54: 王政 | K54: 800元机打蜡卡消费 | L54: -- | M54: 0 | N54: 王政 | O54: 45625 | P54: 0.78061343 | Q54: 0 | R54: 0
A55: 万龙服务中心 | B55: 241129-00013 | C55: 双板 | D55: Atomic/阿托米克 | E55: 170 | F55: 0 | G55: -- | H55: 王政 | I55: 王政 | K55: 800元机打蜡卡消费 | L55: -- | M55: 0 | N55: 王政 | O55: 45625 | P55: 0.77767361 | Q55: 0 | R55: 0
A56: 万龙服务中心 | B56: 241129-00012 | C56: 单板 | D56: Jones | E56: 160 | F56: 89 | G56: 王政 | H56: 王政 | I56: 王政 | K56: 甫山雪板 | L56: -- | M56: 0 | N56: 王政 | O56: 45625 | P56: 0.77534722 | Q56: 0 | R56: 0
A57: 万龙服务中心 | B57: 241129-00011 | C57: 单板 | D57: 未知品牌/未知品牌 | E57: 140 | F57: 89 | G57: 王政 | H57: -- | I57: -- | L57: -- | M57: 0 | N57: 王政 | O57: 45625 | P57: 0.67340278 | Q57: 41239 | R57: 170
A58: 万龙服务中心 | B58: 241129-00010 | C58: 单板 | D58: 未知品牌/未知品牌 | E58: 155 | F58: 89 | G58: 王政 | H58: 王政 | I58: 王政 | L58: -- | M58: 0 | N58: 王政 | O58: 45625 | P58: 0.66134259 | Q58: 41238 | R58: 230
A59: 万龙服务中心 | B59: 241129-00009 | C59: 双板 | D59: Head/海德 | E59: 170 | F59: 89 | G59: 王政 | H59: 王政 | I59: 王政 | L59: -- | M59: 0 | N59: 王政 | O59: 45625 | P59: 0.65689815 | Q59: 41237 | R59: 200
A60: 万龙服务中心 | B60: 241129-00008 | C60: 双板 | D60: Stockli/斯托克林 | E60: 165 | F60: 89 | G60: 王政 | H60: -- | I60: -- | L60: -- | M60: 0 | N60: 王政 | O60: 45625 | P60: 0.64001157 | Q60: 41236 | R60: 150
A61: 万龙服务中心 | B61: 241129-00007 | C61: 双板 | D61: Stockli/斯托克林 | E61: 165 | F61: 88 | G61: 王政 | H61: 王政 | I61: 王政 | L61: -- | M61: 0 | N61: 王政 | O61: 45625 | P61: 0.63496528 | Q61: 41235 | R61: 200
A62: 万龙服务中心 | B62: 241129-00006 | C62: 单板 | D62: 未知品牌/未知品牌 | E62: 150 | F62: 0 | G62: -- | H62: 王政 | I62: 王政 | L62: -- | M62: 0 | N62: 王政 | O62: 45625 | P62: 0.61137731 | Q62: 41234 | R62: 150
A63: 万龙服务中心 | B63: 241129-00005 | C63: 双板 | D63: 未知品牌/未知品牌 | E63: 155 | F63: 89 | G63: 王政 | H63: 王政 | I63: 王政 | L63: -- | M63: 0 | N63: 王政 | O63: 45625 | P63: 0.54679398 | Q63: 41228 | R63: 230
A64: 万龙服务中心 | B64: 241129-00004 | C64: 单板 | D64: 未知品牌/未知品牌 | E64: 150 | F64: 0 | G64: -- | H64: -- | I64: -- | J64: 其它 | K64: 粘固定器 | L64: 王政 | M64: 50 | N64: 王政 | O64: 45625 | P64: 0.51833333 | Q64: 41227 | R64: 50
A65: 万龙服务中心 | B65: 241129-00003 | C65: 双板 | D65: Volkl/沃克 | E65: 160 | F65: 89 | G65: 王政 | H65: -- | I65: -- | L65: -- | M65: 0 | N65: 王政 | O65: 45625 | P65: 0.50821759 | Q65: 41226 | R65: 150
A66: 万龙服务中心 | B66: 241129-00002 | C66: 单板 | D66: 未知品牌/未知品牌 | E66: 140 | F66: 0 | G66: -- | H66: 王政 | I66: 王政 | L66: -- | M66: 0 | N66: 王政 | O66: 45625 | P66: 0.48413194 | Q66: 41224 | R66: 170
A67: 万龙服务中心 | B67: 241129-00001 | C67: 单板 | D67: 未知品牌/未知品牌 | E67: 150 | F67: 0 | G67: -- | H67: -- | I67: -- | J67: 补板底 | L67: 王政 | M67: 100 | N67: 王政 | O67: 45625 | P67: 0.40019676 | Q67: 41220 | R67: 100
A68: 万龙服务中心 | B68: 241128-00013 | C68: 单板 | D68: Nobaday | E68: 140 | F68: 0 | G68: -- | H68: -- | I68: -- | L68: -- | M68: 0 | N68: 王政 | O68: 45624 | P68: 0.86490741 | Q68: 41214 | R68: 170
A69: 万龙服务中心 | B69: 241128-00012 | C69: 单板 | D69: 未知品牌/未知品牌 | E69: 155 | F69: 89 | G69: 王政 | H69: 王政 | I69: 王政 | L69: -- | M69: 0 | N69: 王政 | O69: 45624 | P69: 0.72287037 | Q69: 41211 | R69: 200
A70: 万龙服务中心 | B70: 241128-00011 | C70: 单板 | D70: Rossignol/金鸡 | E70: 155 | F70: 0 | G70: -- | H70: 张亮 | I70: 张亮 | L70: -- | M70: 0 | N70: 张亮 | O70: 45624 | P70: 0.69140046 | Q70: 41210 | R70: 170
A71: 万龙服务中心 | B71: 241128-00010 | C71: 双板 | D71: Elan/伊兰 | E71: 170 | F71: 89 | G71: 王政 | H71: -- | I71: -- | L71: -- | M71: 0 | N71: 王政 | O71: 45624 | P71: 0.67363426 | Q71: 41209 | R71: 150
A72: 万龙服务中心 | B72: 241128-00009 | C72: 双板 | D72: Rossignol/金鸡 | E72: 157 | F72: 89 | G72: 王政 | H72: 王政 | I72: 王政 | K72: 10次卡用户 | L72: -- | M72: 0 | N72: 张亮 | O72: 45624 | P72: 0.66452546 | Q72: 0 | R72: 0
A73: 万龙服务中心 | B73: 241128-00007 | C73: 单板 | D73: Jones | E73: 140 | F73: 0 | G73: -- | H73: 王政 | I73: 王政 | L73: -- | M73: 0 | N73: 王政 | O73: 45624 | P73: 0.65916667 | Q73: 41208 | R73: 320
A74: 万龙服务中心 | B74: 241128-00008 | C74: 单板 | D74: 未知品牌/未知品牌 | E74: 140 | F74: 0 | G74: -- | H74: 王政 | I74: 王政 | L74: -- | M74: 0 | N74: 王政 | O74: 45624 | P74: 0.65916667
A75: 万龙服务中心 | B75: 241128-00006 | C75: 双板 | D75: Salomon/索罗门 | E75: 165 | F75: 0 | G75: -- | H75: 王政 | I75: 王政 | K75: 800元雪季打蜡卡 | L75: -- | M75: 0 | N75: 王政 | O75: 45624 | P75: 0.6349537 | Q75: 0 | R75: 0
A76: 万龙服务中心 | B76: 241128-00005 | C76: 单板 | D76: Burton | E76: 138 | F76: 0 | G76: -- | H76: 张亮 | I76: 张亮 | L76: -- | M76: 0 | N76: 张亮 | O76: 45624 | P76: 0.63457176 | Q76: 41207 | R76: 170
A77: 万龙服务中心 | B77: 241128-00004 | C77: 双板 | D77: Atomic/阿托米克 | E77: 170 | F77: 0 | G77: -- | H77: 王政 | I77: 王政 | K77: 800元雪季打蜡卡 | L77: -- | M77: 0 | N77: 王政 | O77: 45624 | P77: 0.63402778 | Q77: 0 | R77: 0
A78: 万龙服务中心 | B78: 241128-00003 | C78: 双板 | D78: Ogasaka/小贺 | E78: 165 | F78: 87 | G78: 王政 | H78: 王政 | I78: 王政 | L78: -- | M78: 0 | N78: 王政 | O78: 45624 | P78: 0.59357639 | Q78: 41205 | R78: 200
A79: 万龙服务中心 | B79: 241128-00002 | C79: 双板 | D79: Nordica/诺迪卡 | E79: 155 | F79: 89 | G79: 王政 | H79: 王政 | I79: 王政 | L79: -- | M79: 0 | N79: 王政 | O79: 45624 | P79: 0.52359954 | Q79: 41202 | R79: 200
A80: 万龙服务中心 | B80: 241128-00001 | C80: 双板 | D80: Salomon/索罗门 | E80: 155 | F80: 89 | G80: 张亮 | H80: 张亮 | I80: 张亮 | J80: 其它,补板底 | L80: 张亮 | M80: 100 | N80: 张亮 | O80: 45624 | P80: 0.47699074 | Q80: 41200 | R80: 330
A81: 万龙服务中心 | B81: 241127-00013 | C81: 单板 | D81: Salomon/索罗门 | E81: 150 | F81: 89 | G81: 张亮 | H81: 张亮 | I81: 张亮 | L81: -- | M81: 0 | N81: 张亮 | O81: 45623 | P81: 0.70059028 | Q81: 41196 | R81: 200
A82: 万龙服务中心 | B82: 241127-00012 | C82: 双板 | D82: Rossignol/金鸡 | E82: 167 | F82: 88 | G82: 张亮 | H82: -- | I82: -- | L82: -- | M82: 0 | N82: 张亮 | O82: 45623 | P82: 0.69979167 | Q82: 41195 | R82: 150
A83: 万龙服务中心 | B83: 241127-00011 | C83: 双板 | D83: Atomic/阿托米克 | E83: 170 | F83: 0 | G83: -- | H83: -- | I83: -- | J83: 其它 | K83: 24.25机打蜡 | L83: 张亮 | M83: 800 | N83: 张亮 | O83: 45623 | P83: 0.69162037 | Q83: 41194 | R83: 800
A84: 万龙服务中心 | B84: 241127-00010 | C84: 双板 | D84: Salomon/索罗门 | E84: 165 | F84: 0 | G84: -- | H84: -- | I84: -- | J84: 其它 | K84: 机打蜡 | L84: 张亮 | M84: 0 | N84: 张亮 | O84: 45623 | P84: 0.67241898 | Q84: 0 | R84: 0
A85: 万龙服务中心 | B85: 241127-00009 | C85: 双板 | D85: Rossignol/金鸡 | E85: 165 | F85: 89 | G85: 张亮 | H85: -- | I85: -- | L85: -- | M85: 0 | N85: 张亮 | O85: 45623 | P85: 0.63615741 | Q85: 41193 | R85: 170
A86: 万龙服务中心 | B86: 241127-00008 | C86: 双板 | D86: Fischer/费舍尔 | E86: 171 | F86: 88 | G86: 张亮 | H86: 张亮 | I86: 张亮 | L86: -- | M86: 0 | N86: 张亮 | O86: 45623 | P86: 0.63238426 | Q86: 41192 | R86: 230
A87: 万龙服务中心 | B87: 241127-00007 | C87: 单板 | D87: 未知品牌/未知品牌 | E87: 150 | F87: 0 | G87: -- | H87: 张亮 | I87: 张亮 | L87: -- | M87: 0 | N87: 张亮 | O87: 45623 | P87: 0.63108796 | Q87: 41191 | R87: 170
A88: 万龙服务中心 | B88: 241127-00006 | C88: 单板 | D88: Burton | E88: 150 | F88: 0 | G88: -- | H88: -- | I88: -- | J88: 其它,螺丝 | L88: 张亮 | M88: 50 | N88: 张亮 | O88: 45623 | P88: 0.59157407 | Q88: 41190 | R88: 50
A89: 万龙服务中心 | B89: 241127-00005 | C89: 双板 | D89: Head/海德 | E89: 165 | F89: 88 | G89: 张亮 | H89: -- | I89: -- | L89: -- | M89: 0 | N89: 张亮 | O89: 45623 | P89: 0.52678241 | Q89: 41187 | R89: 150
A90: 万龙服务中心 | B90: 241127-00004 | C90: 单板 | D90: 未知品牌/未知品牌 | E90: 150 | F90: 89 | G90: 张亮 | H90: 张亮 | I90: 张亮 | L90: -- | M90: 0 | N90: 张亮 | O90: 45623 | P90: 0.50350694 | Q90: 41186 | R90: 200
A91: 万龙服务中心 | B91: 241127-00003 | C91: 单板 | D91: F2 | E91: 139 | F91: 0 | G91: -- | H91: 张亮 | I91: 张亮 | L91: -- | M91: 0 | N91: 张亮 | O91: 45623 | P91: 0.45325231 | Q91: 41183 | R91: 150
A92: 万龙服务中心 | B92: 241127-00002 | C92: 单板 | D92: 未知品牌/未知品牌 | E92: 155 | F92: 0 | G92: -- | H92: -- | I92: -- | J92: 其它 | K92: 前绑带齿条 | L92: 张亮 | M92: 130 | N92: 张亮 | O92: 45623 | P92: 0.42789352 | Q92: 41182 | R92: 130
A93: 万龙服务中心 | B93: 241127-00001 | C93: 单板 | D93: Nitro | E93: ?159 | F93: 89 | G93: 张亮 | H93: -- | I93: -- | L93: -- | M93: 0 | N93: 张亮 | O93: 45623 | P93: 0.41 | Q93: 41181 | R93: 170
A94: 万龙服务中心 | B94: 241126-00017 | C94: 单板 | D94: Nitro | E94: 155 | F94: 0 | G94: -- | H94: 张亮 | I94: 张亮 | K94: 2付板 | L94: -- | M94: 150 | N94: 张亮 | O94: 45622 | P94: 0.89328704 | Q94: 41179 | R94: 320
A95: 万龙服务中心 | B95: 241126-00016 | C95: 双板 | D95: Fischer/费舍尔 | E95: 155 | F95: 89 | G95: 张亮 | H95: 张亮 | I95: 张亮 | L95: -- | M95: 0 | N95: 张亮 | O95: 45622 | P95: 0.73383102 | Q95: 41177 | R95: 230
A96: 万龙服务中心 | B96: 241126-00015 | C96: 双板 | D96: Fischer/费舍尔 | E96: 165 | F96: 0 | G96: -- | H96: (个人)张亮 | I96: (个人)张亮 | L96: -- | M96: 0 | N96: (个人)张亮 | O96: 45622 | P96: 0.7168287 | Q96: 41176 | R96: 150
A97: 万龙服务中心 | B97: 241126-00013 | C97: 单板 | D97: Capita | E97: 140 | F97: 89 | G97: 王政 | H97: -- | I97: -- | L97: -- | M97: 0 | N97: 王政 | O97: 45622 | P97: 0.6731713 | Q97: 41175 | R97: 430
A98: 万龙服务中心 | B98: 241126-00014 | C98: 单板 | D98: 未知品牌/未知品牌 | E98: 140 | F98: 89 | G98: 王政 | H98: -- | I98: -- | L98: -- | M98: 0 | N98: 王政 | O98: 45622 | P98: 0.6731713
A99: 万龙服务中心 | B99: 241126-00012 | C99: 双板 | D99: Ogasaka/小贺 | E99: 165 | F99: 0 | G99: -- | H99: -- | I99: -- | J99: 补板底 | K99: 万龙质保 | L99: 王政 | M99: 0 | N99: 王政 | O99: 45622 | P99: 0.67071759 | Q99: 0 | R99: 0
A100: 万龙服务中心 | B100: 241126-00011 | C100: 单板 | D100: Capita | E100: 157 | F100: 89 | G100: 张亮 | H100: 张亮 | I100: 张亮 | L100: -- | M100: 0 | N100: (个人)张亮 | O100: 45622 | P100: 0.65520833 | Q100: 41174 | R100: 230
...

Sheet 七色米零售报表
A1: 业务日期 | B1: 单据编号 | C1: 所属门店 | D1: 仓库 | E1: 总计金额 | F1: 实收金额 | G1: 特殊情况 | H1: 结算方式 | I1: 经手人 | J1: 备注
A2: 45598 | B2: XSD20241114000I | C2: 【崇礼】【旗舰店】 | D2: 【旗舰】零售商品仓 | E2: 320 | F2: 320 | H2: 京东收银-ZB | I2: 旗舰王政
A3: 45599 | B3: XSD20241103000I | C3: 【总部】 | D3: 【旗舰】零售商品仓 | E3: 389 | F3: 389 | H3: 京东收银-ZB | I3: 【总部】布乖
A4: 45603 | B4: XSD20241107000 | C4: 【崇礼】【旗舰店】 | D4: 【旗舰】零售商品仓 | E4: 8070 | F4: 8070 | H4: 京东收银-ZB | I4: 【旗舰】布乖
A5: 45605 | B5: XSD20241109001I | C5: 【总部】 | D5: 【旗舰】零售商品仓 | E5: 4650 | F5: 4650 | G5: 11.22提现8997 | H5: 现金-ZB | I5: 【总部】布乖
A6: 45605 | B6: XSD20241109000I | C6: 【总部】 | D6: 【万龙体验】零售商品仓 | E6: 790 | F6: 790 | H6: 【小程序】微信-ZB | I6: 【总部】布乖
A7: 45606 | B7: XSD20241110002I | C7: 【总部】 | D7: 【万龙体验】零售商品仓 | E7: 96 | F7: 0 | G7: 未收款 | H7: 现金-ZB | I7: 【总部】布乖 | J7: 等雪服调换完后一起结账
A8: 45606 | B8: XSD20241110001I | C8: 【总部】 | D8: 【旗舰】零售商品仓 | E8: 0 | F8: 0 | H8: 银行转账-ZB | I8: 【总部】布乖 | J8: 赠送
A9: 45606 | B9: XSD20241110000I | C9: 【总部】 | D9: 【旗舰】租赁试滑仓 | E9: 1300 | F9: 1300 | G9: 11.22提现8997 | H9: 现金-ZB | I9: 【总部】布乖
A10: 45607 | B10: XSD20241111000A | C10: 【崇礼】【万龙店】 | D10: 【万龙体验】租赁试滑仓 | E10: 3780 | F10: 3780 | H10: 【小程序】微信-WL | I10: 【万龙】肖志强 | J10: 儿童成长计划 小程序单号40676
A11: 45610 | B11: XSD20241117001A | C11: 【崇礼】【旗舰店】 | D11: 【旗舰】零售商品仓 | E11: 2400 | F11: 2400 | H11: 【小程序】微信-QJ | I11: 旗舰_修姜山 | J11: 富龙教练 订单号:40729
A12: 45612 | B12: XSD20241116003A | C12: 【崇礼】【万龙店】 | D12: 【万龙体验】零售商品仓 | E12: 199 | F12: 200 | G12: 现金在店长手里 | H12: 现金-WL | I12: 【万龙】肖志强 | J12: 定单号40825
A13: 45612 | B13: XSD20241116002A | C13: 【崇礼】【万龙店】 | D13: 【万龙体验】零售商品仓 | E13: 558 | F13: 558 | H13: 【小程序】微信-WL | I13: 【万龙】肖志强 | J13: 定单号40787
A14: 45612 | B14: XSD20241116001A | C14: 【崇礼】【万龙店】 | D14: 【万龙体验】零售商品仓 | E14: 116 | F14: 116 | H14: 【小程序】微信-WL | I14: 【万龙】肖志强 | J14: 订单号40780
A15: 45612 | B15: XSD20241116000A | C15: 【崇礼】【万龙店】 | D15: 【万龙体验】零售商品仓 | E15: 128 | F15: 128 | H15: 【小程序】微信-WL | I15: 【万龙】肖志强 | J15: 订单号40752
A16: 45613 | B16: XSD20241117002A | C16: 【崇礼】【万龙店】 | D16: 【万龙体验】零售商品仓 | E16: 149 | F16: 149 | H16: 【小程序】微信-WL | I16: 万龙_张小飞 | J16: 订单号40888
A17: 45613 | B17: XSD20241117000A | C17: 【崇礼】【万龙店】 | D17: 【万龙体验】零售商品仓 | E17: 109 | F17: 109 | H17: 【小程序】微信-WL | I17: 万龙_张小飞 | J17: 订单号40857
A18: 45614 | B18: XSD20241118000A | C18: 【崇礼】【万龙店】 | D18: 【万龙体验】零售商品仓 | E18: 30 | F18: 30 | H18: 【小程序】微信-WL | I18: 【万龙】肖志强 | J18: 订单号40923
A19: 45616 | B19: XSD20241120000A | C19: 【崇礼】【万龙店】 | D19: 【万龙体验】零售商品仓 | E19: 0 | F19: 0 | H19: 【小程序】微信-WL | I19: 【万龙】肖志强 | J19: 崔洋招待 孙亚先
A20: 45617 | B20: XSD20241121000I | C20: 【总部】 | D20: 【旗舰】零售商品仓 | E20: 0 | F20: 0 | H20: 银行转账-ZB | I20: 【总部】布乖 | J20: 杨总
A21: 45618 | B21: XSD20241122000I | C21: 【总部】 | D21: 【旗舰】零售商品仓 | E21: 12572.45 | F21: 0 | H21: 银行转账-ZB | I21: 【总部】布乖
A22: 45619 | B22: XSD20241123006I | C22: 【崇礼】【万龙店】 | D22: 【万龙体验】零售商品仓 | E22: 359 | F22: 359 | G22: 微信4775收款 | H22: 【小程序】微信-ZB | I22: 万龙_修姜山 | J22: 雪蜡
A23: 45619 | B23: XSD20241123004I | C23: 【总部】 | D23: 【旗舰】零售商品仓 | E23: 1809.5 | F23: 1809.5 | G23: 11.23提现8997 | H23: 银行转账-ZB | I23: 公司管理员
A24: 45619 | B24: XSD20241123005I | C24: 【总部】 | D24: 【旗舰】零售商品仓 | E24: 434.5 | F24: 434.5 | G24: 11.23提现8997 | H24: 银行转账-ZB | I24: 【总部】布乖
A25: 45619 | B25: XSD20241123002I | C25: 【总部】 | D25: 【旗舰】零售商品仓 | E25: 3299.45 | F25: 0 | H25: 银行转账-ZB | I25: 【总部】布乖
A26: 45619 | B26: XSD20241123001A | C26: 【崇礼】【万龙店】 | D26: 【万龙体验】零售商品仓 | E26: 199 | F26: 199 | G26: 微信4775收款 | H26: 【小程序】微信-WL | I26: 万龙_张小飞 | J26: 41014
A27: 45619 | B27: XSD20241123000A | C27: 【崇礼】【万龙店】 | D27: 【万龙体验】零售商品仓 | E27: 30 | F27: 30 | G27: 微信4775收款 | H27: 【小程序】微信-WL | I27: 【万龙】肖志强 | J27: 订单号：41005
A28: 45620 | B28: XSD20241124001A | C28: 【崇礼】【万龙店】 | D28: 【万龙体验】租赁试滑仓 | E28: 3780 | F28: 3780 | G28: 微信4775收款 | H28: 【小程序】微信-WL | I28: 【万龙】肖志强 | J28: 儿童成长计划 小程序订单号：41111
A29: 45620 | B29: XSD20241124000I | C29: 【总部】 | D29: 【旗舰】零售商品仓 | E29: 445 | F29: 445 | G29: 微信1865收款 | H29: 【小程序】微信-ZB | I29: 公司管理员 | J29: 小程序41098
A30: 45621 | B30: XSD20241125003A | C30: 【崇礼】【万龙店】 | D30: 【万龙体验】零售商品仓 | E30: 30 | F30: 30 | G30: 微信4775收款 | H30: 【小程序】微信-WL | I30: 【万龙】肖志强 | J30: 小程序订单号：41155
A31: 45621 | B31: XSD20241125002A | C31: 【崇礼】【万龙店】 | D31: 【万龙体验】零售商品仓 | E31: 58 | F31: 58 | G31: 微信4775收款 | H31: 【小程序】微信-WL | I31: 【万龙】肖志强 | J31: 小程序订单号：41154
A32: 45621 | B32: XSD20241125001I | C32: 【总部】 | D32: 【旗舰】零售商品仓 | E32: 4100 | F32: 4100 | G32: 11.25提现8997 | H32: 银行转账-ZB | I32: 【总部】布乖 | J32: 批发业务
A33: 45621 | B33: XSD20241125000A | C33: 【崇礼】【万龙店】 | D33: 【万龙体验】零售商品仓 | E33: 58 | F33: 58 | G33: 微信4775收款 | H33: 【小程序】微信-WL | I33: 【万龙】肖志强 | J33: 小程序订单号：41139
A34: 45622 | B34: XSD20241126000I | C34: 【崇礼】【万龙店】 | D34: 【万龙体验】零售商品仓 | E34: 359 | F34: 359 | G34: 银行转账-ZB | H34: 张凯微信收款转布乖微信 提现8997 | I34: 万龙_张凯 | J34: 雪蜡12.2收款
A35: 45624 | B35: XSD20241128000A | C35: 【北京】【南山店】 | D35: 【总部】崇礼新景家园固定资产仓 | E35: 474 | F35: 474 | G35: 11.28提现8997 | H35: 现金-NS | I35: 南山店员02
A36: 45625 | B36: XSD20241129001A | C36: 【崇礼】【万龙店】 | D36: 【万龙体验】零售商品仓 | E36: 174 | F36: 174 | G36: 微信4775收款 | H36: 【小程序】微信-WL | I36: 【万龙】肖志强 | J36: 订单号：41218
A37: 45625 | B37: XSD20241129000A | C37: 【崇礼】【万龙店】 | D37: 【万龙体验】零售商品仓 | E37: 58 | F37: 58 | G37: 微信4775收款 | H37: 【小程序】微信-WL | I37: 万龙_张小飞 | J37: 41216
A38: 45626 | B38: XSD20241130006I | C38: 【崇礼】【万龙店】 | D38: 【万龙体验】零售商品仓 | E38: 359 | F38: 359 | G38: 微信4775收款 | H38: 【小程序】微信-ZB | I38: 万龙_修姜山 | J38: 雪蜡
A39: 45626 | B39: XSD20241130005I | C39: 【总部】 | D39: 【万龙体验】租赁试滑仓 | E39: 6080 | F39: 6080 | G39: 微信4775收款 | H39: 【小程序】微信-ZB | I39: 【总部】布乖
A40: 45626 | B40: XSD20241130004I | C40: 【崇礼】【旗舰店】 | D40: 【旗舰】零售商品仓 | E40: 7159 | F40: 7159 | G40: 11.30提现8997 | H40: 微信转账-LX | I40: 【旗舰】舒武新 | J40: 发快递试号 微信转布乖 提现8997
A41: 45626 | B41: XSD20241130003A | C41: 【北京】【南山店】 | D41: 【南山】零售商品仓 | E41: 4290 | F41: 4290 | H41: 现金-NS | I41: 【南山】张新健
A42: 45626 | B42: XSD20241130002A | C42: 【崇礼】【万龙店】 | D42: 【万龙体验】零售商品仓 | E42: 99 | F42: 99 | G42: 微信4775收款 | H42: 【小程序】微信-WL | I42: 【万龙】肖志强 | J42: 订单号：41391
A43: 45626 | B43: XSD20241130000I | C43: 【总部】 | D43: 【旗舰】零售商品仓 | E43: 1180 | F43: 1180 | G43: 微信1865收款 | H43: 【小程序】微信-ZB | I43: 公司管理员
A44: 45626 | B44: XSD20241130000A | C44: 【崇礼】【万龙店】 | D44: 【万龙体验】零售商品仓 | E44: 199 | F44: 199 | G44: 微信4775收款 | H44: 【小程序】微信-WL | I44: 【万龙】肖志强 | J44: 微信小程序订单号：41273
A45: 45626 | B45: XSD20241201000I | C45: 【崇礼】【万龙店】 | D45: 【万龙体验】零售商品仓 | E45: 259 | F45: 259 | G45: 微信4775收款 | H45: 【小程序】微信-ZB | I45: 万龙_许进升 | J45: 雪蜡 | K45: 11.30七色米与小程序订单核对完成调账之后金额为：54982
A46: 45627 | B46: XSD20241201006A | C46: 【崇礼】【万龙店】 | D46: 【万龙体验】零售商品仓 | E46: 99 | F46: 99 | G46: 微信4775收款 | H46: 【小程序】微信-QJ | I46: 旗舰_修姜山 | J46: 订单号:41518
A47: 45627 | B47: XSD20241201007I | C47: 【崇礼】【万龙店】 | D47: 【万龙体验】零售商品仓 | E47: 198 | F47: 198 | G47: 微信4775收款 | H47: 【小程序】微信-WL | I47: 【万龙】肖志强 | J47: 订单号： 41520
A48: 45627 | B48: XSD20241201004A | C48: 【崇礼】【万龙店】 | D48: 【万龙体验】零售商品仓 | E48: 228 | F48: 228 | G48: 微信4775收款 | H48: 【小程序】微信-WL | I48: 万龙_张小飞 | J48: 订单号：41484
A49: 45627 | B49: XSD20241201003A | C49: 【崇礼】【万龙店】 | D49: 【万龙体验】零售商品仓 | E49: 30 | F49: 30 | G49: 微信4775收款 | H49: 【小程序】微信-WL | I49: 万龙_张小飞 | J49: 订单号：41467
A50: 45627 | B50: XSD20241201002A | C50: 【崇礼】【万龙店】 | D50: 【万龙体验】零售商品仓 | E50: 199 | F50: 199 | G50: 微信4775收款 | H50: 【小程序】微信-WL | I50: 【万龙】肖志强 | J50: 订单号：41459
A51: 45627 | B51: XSD20241201001A | C51: 【崇礼】【万龙店】 | D51: 【万龙体验】零售商品仓 | E51: 30 | F51: 30 | G51: 微信4775收款 | H51: 【小程序】微信-WL | I51: 【万龙】肖志强 | J51: 订单号：41458
A52: 45628 | B52: XSD20241202006I | C52: 【崇礼】【旗舰店】 | D52: 【旗舰】零售商品仓 | E52: 1180 | F52: 1180 | H52: 【小程序】微信-ZB | I52: 【旗舰】崔洋
A53: 45628 | B53: XSD20241202005A | C53: 【崇礼】【万龙店】 | D53: 【万龙体验】零售商品仓 | E53: 58 | F53: 58 | G53: 微信4775收款 | H53: 【小程序】微信-WL | I53: 【万龙】肖志强 | J53: 订单号：41557
A54: 45628 | B54: XSD20241202004A | C54: 【崇礼】【万龙店】 | D54: 【万龙体验】零售商品仓 | E54: 0 | F54: 0 | G54: 微信4775收款 | H54: 【小程序】微信-WL | I54: 【万龙】肖志强 | J54: 崔洋给客户弄报废了
A55: 45628 | B55: XSD20241202003A | C55: 【崇礼】【万龙店】 | D55: 【万龙体验】零售商品仓 | E55: 30 | F55: 30 | G55: 微信4775收款 | H55: 【小程序】微信-WL | I55: 【万龙】肖志强 | J55: 订单号：41538
A56: 45628 | B56: XSD20241202002A | C56: 【崇礼】【万龙店】 | D56: 【万龙体验】零售商品仓 | E56: 898 | F56: 898 | G56: 微信4775收款 | H56: 【小程序】微信-WL | I56: 【万龙】肖志强 | J56: 订单号：41530
A57: 45628 | B57: XSD20241202001A | C57: 【崇礼】【万龙店】 | D57: 【万龙体验】零售商品仓 | E57: 99 | F57: 99 | G57: 微信4775收款 | H57: 【小程序】微信-WL | I57: 【万龙】肖志强 | J57: 订单号：41530
A58: 45628 | B58: XSD20241202000A | C58: 【崇礼】【万龙店】 | D58: 【万龙体验】零售商品仓 | E58: 116 | F58: 116 | G58: 微信4775收款 | H58: 【小程序】微信-WL | I58: 【万龙】肖志强 | J58: 订单号：41530
A59: 45629 | B59: XSD20241203001A | C59: 【崇礼】【万龙店】 | D59: 【万龙体验】零售商品仓 | E59: 90 | F59: 90 | G59: 微信4775收款 | H59: 【小程序】微信-WL | I59: 【万龙】肖志强 | J59: 订单号：41574
A60: 45629 | B60: XSD20241203000A | C60: 【崇礼】【万龙店】 | D60: 【万龙体验】零售商品仓 | E60: 199 | F60: 199 | G60: 微信4775收款 | H60: 【小程序】微信-WL | I60: 万龙_张小飞 | J60: 41565
A61: 45631 | B61: XSD20241205006A | C61: 【北京】【南山店】 | D61: 【南山】零售商品仓 | E61: 0 | F61: 0 | H61: 【小程序】微信-NS | I61: 南山店员01
A62: 45631 | B62: XSD20241205005 | C62: 【总部】 | D62: 【旗舰】零售商品仓 | E62: 300 | F62: 300 | H62: 微信转账-LX | I62: 公司管理员 | J62: 批发业务 微信转布乖 提现8997
A63: 45631 | B63: XSD20241205004 | C63: 【总部】 | D63: 【旗舰】零售商品仓 | E63: 1584 | G63: 1584 | H63: 现金-ZB | I63: 【总部】布乖 | J63: 调换货品
A64: 45631 | B64: XSD20241205003A | C64: 【崇礼】【万龙店】 | D64: 【万龙体验】零售商品仓 | E64: 232 | F64: 232 | G64: 微信4775收款 | H64: 【小程序】微信-WL | I64: 万龙_张小飞 | J64: 41693
A65: 45631 | B65: XSD20241205002A | C65: 【北京】【南山店】 | D65: 【南山】零售商品仓 | E65: 1612 | F65: 1612 | H65: 【小程序】微信-NS | I65: 【南山】舒武新
A66: 45631 | B66: XSD20241205001A | C66: 【崇礼】【万龙店】 | D66: 【万龙体验】零售商品仓 | E66: 30 | F66: 30 | G66: 微信4775收款 | H66: 【小程序】微信-WL | I66: 【万龙】肖志强 | J66: 订单号：41630
A67: 45631 | B67: XSD20241205000A | C67: 【崇礼】【万龙店】 | D67: 【万龙体验】零售商品仓 | E67: 336 | F67: 336 | H67: 【小程序】微信-WL | I67: 万龙_张小飞 | J67: 41598 41597
A68: 45632 | B68: XSD20241206011A | C68: 【北京】【南山店】 | D68: 【南山】零售商品仓 | E68: 399 | F68: 399 | H68: 【小程序】微信-NS | I68: 南山_孙亚先
A69: 45632 | B69: XSD20241206010A | C69: 【北京】【南山店】 | D69: 【南山】零售商品仓 | E69: 69 | F69: 69 | H69: 京东收银-NS | I69: 南山_孙亚先
A70: 45632 | B70: XSD20241206009A | C70: 【北京】【南山店】 | D70: 【南山】零售商品仓 | E70: 158 | F70: 158 | H70: 【小程序】微信-NS | I70: 南山_孙亚先
A71: 45632 | B71: XSD20241206008A | C71: 【北京】【南山店】 | D71: 【南山】零售商品仓 | E71: 129 | F71: 129 | H71: 【小程序】微信-NS | I71: 南山_孙亚先
A72: 45632 | B72: XSD20241206007A | C72: 【北京】【南山店】 | D72: 【南山】零售商品仓 | E72: 3158 | F72: 3158 | H72: 【小程序】微信-NS | I72: 【南山】舒武新
A73: 45632 | B73: XSD20241206005A | C73: 【北京】【南山店】 | D73: 【南山】零售商品仓 | E73: 784 | F73: 784 | H73: 【小程序】微信-NS | I73: 【南山】张新健
A74: 45632 | B74: XSD20241206003A | C74: 【崇礼】【旗舰店】 | D74: 【旗舰】零售商品仓 | E74: 688 | F74: 688 | H74: 【小程序】微信-QJ | I74: 旗舰店员01
A75: 45632 | B75: XSD20241206002A | C75: 【崇礼】【万龙店】 | D75: 【万龙体验】零售商品仓 | E75: 258 | F75: 298 | H75: 【小程序】微信-WL | I75: 万龙_张小飞 | J75: 订单号：41667
A76: 45632 | B76: XSD20241206001A | C76: 【崇礼】【万龙店】 | D76: 【万龙体验】零售商品仓 | E76: 60 | F76: 60 | H76: 【小程序】微信-WL | I76: 【万龙】肖志强 | J76: 订单号：41668
A77: 45632 | B77: XSD20241206006A | C77: 【北京】【南山店】 | D77: 【南山】零售商品仓 | E77: 129 | F77: 129 | H77: 【小程序】微信-NS | I77: 【南山】张新健
A78: 45633 | B78: XSD20241207024I | C78: 【总部】 | D78: 【旗舰】零售商品仓 | E78: 400 | F78: 400 | H78: 银行转账-ZB | I78: 公司管理员 | J78: 哒哒转布乖 提现8997
A79: 45633 | B79: XSD20241207022I | C79: 【作废】回收无效仓库店 | D79: 【万龙体验】零售商品仓 | E79: 4900 | F79: 4900 | H79: 【小程序】微信-ZB | I79: 体验_张凯 | J79: 小程序41785
A80: 45633 | B80: XSD20241207020A | C80: 【北京】【南山店】 | D80: 【南山】零售商品仓 | E80: 129 | F80: 129 | H80: 京东收银-NS | I80: 南山_孙亚先
A81: 45633 | B81: XSD20241207021A | C81: 【北京】【南山店】 | D81: 【南山】零售商品仓 | E81: 316 | F81: 316 | H81: 【小程序】微信-NS | I81: 【南山】张新健 | J81: 林鹏带
A82: 45633 | B82: XSD20241207023A | C82: 【崇礼】【旗舰店】 | D82: 【旗舰】零售商品仓 | E82: 588 | F82: 588 | H82: 【小程序】微信-QJ | I82: 旗舰_修姜山
A83: 45633 | B83: XSD20241207017A | C83: 【北京】【南山店】 | D83: 【南山】零售商品仓 | E83: 300 | F83: 300 | H83: 现金-NS | I83: 【南山】张新健
A84: 45633 | B84: XSD20241207016A | C84: 【北京】【南山店】 | D84: 【南山】零售商品仓 | E84: 398 | F84: 398 | H84: 【小程序】微信-NS | I84: 南山_孙亚先
A85: 45633 | B85: XSD20241207018A | C85: 【崇礼】【旗舰店】 | D85: 【万龙服务】零售商品仓 | E85: 399 | F85: 359 | H85: 【小程序】微信-QJ | I85: 旗舰店员01 | J85: 雪蜡
A86: 45633 | B86: XSD20241207015A | C86: 【北京】【南山店】 | D86: 【南山】零售商品仓 | E86: 129 | F86: 129 | H86: 京东收银-NS | I86: 南山_孙亚先
A87: 45633 | B87: XSD20241207014A | C87: 【北京】【南山店】 | D87: 【南山】零售商品仓 | E87: 129 | F87: 129 | H87: 【小程序】微信-NS | I87: 【南山】舒武新
A88: 45633 | B88: XSD20241207013A | C88: 【崇礼】【万龙店】 | D88: 【万龙体验】零售商品仓 | E88: 60 | F88: 60 | H88: 【小程序】微信-WL | I88: 【万龙】肖志强 | J88: 订单号：41809
A89: 45633 | B89: XSD20241207012A | C89: 【崇礼】【万龙店】 | D89: 【万龙体验】零售商品仓 | E89: 30 | F89: 30 | H89: 【小程序】微信-WL | I89: 万龙_张小飞 | J89: 41804
A90: 45633 | B90: XSD20241207011A | C90: 【北京】【南山店】 | D90: 【南山】零售商品仓 | E90: 480 | F90: 480 | H90: 现金-NS | I90: 【南山】张新健
A91: 45633 | B91: XSD20241207010A | C91: 【北京】【南山店】 | D91: 【南山】零售商品仓 | E91: 4400 | F91: 4400 | H91: 现金-NS | I91: 【南山】张新健
A92: 45633 | B92: XSD20241207007A | C92: 【北京】【南山店】 | D92: 【南山】零售商品仓 | E92: 190 | F92: 190 | H92: 【小程序】微信-NS | I92: 【南山】张新健
A93: 45633 | B93: XSD20241207008A | C93: 【崇礼】【万龙店】 | D93: 【万龙体验】零售商品仓 | E93: 99 | F93: 99 | H93: 【小程序】微信-WL | I93: 【万龙】肖志强 | J93: 订单号：41783
A94: 45633 | B94: XSD20241207006I | C94: 【总部】 | D94: 【万龙体验】零售商品仓 | E94: 5600 | F94: 5600 | H94: 【小程序】微信-ZB | I94: 【总部】布乖 | J94: 小程序41772
A95: 45633 | B95: XSD20241207005A | C95: 【北京】【南山店】 | D95: 【南山】零售商品仓 | E95: 129 | F95: 129 | H95: 京东收银-NS | I95: 南山_孙亚先
A96: 45633 | B96: XSD20241207004A | C96: 【崇礼】【万龙店】 | D96: 【万龙体验】零售商品仓 | E96: 199 | F96: 199 | H96: 【小程序】微信-WL | I96: 万龙_张小飞 | J96: 41757
A97: 45633 | B97: XSD20241207003A | C97: 【崇礼】【万龙店】 | D97: 【万龙体验】零售商品仓 | E97: 30 | F97: 30 | H97: 【小程序】微信-WL | I97: 万龙_张小飞 | J97: 41745
A98: 45633 | B98: XSD20241207001A | C98: 【崇礼】【万龙店】 | D98: 【万龙体验】零售商品仓 | E98: 99 | F98: 99 | H98: 【小程序】微信-WL | I98: 万龙_张小飞 | J98: 41734
A99: 45633 | B99: XSD20241207000A | C99: 【崇礼】【万龙店】 | D99: 【万龙服务】零售商品仓 | E99: 449 | F99: 449 | H99: 【小程序】微信-WL | I99: 万龙_张小飞 | J99: 41747
A100: 45634 | B100: XSD20241208016A | C100: 【北京】【南山店】 | D100: 【南山】零售商品仓 | E100: 796 | F100: 796 | H100: 【小程序】微信-NS | I100: 【南山】舒武新
...

Sheet 备忘录
B1: 租赁收入 | F1: 雪蜡销售 | K1: 崇礼公司现金收入
A2: 2024.11.24 | B2: 1080 | C2: 支付宝收款 | D2: 苍杰报表中没有这两笔订单 | F2: 日期 | G2: 金额 | H2: 收款方式 | I2: 提现时间
A3: 2024.11.23 | B3: 610 | C3: 崔洋个人微信收款 | F3: 2024.11.23 | G3: 359 | H3: 微信4775
F4: 2024.11.26 | G4: 359 | H4: 8997提现 | I4: 12.6 | K4: 45605 | L4: XSD20241109001I | M4: 【总部】 | N4: 4650 | O4: 8997提现 | P4: 11.22提现
F5: 2024.11.30 | G5: 259 | H5: 微信4775 | K5: 45606 | L5: XSD20241110000I | M5: 【旗舰】租赁收入 | N5: 1300 | O5: 8997提现 | P5: 11.22提现
F6: 2024.11.30 | G6: 359 | H6: 微信4775 | K6: 45612 | L6: XSD20241116003A | M6: 【崇礼】【万龙店】 | N6: 200 | O6: 现金 | P6: 给崔洋了
F7: 2024.12.7 | G7: 359 | H7: 微信4775 | K7: 45619 | L7: XSD20241123004I | M7: 【总部】 | N7: 1809.5 | O7: 8997提现 | P7: 11.23提现
F8: 2024.12.8 | G8: 359 | H8: 8997提现 | I8: 12.12 | K8: 45619 | L8: XSD20241123005I | M8: 【总部】 | N8: 434.5 | O8: 8997提现 | P8: 11.23提现
F9: 2024.12.8 | G9: 359 | H9: 8997提现 | I9: 12.12 | K9: 45621 | L9: XSD20241125001I | M9: 【总部】 | N9: 4100 | P9: 11.25提现
A10: 特殊事项 | F10: 2024.12.15 | G10: 149 | H10: 微信4775 | K10: 45622 | L10: XSD20241126000I | M10: 【崇礼】【万龙店】 | N10: 359 | P10: 12.2提现
A11: 2025.1.9 | B11: 5000 | C11: 租赁客人丢失雪板，押金全部赔偿雪板，做到万龙体验中心零售收入中 | F11: 2024.12.15 | G11: 359 | H11: 微信4775 | K11: 45624 | L11: XSD20241128000A | M11: 【北京】【南山店】 | N11: 474 | O11: 8997提现 | P11: 11.28提现
F12: 2024.12.15 | G12: 359 | H12: 微信4775 | K12: 45626 | L12: XSD20241130004I | M12: 【崇礼】【旗舰店】 | N12: 7159 | O12: 8997提现 | P12: 11.30提现
F13: 2024.12.18 | G13: 359 | H13: 8997提现 | K13: 45619 | M13: 南山雪票款 | N13: 610 | O13: 现金
F14: 2024.12.21 | G14: 299 | H14: 微信4775 | K14: 45631 | L14: XSD20241205005 | M14: 【总部】 | N14: 300 | O14: 8997提现 | P14: 12.5提现
F15: 2024.12.22 | G15: 299 | H15: 微信4775 | K15: 45633 | L15: XSD20241207024I | M15: 【总部】 | N15: 400 | O15: 8997提现 | P15: 12.7提现
F16: 2024.12.23 | G16: 359 | H16: 微信3448 | K16: 45637 | L16: XSD20241211008A | M16: 【北京】【南山店】 | N16: 560 | O16: 8997提现 | P16: 12.12提现
F17: 2024.12.28 | G17: 359 | H17: 微信4775 | K17: 45640 | L17: XSD20241214027I | M17: 【崇礼】【万龙店】 | N17: 180 | O17: 8997提现 | P17: 12.12提现 | Q17: 补差
F18: 2024.12.29 | G18: 259 | H18: 微信4775 | K18: 45641 | L18: XSD20241215013I | M18: 【崇礼】【万龙店】 | N18: 359 | O18: 现金 | P18: 4.15提现
F19: 2024.12.29 | G19: 259 | H19: 微信4775 | K19: 45641 | L19: XSD20241215012I | M19: 【崇礼】【万龙店】 | N19: 359 | O19: 现金 | P19: 4.15提现
F20: 2024.12.31 | G20: 259 | H20: 京东收银 | K20: 45644 | L20: XSD20241218013I | M20: 【崇礼】【旗舰店】 | N20: 359 | P20: 布乖
F21: 2025.1.3 | G21: 359 | H21: 微信4775 | K21: 45644 | M21: 万龙体验中心 | N21: 1500 | O21: 8997提现 | P21: 1.19提现
F22: 2025.1.4 | G22: 359 | K22: 45648 | L22: XSD20241222011I | M22: 【崇礼】【旗舰店】 | N22: 6300 | O22: 8997提现 | P22: 12.22提现
F23: 2025.1.4 | G23: 259 | K23: 45648 | L23: XSD20241222022I | M23: 【崇礼】【万龙店】 | N23: 13200 | O23: 8997提现 | P23: 12.22提现
F24: 2025.1.4 | G24: 259 | K24: 45651 | L24: XSD20241225001I | M24: 【崇礼】【旗舰店】 | N24: 1500 | O24: 现金 | P24: 布乖 | Q24: 崔洋开单
F25: 2025.1.5 | G25: 359 | K25: 45652 | L25: XSD20241226003I | M25: 【崇礼】【旗舰店】 | N25: 1000 | O25: 现金 | P25: 4.15提现
F26: 2025.1.5 | G26: 359 | K26: 45676 | L26: XSD20250119011I | M26: 【崇礼】【旗舰店】 | N26: 1670 | O26: 8997提现 | P26: 1.19提现
F27: 2025.1.11 | G27: 259 | K27: 45691 | L27: XSD20250203016I | M27: 【崇礼】【旗舰店】 | N27: 4300 | O27: 8997提现 | P27: 2.6提现
F28: 2025.1.12 | G28: 259 | K28: 45694 | L28: XSD20250206025I | M28: 【总部】 | N28: 4700 | O28: 8997提现 | P28: 2.6提现
F29: 2025.1.12 | G29: 259 | K29: 45697 | L29: XSD20250209017I | M29: 【崇礼】【旗舰店】 | N29: 796 | O29: 现金 | P29: 4.15提现
F30: 2025.1.12 | G30: 259 | K30: 45697 | L30: XSD20250208011I | M30: 公司管理员 | N30: 759 | O30: 现金 | P30: 4.15提现
F31: 2025.1.19 | G31: 259 | K31: 45704 | L31: XSD20250216000I | M31: 【总部】布乖 | N31: 4900 | O31: 8997 | P31: 2.15提现
K32: 45689 | L32: XSD20250201037I | M32: 【总部】 | N32: 800 | O32: 银行转账-ZB | P32: 2.1提现
K33: 45689 | L33: XSD20250201029I | M33: 【崇礼】【旗舰店】 | N33: 100 | O33: 现金 | P33: 4.15提现
K34: 45699 | L34: XSD20250211009I | M34: 【总部】布乖 | N34: 4900 | O34: 8997 | P34: 2.11提现
K35: 45713 | L35: XSD20250225004I | M35: 【总部】布乖 | N35: 4700 | O35: 银行转账-ZB
C36: 南山现金收入 | K36: 45729 | L36: XSD20250312000 | M36: 【总部】 | N36: 560 | O36: 银行转账-ZB
C37: 45626 | D37: XSD20241130003A | E37: 【北京】【南山店】 | F37: 4290 | G37: 现金 | K37: 45732 | L37: XSD20250316004 | M37: 【崇礼】【万龙店】 | N37: 1400 | O37: 银行转账 | P37: 2025.4.11
C38: 45633 | D38: XSD20241207017A | E38: 【北京】【南山店】 | F38: 300 | G38: 现金 | N38: 760
C39: 45633 | D39: XSD20241207011A | E39: 【北京】【南山店】 | F39: 480 | G39: 现金
C40: 45633 | D40: XSD20241207010A | E40: 【北京】【南山店】 | F40: 4400 | G40: 现金
C41: 45639 | D41: XSD20241213007A | E41: 【北京】【南山店】 | F41: 2100 | G41: 现金
C42: 45641 | D42: XSD20241215005A | E42: 【北京】【南山店】 | F42: 99 | G42: 现金
C43: 45635 | D43: XSD20241209002A | E43: 【北京】【南山店】 | F43: 130 | G43: 现金
C44: 45654 | D44: XSD20241228018A | E44: 【北京】【南山店】 | F44: 1360 | G44: 现金
C45: 45654 | D45: XSD20241228017A | E45: 【北京】【南山店】 | F45: 2500 | G45: 现金
C46: 45654 | D46: XSD20241228005A | E46: 【北京】【南山店】 | F46: 336 | G46: 现金
C47: 45654 | D47: XSD20241228019A | E47: 【北京】【南山店】 | F47: 140 | G47: 现金
C48: 45672 | D48: XSD20250115001A | E48: 【北京】【南山店】 | F48: 198 | G48: 现金
C49: 45673 | D49: XSD20250116011A | E49: 【北京】【南山店】 | F49: 100 | G49: 现金
C50: 45687 | D50: XSD20250130010A | E50: 【北京】【南山店】 | F50: 600 | G50: 现金
... C59: 45688 | D59: 租赁业务 | E59: 【北京】【南山店】 | F59: 80 | G59: 现金
F60: 26498
E61: 零售收入 | F61: ==25986-28 -> 25958
E62: 租赁收入 | F62: 540

Sheet 小程序零售报表
A1: 日期 | B1: 七色米订单号 | C1: 商品条码 | D1: 市场价 | E1: 成交价 | F1: 订单号 | G1: 门店 | H1: 姓名 | I1: 电话 | J1: 订单金额（标粉色为七色米未做单） | K1: 调整金额（与七色米对比） | L1: 时间 | M1: 收款方式 | N1: 销售 | O1: 备注
J2: 此两项合计金额为到账金额
A3: 45747 | B3: XSD20241114000I | D3: 858 | E3: 320 | F3: 54082 | G3: 崇礼旗舰店 | J3: 320 | L3: 0.77758102 | M3: 京东收银 | N3: 布乖（个人） | O3: 补2024.11.14订单
A4: 45603 | B4: XSD20241107000 | D4: 14180 | E4: 8070 | F4: 40585 | G4: 崇礼旗舰店 | H4: 吕原野先生 | I4: 17542913333 | J4: 8070 | K4: 0 | L4: 0.94638889 | M4: 京东收银 | N4: 布乖
A5: 45605 | B5: XSD20241109001I | D5: 6344 | E5: 4650 | F5: 40640 | G5: 崇礼旗舰店 | H5: 高嵩先生 | J5: 4650 | K5: 0 | L5: 0.92086806 | M5: 现金 | N5: 布乖
A6: 45605 | B6: null | D6: 1490 | E6: 790 | F6: 40635 | G6: 万龙体验中心 | H6: 霍先生 | I6: 13901273805 | J6: 790 | K6: 0 | L6: 0.7675463 | M6: 微信支付 | N6: 布乖
A7: 45607 | B7: 紧急开单 | D7: 3780 | E7: 3780 | F7: 40676 | G7: 万龙体验中心 | H7: 陈美红女士 | I7: 13510110412 | J7: 3780 | K7: 0 | L7: 0.56416667 | M7: 微信支付 | N7: 肖志强
A8: 45610 | B8: 紧急开单 | D8: 3999 | E8: 2400 | F8: 40729 | G8: 崇礼旗舰店 | H8: 崔杰女士 | I8: 19213045200 | J8: 2400 | K8: 0 | L8: 0.8271412 | M8: 微信支付 | O8: 富龙教练，6折
A9: 45610 | B9: XSD20241114000 | D9: 698 | E9: 320 | F9: 40718 | G9: 崇礼旗舰店 | H9: 孙天时先生 | I9: 13839011338 | J9: 320 | K9: 0 | L9: 0.45260417 | M9: 京东收银 | N9: 布乖 | O9: 实际订单日期2024.11.2
A10: 45610 | B10: XSD20241103000I | D10: 398 | E10: 398 | F10: 40717 | G10: 崇礼旗舰店 | H10: 一尘女士 | J10: 398 | K10: -9 | L10: 0.445625 | M10: 京东收银 | N10: 布乖 | O10: 实际业务日期2024.11.3
A11: 45610 | B11: XSD20241109001I | D11: 6344 | E11: 4650 | F11: 40716 | G11: 崇礼旗舰店 | H11: 高嵩先生 | J11: 4650 | L11: 0.44478009 | M11: 现金 | N11: 布乖 | O11: 实际订单日期2024.11.9
A12: 45610 | B12: XSD20241110000I | D12: 1500 | E12: 1300 | F12: 40715 | G12: 崇礼旗舰店 | H12: 高嵩先生 | J12: 1300 | K12: 0 | L12: 0.44292824 | M12: 现金 | N12: 布乖 | O12: 业务实际日期2024.11.10
A13: 45612 | B13: 紧急开单 | D13: 58 | E13: 58 | F13: 40844 | G13: 万龙体验中心 | H13: 崔洋 | I13: 13910231129 | J13: 58 | L13: 0.85055556 | M13: 微信支付 | N13: 崔洋
A14: 45612 | B14: null | D14: 200 | E14: 200 | F14: 40825 | G14: 万龙体验中心 | H14: 肖志强（个人）先生 | I14: 18612317853 | J14: 200 | L14: 0.67675926 | M14: 现金 | N14: 肖志强
A15: 45612 | B15: 紧急开单 | D15: 558 | E15: 558 | F15: 40787 | G15: 万龙体验中心 | H15: 肖志强（个人）先生 | I15: 18612317853 | J15: 558 | L15: 0.67189815 | M15: 微信支付 | N15: 肖志强
A16: 45612 | B16: 紧急开单 | D16: 116 | E16: 116 | F16: 40780 | G16: 万龙体验中心 | H16: 宗佳女士 | I16: 19932327706 | J16: 116 | L16: 0.47974537 | M16: 微信支付 | N16: 肖志强
A17: 45612 | B17: 紧急开单 | D17: 128 | E17: 128 | F17: 40752 | G17: 万龙体验中心 | H17: 肖志强 | I17: 18612317853 | J17: 128 | L17: 0.34902778 | M17: 微信支付 | N17: 肖志强
A18: 45613 | B18: 紧急开单 | D18: 149 | E18: 149 | F18: 40888 | G18: 万龙体验中心 | H18: 朱女士 | I18: 18018592806 | J18: 149 | L18: 0.70641204 | M18: 微信支付 | N18: (个人)张小飞
A19: 45613 | B19: 紧急开单 | D19: 109 | E19: 109 | F19: 40857 | G19: 万龙体验中心 | H19: 付 | I19: 15635172829 | J19: 109 | L19: 0.46241898 | M19: 微信支付 | N19: (个人)张小飞
A20: 45614 | B20: null | D20: 30 | E20: 30 | F20: 40923 | G20: 万龙体验中心 | H20: 肖志强（个人）先生 | I20: 18612317853 | J20: 30 | L20: 0.76173611 | M20: 微信支付 | N20: 肖志强
A21: 45619 | B21: XSD20241123004I | D21: 3950 | E21: 1809.5 | F21: 41080 | G21: 崇礼旗舰店 | H21: 赵文广先生 | J21: 1809.5 | L21: 0.90758102 | M21: 现金 | N21: 布乖 | O21: 银行转账
A22: 45619 | B22: XSD20241123005I | D22: 790 | E22: 434.5 | F22: 41079 | G22: 崇礼旗舰店 | H22: 赵文广先生 | J22: 434.5 | L22: 0.90662037 | M22: 现金 | N22: 布乖
A23: 45619 | B23: null | D23: 399 | E23: 359 | F23: 41068 | G23: 万龙体验中心 | H23: 张骞先生 | I23: 13693547369 | J23: 359 | L23: 0.74362269 | M23: 微信支付 | N23: 布乖
A24: 45619 | B24: 紧急开单 | D24: 199 | E24: 199 | F24: 41014 | G24: 万龙体验中心 | J24: 199 | L24: 0.42001157 | M24: 微信支付 | N24: (个人)张小飞
A25: 45619 | B25: null | D25: 30 | E25: 30 | F25: 41005 | G25: 万龙体验中心 | H25: 先生 | I25: 18610492765 | J25: 30 | L25: 0.38728009 | M25: 微信支付 | N25: 肖志强
A26: 45620 | B26: null | D26: 3780 | E26: 3780 | F26: 41111 | G26: 万龙体验中心 | H26: 王婧婧女士 | I26: 15357199988 | J26: 3780 | L26: 0.5940162 | M26: 微信支付 | N26: 肖志强 | O26: 儿童成长计划
A27: 45620 | B27: null | D27: 890 | E27: 445 | F27: 41098 | G27: 崇礼旗舰店 | H27: 姜楠女士 | I27: 15210988580 | J27: 445 | L27: 0.51644676 | M27: 微信支付 | N27: 布乖
G28: 崇礼旗舰店 | J28: 0 | K28: 4100 | M28: 提现8997 | N28: 布乖 | O28: 布乖
A29: 45621 | B29: null | D29: 30 | E29: 30 | F29: 41155 | G29: 万龙体验中心 | H29: 朱先生 | I29: 15635261688 | J29: 30 | L29: 0.79612269 | M29: 微信支付 | N29: 肖志强
A30: 45621 | B30: null | D30: 58 | E30: 58 | F30: 41154 | G30: 万龙体验中心 | H30: 郝先生 | I30: 17660406631 | J30: 58 | L30: 0.78623843 | M30: 微信支付 | N30: 肖志强
A31: 45621 | B31: null | D31: 58 | E31: 58 | F31: 41139 | G31: 万龙体验中心 | H31: 赵女士 | I31: 19535784886 | J31: 58 | L31: 0.43165509 | M31: 微信支付 | N31: 肖志强
A32: 45622 | B32: XSD20241126000I | D32: 399 | E32: 359 | F32: 41165 | G32: 万龙体验中心 | H32: 阿振 | J32: 359 | L32: 0.47530093 | M32: 现金 | N32: 布乖 | O32: 实际是微信转账提现
A33: 45624 | B33: null | D33: 4780 | E33: 3080 | F33: 41215 | G33: 崇礼旗舰店 | H33: 沁城先生 | I33: 17278866532 | J33: 3080 | L33: 0.95138889 | M33: 微信支付 | N33: 布乖
A34: 45624 | B34: XSD20241128000A | D34: 790 | E34: 474 | F34: 41204 | G34: 南山 | H34: 邢春杰先生 | I34: 18001077061 | J34: 474 | L34: 0.54810185 | M34: 现金 | O34: 实际微信转布乖
A35: 45625 | B35: null | D35: 2200 | E35: 1500 | F35: 41243 | G35: 万龙体验中心 | H35: 黄女士 | I35: 13161892380 | J35: 1500 | L35: 0.75157407 | M35: 微信支付 | N35: 布乖
A36: 45625 | B36: null | D36: 174 | E36: 174 | F36: 41218 | G36: 万龙体验中心 | J36: 174 | L36: 0.36287037 | M36: 微信支付 | N36: 肖志强
A37: 45625 | B37: 紧急开单 | D37: 58 | E37: 58 | F37: 41216 | G37: 万龙体验中心 | H37: 吕 | I37: 17542913333 | J37: 58 | L37: 0.32701389 | M37: 微信支付 | N37: (个人)张小飞
A38: 45626 | B38: XSD20241130005I | D38: 6080 | E38: 6080 | F38: 41451 | G38: 万龙体验中心 | H38: 李聪女士 | I38: 18210198199 | J38: 6080 | L38: 0.87922454 | M38: 微信支付 | N38: 布乖
A39: 45626 | B39: XSD20241130004I | D39: 8156 | E39: 7159 | F39: 41450 | G39: 崇礼旗舰店 | H39: 小A老师女士 | I39: 13806266161 | J39: 7159 | L39: 0.86989583 | M39: 现金 | N39: 布乖 | O39: 实际微信转布乖
A40: 45626 | B40: XSD20241130003A | D40: 7150 | E40: 4290 | F40: 41440 | G40: 南山 | J40: 4290 | L40: 0.74315972 | M40: 现金 | N40: 张新健
A41: 45626 | B41: null | D41: 99 | E41: 99 | F41: 41405 | G41: 万龙体验中心 | J41: 99 | L41: 0.56638889 | M41: 微信支付 | N41: (个人)张小飞
A42: 45626 | B42: 紧急开单 | D42: 298 | E42: 298 | F42: 41396 | G42: 万龙体验中心 | J42: 298 | L42: 0.55097222 | M42: 微信支付 | N42: (个人)张小飞
B43: 紧急开单 | D43: 298 | E43: 298 | F43: 41396 | G43: 万龙体验中心 | J43: 0 | O43: 已退款
A44: 45626 | B44: 紧急开单 | D44: 99 | E44: 99 | F44: 41391 | G44: 万龙体验中心 | J44: 99 | L44: 0.53515046 | M44: 微信支付 | N44: 肖志强
A45: 45626 | B45: null | D45: 359 | E45: 359 | F45: 41377 | G45: 万龙体验中心 | H45: 杨女士 | I45: 18611849921 | J45: 359 | L45: 0.51166667 | M45: 微信支付 | N45: 樊佳飞
A46: 45626 | B46: null | D46: 259 | E46: 259 | F46: 41299 | G46: 万龙体验中心 | H46: 张先生 | I46: 18787068813 | J46: 259 | L46: 0.44628472 | M46: 微信支付
A47: 45626 | B47: XSD20241130000I | D47: 1780 | E47: 1180 | F47: 41277 | G47: 崇礼旗舰店 | H47: 周萌先生 | I47: 13426377713 | J47: 1180 | L47: 0.41528935 | M47: 微信支付 | N47: 布乖
A48: 45626 | B48: 紧急开单 | D48: 199 | E48: 199 | F48: 41272 | G48: 万龙体验中心 | H48: 肖志强 | I48: 18612317853 | J48: 199 | L48: 0.39077546 | M48: 微信支付 | N48: (个人)张小飞 | O48: 11月报表与七色米核对完成
A49: 45627 | B49: 紧急开单 | D49: 198 | E49: 198 | F49: 41520 | G49: 万龙体验中心 | J49: 198 | L49: 0.75385417 | M49: 微信支付 | N49: 肖志强
A50: 45627 | B50: 紧急开单 | D50: 99 | E50: 99 | F50: 41518 | G50: 万龙体验中心 | J50: 99 | L50: 0.72869213 | M50: 微信支付 | N50: 肖志强
A51: 45627 | B51: 紧急开单 | D51: 228 | E51: 228 | F51: 41484 | G51: 万龙体验中心 | J51: 228 | L51: 0.47103009 | M51: 微信支付 | N51: (个人)张小飞
A52: 45627 | B52: 紧急开单 | D52: 30 | E52: 30 | F52: 41467 | G52: 万龙体验中心 | H52: (个人)张小飞 | I52: 15731361444 | J52: 30 | L52: 0.41935185 | M52: 微信支付 | N52: 肖志强
A53: 45627 | B53: 紧急开单 | D53: 199 | E53: 199 | F53: 41459 | G53: 万龙体验中心 | J53: 199 | L53: 0.38018519 | M53: 微信支付 | N53: 肖志强
A54: 45627 | B54: 紧急开单 | D54: 30 | E54: 30 | F54: 41458 | G54: 万龙体验中心 | H54: 肖志强 | I54: 18612317853 | J54: 30 | L54: 0.37674769 | M54: 微信支付 | N54: 肖志强
A55: 45628 | B55: 紧急开单 | D55: 58 | E55: 58 | F55: 41557 | G55: 万龙体验中心 | J55: 58 | L55: 0.78271991 | M55: 微信支付 | N55: 肖志强
A56: 45628 | B56: null | D56: 1400 | E56: 1180 | F56: 41556 | G56: 崇礼旗舰店 | H56: 荀女士 | I56: 15901135216 | J56: 1180 | L56: 0.72606481 | M56: 微信支付 | N56: 布乖
A57: 45628 | B57: 紧急开单 | D57: 30 | E57: 30 | F57: 41538 | G57: 万龙体验中心 | J57: 30 | L57: 0.48765046 | M57: 微信支付 | N57: 肖志强
A58: 45628 | B58: null | D58: 1113 | E58: 1113 | F58: 41530 | G58: 万龙体验中心 | H58: 张 | I58: 15776321790 | J58: 1113 | L58: 0.41378472 | M58: 微信支付 | N58: 肖志强
A59: 45629 | B59: 紧急开单 | D59: 90 | E59: 90 | F59: 41574 | G59: 万龙体验中心 | J59: 90 | L59: 0.56976852 | M59: 微信支付 | N59: 肖志强
A60: 45629 | B60: 紧急开单 | D60: 199 | E60: 199 | F60: 41565 | G60: 万龙体验中心 | J60: 199 | L60: 0.48241898 | M60: 微信支付 | N60: (个人)张小飞
A61: 45630 | B61: 紧急开单 | D61: 168 | E61: 168 | F61: 41598 | G61: 万龙体验中心 | J61: 168 | L61: 0.43784722 | M61: 微信支付 | N61: (个人)张小飞
A62: 45630 | B62: 紧急开单 | D62: 168 | E62: 168 | F62: 41597 | G62: 万龙体验中心 | J62: 168 | L62: 0.43722222 | M62: 微信支付 | N62: (个人)张小飞
A63: 45631 | B63: XSD20241205005 | D63: 419 | E63: 300 | F63: 41643 | G63: 崇礼旗舰店 | H63: 娜姐女士 | J63: 300 | L63: 0.51189815 | M63: 现金 | N63: 布乖 | O63: 实际微信转账布乖 提现8997
A64: 45631 | B64: XSD20241205002A | D64: 2190 | E64: 1612 | F64: 41640 | G64: 南山 | H64: 施先生 | I64: 13501138725 | J64: 1612 | L64: 0.47361111 | M64: 微信支付 | N64: 张新健
A65: 45631 | B65: 紧急开单 | D65: 232 | E65: 232 | F65: 41639 | G65: 万龙体验中心 | J65: 232 | L65: 0.4725463 | M65: 微信支付 | N65: (个人)张小飞
A66: 45631 | B66: 紧急开单 | D66: 30 | E66: 30 | F66: 41630 | G66: 万龙体验中心 | J66: 30 | L66: 0.4022338 | M66: 微信支付 | N66: 肖志强
A67: 45632 | B67: XSD20241206011A | D67: 589 | E67: 399 | F67: 41732 | G67: 南山 | J67: 399 | L67: 0.92193287 | M67: 微信支付 | N67: 南山_孙亚先
A68: 45632 | B68: XSD20241206010A | D68: 69 | E68: 69 | F68: 41726 | G68: 南山 | H68: 王女士 | J68: 69 | L68: 0.84438657 | M68: 京东收银 | N68: 南山_孙亚先
A69: 45632 | B69: XSD20241206009A | D69: 499 | E69: 158 | F69: 41725 | G69: 南山 | J69: 158 | L69: 0.83710648 | M69: 微信支付 | N69: 南山_孙亚先
A70: 45632 | B70: XSD20241206008A | D70: 199 | E70: 129 | F70: 41724 | G70: 南山 | J70: 129 | L70: 0.81092593 | M70: 微信支付 | N70: 南山_孙亚先
A71: 45632 | B71: XSD20241206007A | D71: 4328 | E71: 3158 | F71: 41722 | G71: 南山 | H71: 先生 | I71: 13910237667 | J71: 3158 | L71: 0.79430556 | M71: 微信支付 | N71: 舒武新
A72: 45632 | B72: XSD20241206004A | D72: 980 | E72: 784 | F72: 41720 | G72: 南山 | H72: 杨 | I72: 18765941333 | J72: 784 | L72: 0.7621412 | M72: 微信支付 | N72: 张新健
A73: 45632 | B73: 紧急开单 | D73: 688 | E73: 688 | F73: 41717 | G73: 崇礼旗舰店 | H73: 刘先生 | I73: 15062511147 | J73: 688 | L73: 0.69813657 | M73: 微信支付 | N73: 樊佳飞
A74: 45632 | B74: XSD20241206000A | D74: 199 | E74: 129 | F74: 41675 | G74: 南山 | H74: 杜 | I74: 18510527851 | J74: 129 | L74: 0.45601852 | M74: 微信支付 | N74: 张新健
A75: 45632 | B75: 紧急开单 | D75: 60 | E75: 60 | F75: 41668 | G75: 万龙体验中心 | J75: 60 | L75: 0.41196759 | M75: 微信支付 | N75: 肖志强
A76: 45632 | B76: null | D76: 298 | E76: 298 | F76: 41667 | G76: 万龙体验中心 | J76: 298 | L76: 0.41082176 | M76: 微信支付 | N76: (个人)张小飞
A77: 45633 | B77: XSD20241207024I | D77: 698 | E77: 400 | F77: 41885 | G77: 崇礼旗舰店 | H77: 晋哒哒 | J77: 400 | L77: 0.91795139 | M77: 现金 | N77: 布乖
A78: 45633 | B78: XSD20241207021A | D78: 396 | E78: 316 | F78: 41879 | G78: 南山 | H78: 女士 | I78: 18733844444 | J78: 316 | L78: 0.81537037 | M78: 微信支付 | N78: 张新健
A79: 45633 | B79: XSD20241207020A | D79: 199 | E79: 129 | F79: 41878 | G79: 南山 | H79: 王先生 | J79: 129 | L79: 0.80652778 | M79: 京东收银 | N79: 南山_孙亚先
A80: 45633 | B80: 紧急开单 | D80: 688 | E80: 588 | F80: 41868 | G80: 崇礼旗舰店 | H80: 梁女士 | I80: 18503867999 | J80: 588 | L80: 0.75819444 | M80: 微信支付 | N80: 樊佳飞
A81: 45633 | B81: XSD20241207017A | D81: 380 | E81: 300 | F81: 41862 | G81: 南山 | H81: 储先生 | I81: 15010580216 | J81: 300 | L81: 0.73334491 | M81: 现金 | N81: 张新健
A82: 45633 | B82: XSD20241207016A | D82: 899 | E82: 398 | F82: 41850 | G82: 南山 | H82: 孙先生 | J82: 398 | L82: 0.70423611 | M82: 微信支付 | N82: 南山_孙亚先
A83: 45633 | B83: XSD20241207015A | D83: 199 | E83: 129 | F83: 41816 | G83: 南山 | H83: 陈女士 | J83: 129 | L83: 0.60537037 | M83: 京东收银 | N83: 南山_孙亚先
A84: 45633 | B84: XSD20241207014A | D84: 199 | E84: 129 | F84: 41813 | G84: 南山 | J84: 129 | L84: 0.59085648 | M84: 微信支付 | N84: 舒武新
A85: 45633 | B85: 紧急开单 | D85: 359 | E85: 359 | F85: 41810 | G85: 万龙体验中心 | H85: 张先生 | I85: 13148738667 | J85: 359 | L85: 0.57759259 | M85: 微信支付 | N85: 樊佳飞
A86: 45633 | B86: 紧急开单 | D86: 60 | E86: 60 | F86: 41809 | G86: 万龙体验中心 | J86: 60 | L86: 0.57674769 | M86: 微信支付 | N86: 肖志强
A87: 45633 | B87: 紧急开单 | D87: 30 | E87: 30 | F87: 41804 | G87: 万龙体验中心 | J87: 30 | L87: 0.56528935 | M87: 微信支付 | N87: (个人)张小飞
A88: 45633 | B88: XSD20241207011A | D88: 680 | E88: 480 | F88: 41801 | G88: 南山 | J88: 480 | L88: 0.55085648 | M88: 现金 | N88: 张新健
A89: 45633 | B89: XSD20241207009A | D89: 8800 | E89: 4400 | F89: 41796 | G89: 南山 | H89: 储先生 | I89: 15010580216 | J89: 4400 | L89: 0.53989583 | M89: 现金 | N89: 张新健
A90: 45633 | B90: XSD20241207007A | D90: 400 | E90: 190 | F90: 41786 | G90: 南山 | H90: 石洋 | I90: 15810020350 | J90: 190 | L90: 0.50378472 | M90: 微信支付 | N90: 张新健
A91: 45633 | B91: null | D91: 8598 | E91: 4900 | F91: 41785 | G91: 万龙体验中心 | H91: 请别吃了太阳先生 | I91: 18519145143 | J91: 4900 | L91: 0.50222222 | M91: 微信支付 | N91: 布乖
A92: 45633 | B92: 紧急开单 | D92: 99 | E92: 99 | F92: 41783 | G92: 万龙体验中心 | J92: 99 | L92: 0.49986111 | M92: 微信支付 | N92: 肖志强
A93: 45633 | B93: null | D93: 7500 | E93: 5600 | F93: 41772 | G93: 万龙体验中心 | H93: 王晓雨先生 | I93: 18611346090 | J93: 5600 | L93: 0.46878472 | M93: 微信支付 | N93: 布乖
A94: 45633 | B94: XSD20241207005A | D94: 199 | E94: 129 | F94: 41768 | G94: 南山 | J94: 129 | L94: 0.45146991 | M94: 京东收银 | N94: 南山_孙亚先
A95: 45633 | B95: 紧急开单 | D95: 199 | E95: 199 | F95: 41757 | G95: 万龙体验中心 | J95: 199 | L95: 0.41895833 | M95: 微信支付 | N95: (个人)张小飞
A96: 45633 | B96: 紧急开单 | D96: 449 | E96: 449 | F96: 41747 | G96: 万龙体验中心 | J96: 449 | L96: 0.39043981 | M96: 微信支付 | N96: (个人)张小飞
A97: 45633 | B97: 紧急开单 | D97: 30 | E97: 30 | F97: 41745 | G97: 万龙体验中心 | J97: 30 | L97: 0.38184028 | M97: 微信支付 | N97: (个人)张小飞
A98: 45633 | B98: 紧急开单 | D98: 99 | E98: 99 | F98: 41743 | G98: 万龙体验中心 | J98: 99 | L98: 0.38069444 | M98: 微信支付 | N98: (个人)张小飞
A99: 45634 | B99: XSD20241208016A | D99: 898 | E99: 796 | F99: 41985 | G99: 南山 | H99: 舒武新 | I99: 13693171170 | J99: 796 | L99: 0.81627315 | M99: 微信支付 | N99: 舒武新
A100: 45634 | B100: XSD20241208013A | D100: 199 | E100: 128 | F100: 41984 | G100: 南山 | J100: 128 | L100: 0.81078704 | M100: 京东收银 | N100: 张新健
...

Sheet 万龙雪票
A1: `2024-12-19 22:26:14 | B1: `wxd1310896f2aa68bb | C1: `1636140745 | D1: `0 | E1: ` | F1: `4200002363202412196830551366 | G1: `QJ_XP_20241219_042754_ZF_01 | H1: `oHdTn5Wlwy37YA6kmJP6zE9AoTlI | I1: `JSAPI | J1: `SUCCESS | K1: `BOC_CREDIT | L1: `CNY | M1: `0.14 | N1: `0.00 | O1: `0 | P1: `0 | Q1: `0.00 | R1: `0.00 | S1: ` | T1: ` | U1: `租赁 | V1: ` | W1: `0.00000 | X1: `0.54% | Y1: 0.14 | Z1: 0
A2: `2024-12-19 22:09:30 | B2: `wxd1310896f2aa68bb | C2: `1636140745 | D2: `0 | E2: ` | F2: `4200002368202412190711419979 | G2: `QJ_XP_20241219_042748_ZF_01 | H2: `oHdTn5Wlwy37YA6kmJP6zE9AoTlI | I2: `JSAPI | J2: `SUCCESS | K2: `BOC_CREDIT | L2: `CNY | M2: `0.11 | N2: `0.00 | O2: `0 | P2: `0 | Q2: `0.00 | R2: `0.00 | S2: ` | T2: ` | U2: `租赁 | V2: ` | W2: `0.00000 | X2: `0.54% | Y2: 0.11 | Z2: 0 | AA2: `
A3: `2024-12-19 22:56:25 | B3: `wxd1310896f2aa68bb | C3: `1636140745 | D3: `0 | E3: ` | F3: `4200002370202412197726571637 | G3: `QJ_XP_20241219_042759_ZF_01 | H3: `oHdTn5Wlwy37YA6kmJP6zE9AoTlI | I3: `JSAPI | J3: `SUCCESS | K3: `BOC_CREDIT | L3: `CNY | M3: `0.08 | N3: `0.00 | O3: `0 | P3: `0 | Q3: `0.00 | R3: `0.00 | S3: ` | T3: ` | U3: `租赁 | V3: ` | W3: `0.00000 | X3: `0.54% | Y3: 0.08 | Z3: 0 | AA3: `
A4: `2024-12-19 22:39:30 | B4: `wxd1310896f2aa68bb | C4: `1636140745 | D4: `0 | E4: ` | F4: `4200002373202412194657595334 | G4: `QJ_XP_20241219_042755_ZF_01 | H4: `oHdTn5Wlwy37YA6kmJP6zE9AoTlI | I4: `JSAPI | J4: `SUCCESS | K4: `BOC_CREDIT | L4: `CNY | M4: `0.14 | N4: `0.00 | O4: `0 | P4: `0 | Q4: `0.00 | R4: `0.00 | S4: ` | T4: ` | U4: `租赁 | V4: ` | W4: `0.00000 | X4: `0.54% | Y4: 0.14 | Z4: 0 | AA4: `
A5: `2024-12-19 22:50:46 | B5: `wxd1310896f2aa68bb | C5: `1636140745 | D5: `0 | E5: ` | F5: `4200002383202412192767242960 | G5: `QJ_XP_20241219_042757_ZF_01 | H5: `oHdTn5Wlwy37YA6kmJP6zE9AoTlI | I5: `JSAPI | J5: `SUCCESS | K5: `BOC_CREDIT | L5: `CNY | M5: `0.14 | N5: `0.00 | O5: `0 | P5: `0 | Q5: `0.00 | R5: `0.00 | S5: ` | T5: ` | U5: `租赁 | V5: ` | W5: `0.00000 | X5: `0.54% | Y5: 0.14 | Z5: 0 | AA5: `
A6: `2024-12-19 22:25:27 | B6: `wxd1310896f2aa68bb | C6: `1636140745 | D6: `0 | E6: ` | F6: `4200002388202412192217351495 | G6: `QJ_XP_20241219_042753_ZF_01 | H6: `oHdTn5Wlwy37YA6kmJP6zE9AoTlI | I6: `JSAPI | J6: `SUCCESS | K6: `BOC_CREDIT | L6: `CNY | M6: `0.14 | N6: `0.00 | O6: `0 | P6: `0 | Q6: `0.00 | R6: `0.00 | S6: ` | T6: ` | U6: `租赁 | V6: ` | W6: `0.00000 | X6: `0.54% | Y6: 0.14 | Z6: 0 | AA6: `
A7: `2024-12-19 21:35:18 | B7: `wxd1310896f2aa68bb | C7: `1636140745 | D7: `0 | E7: ` | F7: `4200002388202412199699549948 | G7: `QJ_XP_20241219_042740_ZF_01 | H7: `oHdTn5Wlwy37YA6kmJP6zE9AoTlI | I7: `JSAPI | J7: `SUCCESS | K7: `BOC_CREDIT | L7: `CNY | M7: `0.11 | N7: `0.00 | O7: `0 | P7: `0 | Q7: `0.00 | R7: `0.00 | S7: ` | T7: ` | U7: `租赁 | V7: ` | W7: `0.00000 | X7: `0.54% | Y7: 0.11 | Z7: 0 | AA7: `
A8: `2024-12-19 22:19:14 | B8: `wxd1310896f2aa68bb | C8: `1636140745 | D8: `0 | E8: ` | F8: `4200002389202412198416476825 | G8: `QJ_XP_20241219_042752_ZF_01 | H8: `oHdTn5Wlwy37YA6kmJP6zE9AoTlI | I8: `JSAPI | J8: `SUCCESS | K8: `BOC_CREDIT | L8: `CNY | M8: `0.14 | N8: `0.00 | O8: `0 | P8: `0 | Q8: `0.00 | R8: `0.00 | S8: ` | T8: ` | U8: `租赁 | V8: ` | W8: `0.00000 | X8: `0.54% | Y8: 0.14 | Z8: 0 | AA8: `
A9: `2024-12-19 22:10:33 | B9: `wxd1310896f2aa68bb | C9: `1636140745 | D9: `0 | E9: ` | F9: `4200002390202412196675847654 | G9: `QJ_XP_20241219_042749_ZF_01 | H9: `oHdTn5Wlwy37YA6kmJP6zE9AoTlI | I9: `JSAPI | J9: `SUCCESS | K9: `BOC_CREDIT | L9: `CNY | M9: `0.11 | N9: `0.00 | O9: `0 | P9: `0 | Q9: `0.00 | R9: `0.00 | S9: ` | T9: ` | U9: `租赁 | V9: ` | W9: `0.00000 | X9: `0.54% | Y9: 0.11 | Z9: 0 | AA9: `
A10: `2024-12-19 21:55:21 | B10: `wxd1310896f2aa68bb | C10: `1636140745 | D10: `0 | E10: ` | F10: `4200002488202412192682570706 | G10: `QJ_XP_20241219_042747_ZF_01 | H10: `oHdTn5Wlwy37YA6kmJP6zE9AoTlI | I10: `JSAPI | J10: `SUCCESS | K10: `BOC_CREDIT | L10: `CNY | M10: `0.11 | N10: `0.00 | O10: `0 | P10: `0 | Q10: `0.00 | R10: `0.00 | S10: ` | T10: ` | U10: `租赁 | V10: ` | W10: `0.00000 | X10: `0.54% | Y10: 0.11 | Z10: 0 | AA10: `
A11: `2024-12-19 22:15:39 | B11: `wxd1310896f2aa68bb | C11: `1636140745 | D11: `0 | E11: ` | F11: `4200002489202412195356559746 | G11: `QJ_XP_20241219_042751_ZF_01 | H11: `oHdTn5Wlwy37YA6kmJP6zE9AoTlI | I11: `JSAPI | J11: `SUCCESS | K11: `BOC_CREDIT | L11: `CNY | M11: `0.14 | N11: `0.00 | O11: `0 | P11: `0 | Q11: `0.00 | R11: `0.00 | S11: ` | T11: ` | U11: `租赁 | V11: ` | W11: `0.00000 | X11: `0.54% | Y11: 0.14 | Z11: 0 | AA11: `
A12: `2024-12-19 20:14:37 | B12: `wxd1310896f2aa68bb | C12: `1636140745 | D12: `0 | E12: ` | F12: `4200002496202412195256641423 | G12: `QJ_XP_20241219_042734_ZF_01 | H12: `oHdTn5Wlwy37YA6kmJP6zE9AoTlI | I12: `JSAPI | J12: `SUCCESS | K12: `BOC_CREDIT | L12: `CNY | M12: `0.14 | N12: `0.00 | O12: `0 | P12: `0 | Q12: `0.00 | R12: `0.00 | S12: ` | T12: ` | U12: `租赁 | V12: ` | W12: `0.00000 | X12: `0.54% | Y12: 0.14 | Z12: 0 | AA12: `
A13: `2024-12-19 21:04:40 | B13: `wxd1310896f2aa68bb | C13: `1636140745 | D13: `0 | E13: ` | F13: `4200002503202412193198167017 | G13: `QJ_XP_20241219_042738_ZF_01 | H13: `oHdTn5Wlwy37YA6kmJP6zE9AoTlI | I13: `JSAPI | J13: `SUCCESS | K13: `BOC_CREDIT | L13: `CNY | M13: `0.19 | N13: `0.00 | O13: `0 | P13: `0 | Q13: `0.00 | R13: `0.00 | S13: ` | T13: ` | U13: `租赁 | V13: ` | W13: `0.00000 | X13: `0.54% | Y13: 0.19 | Z13: 0 | AA13: `
... A24: `2024-12-20 19:33:13 | B24: `wxd1310896f2aa68bb | C24: `1636140745 | D24: `0 | E24: ` | F24: `4200002388202412192217351495 | G24: `QJ_XP_20241219_042753_ZF_01 | H24: `oHdTn5Wlwy37YA6kmJP6zE9AoTlI | I24: `JSAPI | J24: `REFUND | K24: `BOC_CREDIT | L24: `CNY | M24: `0.00 | N24: `0.00 | O24: `50301501732024122009029816380 | P24: `QJ_XP_20241219_042753_ZF_01_TK_01_20241220 | Q24: `0.14 | R24: `0.00 | S24: `ORIGINAL | T24: `SUCCESS | U24: `租赁 | V24: ` | W24: `0.00000 | X24: `0.54% | Y24: 0 | Z24: 0.14 | AA24: `
A25: `2024-12-20 19:26:45 | B25: `wxd1310896f2aa68bb | C25: `1636140745 | D25: `0 | E25: ` | F25: `4200002388202412199699549948 | G25: `QJ_XP_20241219_042740_ZF_01 | H25: `oHdTn5Wlwy37YA6kmJP6zE9AoTlI | I25: `JSAPI | J25: `REFUND | K25: 44892 | L25: `CNY | M25: `0.00 | N25: `0.00 | O25: `50302801782024122065204720853 | P25: `QJ_XP_20241219_042740_ZF_01_TK_01_20241220 | Q25: `0.11 | R25: `0.00 | S25: `ORIGINAL | T25: `SUCCESS | U25: `租赁 | V25: ` | W25: `0.00000 | X25: `0.54% | Y25: 0 | Z25: 0.11 | AA25: `
A26: `2024-12-20 19:33:08 | B26: `wxd1310896f2aa68bb | C26: `1636140745 | D26: `0 | E26: ` | F26: `4200002389202412198416476825 | G26: `QJ_XP_20241219_042752_ZF_01 | H26: `oHdTn5Wlwy37YA6kmJP6zE9AoTlI | I26: `JSAPI | J26: `REFUND | K26: `BOC_CREDIT | L26: `CNY | M26: `0.00 | N26: `0.00 | O26: `50302501622024122067882619760 | P26: `QJ_XP_20241219_042752_ZF_01_TK_01_20241220 | Q26: `0.14 | R26: `0.00 | S26: `ORIGINAL | T26: `SUCCESS | U26: `租赁 | V26: ` | W26: `0.00000 | X26: `0.54% | Y26: 0 | Z26: 0.14 | AA26: `
A27: `2024-12-20 19:27:28 | B27: `wxd1310896f2aa68bb | C27: `1636140745 | D27: `0 | E27: ` | F27: `4200002390202412196675847654 | G27: `QJ_XP_20241219_042749_ZF_01 | H27: `oHdTn5Wlwy37YA6kmJP6zE9AoTlI | I27: `JSAPI | J27: `REFUND | K27: `BOC_CREDIT | L27: `CNY | M27: `0.00 | N27: `0.00 | O27: `50301401892024122057710874471 | P27: `QJ_XP_20241219_042749_ZF_01_TK_01_20241220 | Q27: `0.11 | R27: `0.00 | S27: `ORIGINAL | T27: `SUCCESS | U27: `租赁 | V27: ` | W27: `0.00000 | X27: `0.54% | Y27: 0 | Z27: 0.11 | AA27: `
A28: `2024-12-20 19:27:00 | B28: `wxd1310896f2aa68bb | C28: `1636140745 | D28: `0 | E28: ` | F28: `4200002488202412192682570706 | G28: `QJ_XP_20241219_042747_ZF_01 | H28: `oHdTn5Wlwy37YA6kmJP6zE9AoTlI | I28: `JSAPI | J28: `REFUND | K28: `BOC_CREDIT | L28: `CNY | M28: `0.00 | N28: `0.00 | O28: `50302601742024122058326942582 | P28: `QJ_XP_20241219_042747_ZF_01_TK_01_20241220 | Q28: `0.11 | R28: `0.00 | S28: `ORIGINAL | T28: `SUCCESS | U28: `租赁 | V28: ` | W28: `0.00000 | X28: `0.54% | Y28: 0 | Z28: 0.11 | AA28: `
A29: `2024-12-20 19:33:03 | B29: `wxd1310896f2aa68bb | C29: `1636140745 | D29: `0 | E29: ` | F29: `4200002489202412195356559746 | G29: `QJ_XP_20241219_042751_ZF_01 | H29: `oHdTn5Wlwy37YA6kmJP6zE9AoTlI | I29: `JSAPI | J29: `REFUND | K29: `BOC_CREDIT | L29: `CNY | M29: `0.00 | N29: `0.00 | O29: `50302601662024122007017354329 | P29: `QJ_XP_20241219_042751_ZF_01_TK_01_20241220 | Q29: `0.14 | R29: `0.00 | S29: `ORIGINAL | T29: `SUCCESS | U29: `租赁 | V29: ` | W29: `0.00000 | X29: `0.54% | Y29: 0 | Z29: 0.14 | AA29: `
A30: `2024-12-20 19:24:13 | B30: `wxd1310896f2aa68bb | C30: `1636140745 | D30: `0 | E30: ` | F30: `4200002496202412195256641423 | G30: `QJ_XP_20241219_042734_ZF_01 | H30: `oHdTn5Wlwy37YA6kmJP6zE9AoTlI | I30: `JSAPI | J30: `REFUND | K30: `BOC_CREDIT | L30: `CNY | M30: `0.00 | N30: `0.00 | O30: `50302301742024122050431371451 | P30: `QJ_XP_20241219_042734_ZF_01_TK_01_20241220 | Q30: `0.14 | R30: `0.00 | S30: `ORIGINAL | T30: `SUCCESS | U30: `租赁 | V30: ` | W30: `0.00000 | X30: `0.54% | Y30: 0 | Z30: 0.14 | AA30: `
A31: `2024-12-20 19:25:22 | B31: `wxd1310896f2aa68bb | C31: `1636140745 | D31: `0 | E31: ` | F31: `4200002503202412193198167017 | G31: `QJ_XP_20241219_042738_ZF_01 | H31: `oHdTn5Wlwy37YA6kmJP6zE9AoTlI | I31: `JSAPI | J31: `REFUND | K31: `BOC_CREDIT | L31: `CNY | M31: `0.00 | N31: `0.00 | O31: `50301701892024122000301644475 | P31: `QJ_XP_20241219_042738_ZF_01_TK_01_20241220 | Q31: `0.19 | R31: `0.00 | S31: `ORIGINAL | T31: `SUCCESS | U31: `租赁 | V31: ` | W31: `0.00000 | X31: `0.54% | Y31: 0 | Z31: 0.19 | AA31: `
A32: `2024-12-20 19:24:23 | B32: `wxd1310896f2aa68bb | C32: `1636140745 | D32: `0 | E32: ` | F32: `4200002503202412195996553488 | G32: `QJ_XP_20241219_042735_ZF_01 | H32: `oHdTn5Wlwy37YA6kmJP6zE9AoTlI | I32: `JSAPI | J32: `REFUND | K32: `BOC_CREDIT | L32: `CNY | M32: `0.00 | N32: `0.00 | O32: `50300801802024122013453675551 | P32: `QJ_XP_20241219_042735_ZF_01_TK_01_20241220 | Q32: `0.14 | R32: `0.00 | S32: `ORIGINAL | T32: `SUCCESS | U32: `租赁 | V32: ` | W32: `0.00000 | X32: `0.54% | Y32: 0 | Z32: 0.14 | AA32: `
A33: `2024-12-20 17:50:13 | B33: `wxd1310896f2aa68bb | C33: `1636140745 | D33: `0 | E33: ` | F33: `4200002506202412204746621757 | G33: `QJ_XP_20241220_042803_ZF_01 | H33: `oHdTn5Wlwy37YA6kmJP6zE9AoTlI | I33: `JSAPI | J33: `SUCCESS | K33: `CMB_CREDIT | L33: `CNY | M33: `0.08 | N33: `0.00 | O33: `0 | P33: `0 | Q33: `0.00 | R33: `0.00 | S33: ` | T33: ` | U33: `租赁 | V33: ` | W33: `0.00000 | X33: `0.54% | Y33: 0.08 | Z33: 0 | AA33: `
A34: `2024-12-20 19:34:46 | B34: `wxd1310896f2aa68bb | C34: `1636140745 | D34: `0 | E34: ` | F34: `4200002506202412204746621757 | G34: `QJ_XP_20241220_042803_ZF_01 | H34: `oHdTn5Wlwy37YA6kmJP6zE9AoTlI | I34: `JSAPI | J34: `REFUND | K34: `CMB_CREDIT | L34: `CNY | M34: `0.00 | N34: `0.00 | O34: `50303701912024122059328924086 | P34: `QJ_XP_20241220_042803_ZF_01_TK_01_20241220 | Q34: `0.08 | R34: `0.00 | S34: `ORIGINAL | T34: `SUCCESS | U34: `租赁 | V34: ` | W34: `0.00000 | X34: `0.54% | Y34: 0 | Z34: 0.08 | AA34: `
A35: `2024-12-20 19:26:52 | B35: `wxd1310896f2aa68bb | C35: `1636140745 | D35: `0 | E35: ` | F35: `4200002507202412199931616380 | G35: `QJ_XP_20241219_042746_ZF_01 | H35: `oHdTn5Wlwy37YA6kmJP6zE9AoTlI | I35: `JSAPI | J35: `REFUND | K35: `BOC_CREDIT | L35: `CNY | M35: `0.00 | N35: `0.00 | O35: `50302001662024122024266958475 | P35: `QJ_XP_20241219_042746_ZF_01_TK_01_20241220 | Q35: `0.11 | R35: `0.00 | S35: `ORIGINAL | T35: `SUCCESS | U35: `租赁 | V35: ` | W35: `0.00000 | X35: `0.54% | Y35: 0 | Z35: 0.11 | AA35: `
A36: `2024-12-20 19:25:57 | B36: `wxd1310896f2aa68bb | C36: `1636140745 | D36: `0 | E36: ` | F36: `4200002511202412198453095881 | G36: `QJ_XP_20241219_042739_ZF_01 | H36: `oHdTn5Wlwy37YA6kmJP6zE9AoTlI | I36: `JSAPI | J36: `REFUND | K36: `BOC_CREDIT | L36: `CNY | M36: `0.00 | N36: `0.00 | O36: `50300101802024122061549253086 | P36: `QJ_XP_20241219_042739_ZF_01_TK_01_20241220 | Q36: `0.11 | R36: `0.00 | S36: `ORIGINAL | T36: `SUCCESS | U36: `租赁 | V36: ` | W36: `0.00000 | X36: `0.54% | Y36: 0 | Z36: 0.11 | AA36: `
A37: `2024-12-20 19:25:05 | B37: `wxd1310896f2aa68bb | C37: `1636140745 | D37: `0 | E37: ` | F37: `4200002514202412197353324959 | G37: `QJ_XP_20241219_042737_ZF_01 | H37: `oHdTn5Wlwy37YA6kmJP6zE9AoTlI | I37: `JSAPI | J37: `REFUND | K37: `BOC_CREDIT | L37: `CNY | M37: `0.00 | N37: `0.00 | O37: `50303901752024122034449546810 | P37: `QJ_XP_20241219_042737_ZF_01_TK_01_20241220 | Q37: `0.14 | R37: `0.00 | S37: `ORIGINAL | T37: `SUCCESS | U37: `租赁 | V37: ` | W37: `0.00000 | X37: `0.54% | Y37: 0 | Z37: 0.14 | AA37: `
... A104: `2024-12-26 19:15:11 | B104: `wxd1310896f2aa68bb | C104: `1636140745 | D104: `0 | E104: ` | F104: `4200002364202412267992507238 | G104: `QJ_XP_20241226_043384_ZF_01 | H104: `oHdTn5enw9r05VeyOd5AnR4obmEA | I104: `JSAPI | J104: `REFUND | K104: `CMB_CREDIT | L104: `CNY | M104: `0.00 | N104: `0.00 | O104: `50303801632024122609605586906 | P104: `QJ_XP_20241226_043384_ZF_01_TK_01_20241226 | Q104: `0.08 | R104: `0.00 | S104: `ORIGINAL | T104: `SUCCESS | U104: `租赁 | V104: ` | W104: `0.00000 | X104: `0.54% | Y104: 0 | Z104: 0.08 | AA104: `
A105: `2024-12-27 22:41:29 | B105: `wxd1310896f2aa68bb | C105: `1636140745 | D105: `0 | E105: ` | F105: `4200002364202412271170256154 | G105: `QJ_XP_20241227_043504_ZF_01 | H105: `oHdTn5RBMZkgDb8KDc09Mbmm-j58 | I105: `JSAPI | J105: `SUCCESS | K105: `OTHERS | L105: `CNY | M105: `1600.00 | N105: `0.00 | O105: `0 | P105: `0 | Q105: `0.00 | R105: `0.00 | S105: ` | T105: ` | U105: `租赁 | V105: ` | W105: `8.64000 | X105: `0.54% | Y105: 1600 | Z105: 0
A106: `2024-12-27 23:12:28 | B106: `wxd1310896f2aa68bb | C106: `1636140745 | D106: `0 | E106: ` | F106: `4200002373202412273379009122 | G106: `QJ_XP_20241227_043507_ZF_01 | H106: `oHdTn5RBMZkgDb8KDc09Mbmm-j58 | I106: `JSAPI | J106: `SUCCESS | K106: `OTHERS | L106: `CNY | M106: `1600.00 | N106: `0.00 | O106: `0 | P106: `0 | Q106: `0.00 | R106: `0.00 | S106: ` | T106: ` | U106: `租赁 | V106: ` | W106: `8.64000 | X106: `0.54% | Y106: 1600 | Z106: 0 | AA106: `
A107: `2024-12-27 17:59:14 | B107: `wxd1310896f2aa68bb | C107: `1636140745 | D107: `0 | E107: ` | F107: `4200002502202412276023501979 | G107: `QJ_XP_20241227_043472_ZF_01 | H107: `oHdTn5RBMZkgDb8KDc09Mbmm-j58 | I107: `JSAPI | J107: `SUCCESS | K107: `OTHERS | L107: `CNY | M107: `1010.00 | N107: `0.00 | O107: `0 | P107: `0 | Q107: `0.00 | R107: `0.00 | S107: ` | T107: ` | U107: `租赁 | V107: ` | W107: `5.45000 | X107: `0.54% | Y107: 1010 | Z107: 0 | AA107: `
A108: `2024-12-28 16:53:54 | B108: `wxd1310896f2aa68bb | C108: `1636140745 | D108: `0 | E108: ` | F108: `4200002368202412253439639887 | G108: `QJ_XP_20241225_043301_ZF_01 | H108: `oHdTn5Wlwy37YA6kmJP6zE9AoTlI | I108: `JSAPI | J108: `REFUND | K108: `CMB_CREDIT | L108: `CNY | M108: `0.00 | N108: `0.00 | O108: `50300701802024122893341982379 | P108: `QJ_XP_20241225_043301_ZF_01_TK_01_20241228 | Q108: `0.09 | R108: `0.00 | S108: `ORIGINAL | T108: `SUCCESS | U108: `租赁 | V108: ` | W108: `0.00000 | X108: `0.54% | Y108: 0 | Z108: 0.09 | AA108: `
A109: `2024-12-31 19:02:31 | B109: `wxd1310896f2aa68bb | C109: `1636140745 | D109: `0 | E109: ` | F109: `4200002372202412316211298338 | G109: `QJ_XP_20241231_043948_ZF_01 | H109: `oHdTn5TsXAwIzkSY64wWcAblQ93U | I109: `JSAPI | J109: `SUCCESS | K109: `CMB_DEBIT | L109: `CNY | M109: `433.00 | N109: `0.00 | O109: `0 | P109: `0 | Q109: `0.00 | R109: `0.00 | S109: ` | T109: ` | U109: `租赁 | V109: ` | W109: `2.34000 | X109: `0.54% | Y109: 433 | Z109: 0 | AA109: `
A110: `2024-12-31 19:02:37 | B110: `wxd1310896f2aa68bb | C110: `1636140745 | D110: `0 | E110: ` | F110: `4200002372202412316211298338 | G110: `QJ_XP_20241231_043948_ZF_01 | H110: `oHdTn5TsXAwIzkSY64wWcAblQ93U | I110: `JSAPI | J110: `REFUND | K110: `CMB_DEBIT | L110: `CNY | M110: `0.00 | N110: `0.00 | O110: `50301801692024123190646371089 | P110: `QJ_XP_20241231_043948_ZF_01_TK_01_20241231 | Q110: `433.00 | R110: `0.00 | S110: `ORIGINAL | T110: `SUCCESS | U110: `租赁 | V110: ` | W110: `-2.34000 | X110: `0.54% | Y110: 0 | Z110: 433 | AA110: `
A111: `2024-12-31 11:43:52 | B111: `wxd1310896f2aa68bb | C111: `1636140745 | D111: `0 | E111: ` | F111: `4200002380202412314026446539 | G111: `QJ_XP_20241231_043797_ZF_01 | H111: `oHdTn5Wlwy37YA6kmJP6zE9AoTlI | I111: `JSAPI | J111: `SUCCESS | K111: `CMB_CREDIT | L111: `CNY | M111: `0.14 | N111: `0.00 | O111: `0 | P111: `0 | Q111: `0.00 | R111: `0.00 | S111: ` | T111: ` | U111: `租赁 | V111: ` | W111: `0.00000 | X111: `0.54% | Y111: 0.14 | Z111: 0 | AA111: `
A112: `2024-12-31 08:10:07 | B112: `wxd1310896f2aa68bb | C112: `1636140745 | D112: `0 | E112: ` | F112: `4200002384202412319948876613 | G112: `QJ_XP_20241231_043894_ZF_01 | H112: `oHdTn5XzdErjCwQLy4JjIMXcwXJY | I112: `JSAPI | J112: `SUCCESS | K112: `ICBC_CREDIT | L112: `CNY | M112: `348.00 | N112: `0.00 | O112: `0 | P112: `0 | Q112: `0.00 | R112: `0.00 | S112: ` | T112: ` | U112: `租赁 | V112: ` | W112: `1.88000 | X112: `0.54% | Y112: 348 | Z112: 0 | AA112: `
A113: `2024-12-31 11:30:01 | B113: `wxd1310896f2aa68bb | C113: `1636140745 | D113: `0 | E113: ` | F113: `4200002388202412317229991882 | G113: `QJ_XP_20241231_043796_ZF_01 | H113: `oHdTn5Wlwy37YA6kmJP6zE9AoTlI | I113: `JSAPI | J113: `SUCCESS | K113: `CMB_CREDIT | L113: `CNY | M113: `0.14 | N113: `0.00 | O113: `0 | P113: `0 | Q113: `0.00 | R113: `0.00 | S113: ` | T113: ` | U113: `租赁 | V113: ` | W113: `0.00000 | X113: `0.54% | Y113: 0.14 | Z113: 0 | AA113: `
A114: `2024-12-31 19:21:59 | B114: `wxd1310896f2aa68bb | C114: `1636140745 | D114: `0 | E114: ` | F114: `4200002497202412313755457547 | G114: `QJ_XP_20241231_043949_ZF_01 | H114: `oHdTn5TsXAwIzkSY64wWcAblQ93U | I114: `JSAPI | J114: `SUCCESS | K114: `CMB_DEBIT | L114: `CNY | M114: `433.00 | N114: `0.00 | O114: `0 | P114: `0 | Q114: `0.00 | R114: `0.00 | S114: ` | T114: ` | U114: `租赁 | V114: ` | W114: `2.34000 | X114: `0.54% | Y114: 433 | Z114: 0 | AA114: `
A115: `2025-01-01 09:16:42 | B115: `wxd1310896f2aa68bb | C115: `1636140745 | D115: `0 | E115: ` | F115: `4200002383202501014891164994 | G115: `QJ_XP_20250101_043962_ZF_01 | H115: `oHdTn5VnsHcKjcpMN3dpigNd8stA | I115: `JSAPI | J115: `SUCCESS | K115: `OTHERS | L115: `CNY | M115: `479.00 | N115: `0.00 | O115: `0 | P115: `0 | Q115: `0.00 | R115: `0.00 | S115: ` | T115: ` | U115: `租赁 | V115: ` | W115: `2.59000 | X115: `0.54% | Y115: 479 | Z115: 0 | AA115: `
A116: `2025-01-01 12:09:24 | B116: `wxd1310896f2aa68bb | C116: `1636140745 | D116: `0 | E116: ` | F116: `4200002520202501011079581305 | G116: `QJ_XP_20250101_043975_ZF_01 | H116: `oHdTn5VnsHcKjcpMN3dpigNd8stA | I116: `JSAPI | J116: `SUCCESS | K116: `SPDB_DEBIT | L116: `CNY | M116: `348.00 | N116: `0.00 | O116: `0 | P116: `0 | Q116: `0.00 | R116: `0.00 | S116: ` | T116: ` | U116: `租赁 | V116: ` | W116: `1.88000 | X116: `0.54% | Y116: 348 | Z116: 0 | AA116: `
A117: `2025-01-02 15:56:39 | B117: `wxd1310896f2aa68bb | C117: `1636140745 | D117: `0 | E117: ` | F117: `4200002363202501024871603562 | G117: `QJ_XP_20250102_044074_ZF_01 | H117: `oHdTn5XweSbNklGsYWvcxnzYnBHc | I117: `JSAPI | J117: `SUCCESS | K117: `OTHERS | L117: `CNY | M117: `479.00 | N117: `0.00 | O117: `0 | P117: `0 | Q117: `0.00 | R117: `0.00 | S117: ` | T117: ` | U117: `租赁 | V117: ` | W117: `2.59000 | X117: `0.54% | Y117: 479 | Z117: 0 | AA117: `
... A132: `2025-01-03 19:46:10 | B132: `wxd1310896f2aa68bb | C132: `1636140745 | D132: `0 | E132: ` | F132: `4200002512202501039080718049 | G132: `QJ_XP_20250103_044202_ZF_01 | H132: `oHdTn5frYUFRgduS6Mues1x2YcGM | I132: `JSAPI | J132: `SUCCESS | K132: `OTHERS | L132: `CNY | M132: `185.00 | N132: `0.00 | O132: `0 | P132: `0 | Q132: `0.00 | R132: `0.00 | S132: ` | T132: ` | U132: `租赁 | V132: ` | W132: `1.00000 | X132: `0.54% | Y132: 185 | Z132: 0 | AA132: `
A133: `2025-01-03 16:11:39 | B133: `wxd1310896f2aa68bb | C133: `1636140745 | D133: `0 | E133: ` | F133: `4200002517202501035946862318 | G133: `QJ_XP_20250103_044178_ZF_01 | H133: `oHdTn5XHtPAWJrqwtQhUaGuqCuz0 | I133: `JSAPI | J133: `SUCCESS | K133: `CCB_DEBIT | L133: `CNY | M133: `800.00 | N133: `0.00 | O133: `0 | P133: `0 | Q133: `0.00 | R133: `0.00 | S133: ` | T133: ` | U133: `租赁 | V133: ` | W133: `4.32000 | X133: `0.54% | Y133: 800 | Z133: 0
A134: `2025-01-03 21:21:23 | B134: `wxd1310896f2aa68bb | C134: `1636140745 | D134: `0 | E134: ` | F134: `4200002517202501035946862318 | G134: `QJ_XP_20250103_044178_ZF_01 | H134: `oHdTn5XHtPAWJrqwtQhUaGuqCuz0 | I134: `JSAPI | J134: `REFUND | K134: `CCB_DEBIT | L134: `CNY | M134: `0.00 | N134: `0.00 | O134: `50303802152025010378172756457 | P134: `QJ_XP_20250103_044178_ZF_01_TK_01_20250103 | Q134: `800.00 | R134: `0.00 | S134: `ORIGINAL | T134: `SUCCESS | U134: `租赁 | V134: ` | W134: `-4.32000 | X134: `0.54% | Y134: 0 | Z134: 800 | AA134: `
A135: `2025-01-03 18:00:33 | B135: `wxd1310896f2aa68bb | C135: `1636140745 | D135: `0 | E135: ` | F135: `4200002518202501031762112661 | G135: `QJ_XP_20250103_044191_ZF_01 | H135: `oHdTn5c37nPiKhh4IuXr7u4apFSU | I135: `JSAPI | J135: `SUCCESS | K135: `COMM_DEBIT | L135: `CNY | M135: `370.00 | N135: `0.00 | O135: `0 | P135: `0 | Q135: `0.00 | R135: `0.00 | S135: ` | T135: ` | U135: `租赁 | V135: ` | W135: `2.00000 | X135: `0.54% | Y135: 370 | Z135: 0 | AA135: `
A136: `2025-01-03 17:54:59 | B136: `wxd1310896f2aa68bb | C136: `1636140745 | D136: `0 | E136: ` | F136: `4200002520202501033958269942 | G136: `QJ_XP_20250103_044189_ZF_01 | H136: `oHdTn5V7jnMfYbzeYWeHHrs5TalM | I136: `JSAPI | J136: `SUCCESS | K136: `CMB_DEBIT | L136: `CNY | M136: `185.00 | N136: `0.00 | O136: `0 | P136: `0 | Q136: `0.00 | R136: `0.00 | S136: ` | T136: ` | U136: `租赁 | V136: ` | W136: `1.00000 | X136: `0.54% | Y136: 185 | Z136: 0 | AA136: `
A137: `2025-01-04 18:16:35 | B137: `wxd1310896f2aa68bb | C137: `1636140745 | D137: `0 | E137: ` | F137: `4200002378202501044819082251 | G137: `QJ_XP_20250104_044390_ZF_01 | H137: `oHdTn5VWgJHBPOoeVj08ZY22C5Bg | I137: `JSAPI | J137: `SUCCESS | K137: `CMB_CREDIT | L137: `CNY | M137: `425.00 | N137: `0.00 | O137: `0 | P137: `0 | Q137: `0.00 | R137: `0.00 | S137: ` | T137: ` | U137: `租赁 | V137: ` | W137: `2.30000 | X137: `0.54% | Y137: 425 | Z137: 0 | AA137: `
A138: `2025-01-04 08:49:41 | B138: `wxd1310896f2aa68bb | C138: `1636140745 | D138: `0 | E138: ` | F138: `4200002383202501045142787847 | G138: `QJ_XP_20250104_044233_ZF_01 | H138: `oHdTn5TfFvrp-Dffz-UHZWaWlieU | I138: `JSAPI | J138: `SUCCESS | K138: `OTHERS | L138: `CNY | M138: `395.00 | N138: `0.00 | O138: `0 | P138: `0 | Q138: `0.00 | R138: `0.00 | S138: ` | T138: ` | U138: `租赁 | V138: ` | W138: `2.13000 | X138: `0.54% | Y138: 395 | Z138: 0 | AA138: `
A139: `2025-01-04 10:09:15 | B139: `wxd1310896f2aa68bb | C139: `1636140745 | D139: `0 | E139: ` | F139: `4200002390202501047348908795 | G139: `QJ_XP_20250104_044258_ZF_01 | H139: `oHdTn5ULxEoUc3FWTsTxECiJUOzA | I139: `JSAPI | J139: `SUCCESS | K139: `OTHERS | L139: `CNY | M139: `471.00 | N139: `0.00 | O139: `0 | P139: `0 | Q139: `0.00 | R139: `0.00 | S139: ` | T139: ` | U139: `租赁 | V139: ` | W139: `2.54000 | X139: `0.54% | Y139: 471 | Z139: 0 | AA139: `
A140: `2025-01-04 11:52:26 | B140: `wxd1310896f2aa68bb | C140: `1636140745 | D140: `0 | E140: ` | F140: `4200002486202501040204230279 | G140: `QJ_XP_20250104_044295_ZF_01 | H140: `oHdTn5dAvz63fulrW5Z7fNZEJTrg | I140: `JSAPI | J140: `SUCCESS | K140: `OTHERS | L140: `CNY | M140: `395.00 | N140: `0.00 | O140: `0 | P140: `0 | Q140: `0.00 | R140: `0.00 | S140: ` | T140: ` | U140: `租赁 | V140: ` | W140: `2.13000 | X140: `0.54% | Y140: 395 | Z140: 0 | AA140: `
A141: `2025-01-04 09:44:57 | B141: `wxd1310896f2aa68bb | C141: `1636140745 | D141: `0 | E141: ` | F141: `4200002502202501045668282376 | G141: `QJ_XP_20250104_044253_ZF_01 | H141: `oHdTn5UAJSWzTcnw-vSTQkIH7VK0 | I141: `JSAPI | J141: `SUCCESS | K141: `CMB_DEBIT | L141: `CNY | M141: `1413.00 | N141: `0.00 | O141: `0 | P141: `0 | Q141: `0.00 | R141: `0.00 | S141: ` | T141: ` | U141: `租赁 | V141: ` | W141: `7.63000 | X141: `0.54% | Y141: 1413 | Z141: 0 | AA141: `
A142: `2025-01-04 13:29:49 | B142: `wxd1310896f2aa68bb | C142: `1636140745 | D142: `0 | E142: ` | F142: `4200002503202501040962407379 | G142: `QJ_XP_20250104_044323_ZF_01 | H142: `oHdTn5U2FsNWKhvfnL-KtiUJi3g4 | I142: `JSAPI | J142: `SUCCESS | K142: `CMB_CREDIT | L142: `CNY | M142: `185.00 | N142: `0.00 | O142: `0 | P142: `0 | Q142: `0.00 | R142: `0.00 | S142: ` | T142: ` | U142: `租赁 | V142: ` | W142: `1.00000 | X142: `0.54% | Y142: 185 | Z142: 0 | AA142: `
A143: `2025-01-04 09:42:27 | B143: `wxd1310896f2aa68bb | C143: `1636140745 | D143: `0 | E143: ` | F143: `4200002505202501043186777014 | G143: `QJ_XP_20250104_044251_ZF_01 | H143: `oHdTn5ccnOjUoX-vpWn3rdGg3jTI | I143: `JSAPI | J143: `SUCCESS | K143: `CCB_CREDIT | L143: `CNY | M143: `1415.00 | N143: `0.00 | O143: `0 | P143: `0 | Q143: `0.00 | R143: `0.00 | S143: ` | T143: ` | U143: `租赁 | V143: ` | W143: `7.64000 | X143: `0.54% | Y143: 1415 | Z143: 0 | AA143: `
A144: `2025-01-04 11:21:12 | B144: `wxd1310896f2aa68bb | C144: `1636140745 | D144: `0 | E144: ` | F144: `4200002506202501048464018794 | G144: `QJ_XP_20250104_044281_ZF_01 | H144: `oHdTn5YG_zNtCpIXDEC9tT2tEZNI | I144: `JSAPI | J144: `SUCCESS | K144: `COMM_CREDIT | L144: `CNY | M144: `395.00 | N144: `0.00 | O144: `0 | P144: `0 | Q144: `0.00 | R144: `0.00 | S144: ` | T144: ` | U144: `租赁 | V144: ` | W144: `2.13000 | X144: `0.54% | Y144: 395 | Z144: 0 | AA144: `
A145: `2025-01-04 11:16:54 | B145: `wxd1310896f2aa68bb | C145: `1636140745 | D145: `0 | E145: ` | F145: `4200002509202501041737125746 | G145: `QJ_XP_20250104_044277_ZF_01 | H145: `oHdTn5YG_zNtCpIXDEC9tT2tEZNI | I145: `JSAPI | J145: `SUCCESS | K145: `COMM_CREDIT | L145: `CNY | M145: `395.00 | N145: `0.00 | O145: `0 | P145: `0 | Q145: `0.00 | R145: `0.00 | S145: ` | T145: ` | U145: `租赁 | V145: ` | W145: `2.13000 | X145: `0.54% | Y145: 395 | Z145: 0 | AA145: `
... A391: `2025-02-01 08:46:13 | B391: `wxd1310896f2aa68bb | C391: `1636140745 | D391: `0 | E391: ` | F391: `4200002596202502012455786955 | G391: `QJ_XP_20250201_047771_ZF_01 | H391: `oHdTn5efVa8jFP0kAu0FYlFY_Yx8 | I391: `JSAPI | J391: `SUCCESS | K391: `CMB_CREDIT | L391: `CNY | M391: `577.00 | N391: `0.00 | O391: `0 | P391: `0 | Q391: `0.00 | R391: `0.00 | S391: ` | T391: ` | U391: `租赁 | V391: ` | W391: `3.12000 | X391: `0.54% | Y391: 577 | Z391: 0 | AA391: `
A392: `2025-02-02 08:10:10 | B392: `wxd1310896f2aa68bb | C392: `1636140745 | D392: `0 | E392: ` | F392: `4200002488202502016849458268 | G392: `QJ_XP_20250201_047906_ZF_01 | H392: `oHdTn5TDhxcSUOuGI3kyhVW0UNEA | I392: `JSAPI | J392: `REFUND | K392: `ICBC_DEBIT | L392: `CNY | M392: `0.00 | N392: `0.00 | O392: `50302801942025020240147527983 | P392: `QJ_XP_20250201_047906_ZF_01_TK_01_20250202 | Q392: `1284.00 | R392: `0.00 | S392: `ORIGINAL | T392: `SUCCESS | U392: `租赁 | V392: ` | W392: `-6.93000 | X392: `0.54% | Y392: 0 | Z392: 1284
A393: `2025-02-02 11:57:41 | B393: `wxd1310896f2aa68bb | C393: `1636140745 | D393: `0 | E393: ` | F393: `4200002488202502022055108947 | G393: `QJ_XP_20250202_047959_ZF_01 | H393: `oHdTn5YNXLdPsLOkQSVn5lRe-Ee8 | I393: `JSAPI | J393: `SUCCESS | K393: `OTHERS | L393: `CNY | M393: `484.00 | N393: `0.00 | O393: `0 | P393: `0 | Q393: `0.00 | R393: `0.00 | S393: ` | T393: ` | U393: `租赁 | V393: ` | W393: `2.61000 | X393: `0.54% | Y393: 484 | Z393: 0 | AA393: `
A394: `2025-02-02 10:09:17 | B394: `wxd1310896f2aa68bb | C394: `1636140745 | D394: `0 | E394: ` | F394: `4200002491202502026905093051 | G394: `QJ_XP_20250202_047932_ZF_01 | H394: `oHdTn5RdpF8J7L2kOe-wqaGbV2E4 | I394: `JSAPI | J394: `SUCCESS | K394: `ICBC_DEBIT | L394: `CNY | M394: `1284.00 | N394: `0.00 | O394: `0 | P394: `0 | Q394: `0.00 | R394: `0.00 | S394: ` | T394: ` | U394: `租赁 | V394: ` | W394: `6.93000 | X394: `0.54% | Y394: 1284 | Z394: 0 | AA394: `
A395: `2025-02-02 18:56:07 | B395: `wxd1310896f2aa68bb | C395: `1636140745 | D395: `0 | E395: ` | F395: `4200002491202502026905093051 | G395: `QJ_XP_20250202_047932_ZF_01 | H395: `oHdTn5RdpF8J7L2kOe-wqaGbV2E4 | I395: `JSAPI | J395: `REFUND | K395: `ICBC_DEBIT | L395: `CNY | M395: `0.00 | N395: `0.00 | O395: `50301102492025020290035441775 | P395: `QJ_XP_20250202_047932_ZF_01_TK_01_20250202 | Q395: `1284.00 | R395: `0.00 | S395: `ORIGINAL | T395: `SUCCESS | U395: `租赁 | V395: ` | W395: `-6.93000 | X395: `0.54% | Y395: 0 | Z395: 1284 | AA395: `
A396: `2025-02-02 09:50:04 | B396: `wxd1310896f2aa68bb | C396: `1636140745 | D396: `0 | E396: ` | F396: `4200002495202502023103432262 | G396: `QJ_XP_20250202_047927_ZF_01 | H396: `oHdTn5TDhxcSUOuGI3kyhVW0UNEA | I396: `JSAPI | J396: `SUCCESS | K396: `ICBC_DEBIT | L396: `CNY | M396: `577.00 | N396: `0.00 | O396: `0 | P396: `0 | Q396: `0.00 | R396: `0.00 | S396: ` | T396: ` | U396: `租赁 | V396: ` | W396: `3.12000 | X396: `0.54% | Y396: 577 | Z396: 0 | AA396: `
A397: `2025-02-02 21:07:42 | B397: `wxd1310896f2aa68bb | C397: `1636140745 | D397: `0 | E397: ` | F397: `4200002497202502022132570429 | G397: `QJ_XP_20250202_048059_ZF_01 | H397: `oHdTn5RdpF8J7L2kOe-wqaGbV2E4 | I397: `JSAPI | J397: `SUCCESS | K397: `ICBC_DEBIT | L397: `CNY | M397: `1284.00 | N397: `0.00 | O397: `0 | P397: `0 | Q397: `0.00 | R397: `0.00 | S397: ` | T397: ` | U397: `租赁 | V397: ` | W397: `6.93000 | X397: `0.54% | Y397: 1284 | Z397: 0 | AA397: `
A398: `2025-02-02 11:05:00 | B398: `wxd1310896f2aa68bb | C398: `1636140745 | D398: `0 | E398: ` | F398: `4200002498202502021133631103 | G398: `QJ_XP_20250202_047945_ZF_01 | H398: `oHdTn5aFnGTyC9tL-SfAmQPJPXps | I398: `JSAPI | J398: `SUCCESS | K398: `OTHERS | L398: `CNY | M398: `484.00 | N398: `0.00 | O398: `0 | P398: `0 | Q398: `0.00 | R398: `0.00 | S398: ` | T398: ` | U398: `租赁 | V398: ` | W398: `2.61000 | X398: `0.54% | Y398: 484 | Z398: 0 | AA398: `
A399: `2025-02-02 11:45:16 | B399: `wxd1310896f2aa68bb | C399: `1636140745 | D399: `0 | E399: ` | F399: `4200002512202502026281613903 | G399: `QJ_XP_20250202_047955_ZF_01 | H399: `oHdTn5YfsyJG0hYg6zyCo9TM7CD8 | I399: `JSAPI | J399: `SUCCESS | K399: `ICBC_CREDIT | L399: `CNY | M399: `484.00 | N399: `0.00 | O399: `0 | P399: `0 | Q399: `0.00 | R399: `0.00 | S399: ` | T399: ` | U399: `租赁 | V399: ` | W399: `2.61000 | X399: `0.54% | Y399: 484 | Z399: 0 | AA399: `
A400: `2025-02-02 16:54:33 | B400: `wxd1310896f2aa68bb | C400: `1636140745 | D400: `0 | E400: ` | F400: `4200002513202502029750288017 | G400: `QJ_XP_20250202_048020_ZF_01 | H400: `oHdTn5dcL8Ao5NavV5vEzdXdfPmo | I400: `JSAPI | J400: `SUCCESS | K400: `OTHERS | L400: `CNY | M400: `577.00 | N400: `0.00 | O400: `0 | P400: `0 | Q400: `0.00 | R400: `0.00 | S400: ` | T400: ` | U400: `租赁 | V400: ` | W400: `3.12000 | X400: `0.54% | Y400: 577 | Z400: 0 | AA400: `
A401: `2025-02-02 21:08:08 | B401: `wxd1310896f2aa68bb | C401: `1636140745 | D401: `0 | E401: ` | F401: `4200002514202502021641886701 | G401: `QJ_XP_20250202_048060_ZF_01 | H401: `oHdTn5RdpF8J7L2kOe-wqaGbV2E4 | I401: `JSAPI | J401: `SUCCESS | K401: `ICBC_DEBIT | L401: `CNY | M401: `1284.00 | N401: `0.00 | O401: `0 | P401: `0 | Q401: `0.00 | R401: `0.00 | S401: ` | T401: ` | U401: `租赁 | V401: ` | W401: `6.93000 | X401: `0.54% | Y401: 1284 | Z401: 0 | AA401: `
A402: `2025-02-02 08:01:30 | B402: `wxd1310896f2aa68bb | C402: `1636140745 | D402: `0 | E402: ` | F402: `4200002520202502027836288547 | G402: `QJ_XP_20250202_047915_ZF_01 | H402: `oHdTn5USfgGXZ-oO9GyN1HW6DXqI | I402: `JSAPI | J402: `SUCCESS | K402: `ICBC_DEBIT | L402: `CNY | M402: `577.00 | N402: `0.00 | O402: `0 | P402: `0 | Q402: `0.00 | R402: `0.00 | S402: ` | T402: ` | U402: `租赁 | V402: ` | W402: `3.12000 | X402: `0.54% | Y402: 577 | Z402: 0 | AA402: `
A403: `2025-02-02 08:24:03 | B403: `wxd1310896f2aa68bb | C403: `1636140745 | D403: `0 | E403: ` | F403: `4200002596202502025742861589 | G403: `QJ_XP_20250202_047917_ZF_01 | H403: `oHdTn5TDhxcSUOuGI3kyhVW0UNEA | I403: `JSAPI | J403: `SUCCESS | K403: `ICBC_DEBIT | L403: `CNY | M403: `670.00 | N403: `0.00 | O403: `0 | P403: `0 | Q403: `0.00 | R403: `0.00 | S403: ` | T403: ` | U403: `租赁 | V403: ` | W403: `3.62000 | X403: `0.54% | Y403: 670 | Z403: 0 | AA403: `
A404: `2025-02-02 09:50:12 | B404: `wxd1310896f2aa68bb | C404: `1636140745 | D404: `0 | E404: ` | F404: `4200002596202502025742861589 | G404: `QJ_XP_20250202_047917_ZF_01 | H404: `oHdTn5TDhxcSUOuGI3kyhVW0UNEA | I404: `JSAPI | J404: `REFUND | K404: `ICBC_DEBIT | L404: `CNY | M404: `0.00 | N404: `0.00 | O404: `50302902382025020242222718334 | P404: `QJ_XP_20250202_047917_ZF_01_TK_01_20250202 | Q404: `670.00 | R404: `0.00 | S404: `ORIGINAL | T404: `SUCCESS | U404: `租赁 | V404: ` | W404: `-3.62000 | X404: `0.54% | Y404: 0 | Z404: 670 | AA404: `
... A586: `2025-02-28 12:00:52 | B586: `wxd1310896f2aa68bb | C586: `1636140745 | D586: `0 | E586: ` | F586: `4200002600202502284403396424 | G586: `QJ_XP_20250228_050831_ZF_01 | H586: `oHdTn5clgbXnrh7jprSUBNmkBve4 | I586: `JSAPI | J586: `SUCCESS | K586: `ABC_CREDIT | L586: `CNY | M586: `348.00 | N586: `0.00 | O586: `0 | P586: `0 | Q586: `0.00 | R586: `0.00 | S586: ` | T586: ` | U586: `租赁 | V586: ` | W586: `1.88000 | X586: `0.54% | Y586: 348 | Z586: 0 | AA586: `
A587: `2025-03-01 07:24:20 | B587: `wxd1310896f2aa68bb | C587: `1636140745 | D587: `0 | E587: ` | F587: `4200002492202503018876811585 | G587: `QJ_XP_20250301_050863_ZF_01 | H587: `oHdTn5SjCWYAWs4_wEBTEzm13RAg | I587: `JSAPI | J587: `SUCCESS | K587: `CMB_DEBIT | L587: `CNY | M587: `1043.00 | N587: `0.00 | O587: `0 | P587: `0 | Q587: `0.00 | R587: `0.00 | S587: ` | T587: ` | U587: `租赁 | V587: ` | W587: `5.63000 | X587: `0.54% | Y587: 1043 | Z587: 0
A588: `2025-03-01 07:15:24 | B588: `wxd1310896f2aa68bb | C588: `1636140745 | D588: `0 | E588: ` | F588: `4200002495202503013935099567 | G588: `QJ_XP_20250301_050861_ZF_01 | H588: `oHdTn5acbys3tR-PpQOm1Pp0uWDA | I588: `JSAPI | J588: `SUCCESS | K588: `CIB_DEBIT | L588: `CNY | M588: `1043.00 | N588: `0.00 | O588: `0 | P588: `0 | Q588: `0.00 | R588: `0.00 | S588: ` | T588: ` | U588: `租赁 | V588: ` | W588: `5.63000 | X588: `0.54% | Y588: 1043 | Z588: 0
A589: `2025-03-01 09:41:27 | B589: `wxd1310896f2aa68bb | C589: `1636140745 | D589: `0 | E589: ` | F589: `4200002495202503014138112231 | G589: `QJ_XP_20250301_050890_ZF_01 | H589: `oHdTn5VNOT0Y7A2dSWDjvVMjP1g0 | I589: `JSAPI | J589: `SUCCESS | K589: `CITIC_CREDIT | L589: `CNY | M589: `490.00 | N589: `0.00 | O589: `0 | P589: `0 | Q589: `0.00 | R589: `0.00 | S589: ` | T589: ` | U589: `租赁 | V589: ` | W589: `2.65000 | X589: `0.54% | Y589: 490 | Z589: 0
A590: `2025-03-01 08:19:40 | B590: `wxd1310896f2aa68bb | C590: `1636140745 | D590: `0 | E590: ` | F590: `4200002503202503012591880891 | G590: `QJ_XP_20250301_050868_ZF_01 | H590: `oHdTn5QOOfavlqhpivM4Y843Iu0g | I590: `JSAPI | J590: `SUCCESS | K590: `CMB_DEBIT | L590: `CNY | M590: `559.00 | N590: `0.00 | O590: `0 | P590: `0 | Q590: `0.00 | R590: `0.00 | S590: ` | T590: ` | U590: `租赁 | V590: ` | W590: `3.02000 | X590: `0.54% | Y590: 559 | Z590: 0
A591: `2025-03-01 08:02:00 | B591: `wxd1310896f2aa68bb | C591: `1636140745 | D591: `0 | E591: ` | F591: `4200002503202503019597387536 | G591: `QJ_XP_20250301_050864_ZF_01 | H591: `oHdTn5USfgGXZ-oO9GyN1HW6DXqI | I591: `JSAPI | J591: `SUCCESS | K591: `OTHERS | L591: `CNY | M591: `559.00 | N591: `0.00 | O591: `0 | P591: `0 | Q591: `0.00 | R591: `0.00 | S591: ` | T591: ` | U591: `租赁 | V591: ` | W591: `3.02000 | X591: `0.54% | Y591: 559 | Z591: 0
A592: `2025-03-01 13:02:13 | B592: `wxd1310896f2aa68bb | C592: `1636140745 | D592: `0 | E592: ` | F592: `4200002504202503012066867463 | G592: `QJ_XP_20250301_050943_ZF_01 | H592: `oHdTn5RG9evg9OntJmi0Xr7ow9V8 | I592: `JSAPI | J592: `SUCCESS | K592: `BOC_DEBIT | L592: `CNY | M592: `480.00 | N592: `0.00 | O592: `0 | P592: `0 | Q592: `0.00 | R592: `0.00 | S592: ` | T592: ` | U592: `租赁 | V592: ` | W592: `2.59000 | X592: `0.54% | Y592: 480 | Z592: 0
A593: `2025-03-01 08:47:40 | B593: `wxd1310896f2aa68bb | C593: `1636140745 | D593: `0 | E593: ` | F593: `4200002505202503018572351605 | G593: `QJ_XP_20250301_050878_ZF_01 | H593: `oHdTn5f7RhjkOMn3vzKVvV4rqDoU | I593: `JSAPI | J593: `SUCCESS | K593: `CMB_CREDIT | L593: `CNY | M593: `829.00 | N593: `0.00 | O593: `0 | P593: `0 | Q593: `0.00 | R593: `0.00 | S593: ` | T593: ` | U593: `租赁 | V593: ` | W593: `4.48000 | X593: `0.54% | Y593: 829 | Z593: 0
A594: `2025-03-01 11:24:20 | B594: `wxd1310896f2aa68bb | C594: `1636140745 | D594: `0 | E594: ` | F594: `4200002507202503014442820687 | G594: `QJ_XP_20250301_050920_ZF_01 | H594: `oHdTn5dfyhe0vcX25H9WZKpZLV8Y | I594: `JSAPI | J594: `SUCCESS | K594: `CITIC_CREDIT | L594: `CNY | M594: `829.00 | N594: `0.00 | O594: `0 | P594: `0 | Q594: `0.00 | R594: `0.00 | S594: ` | T594: ` | U594: `租赁 | V594: ` | W594: `4.48000 | X594: `0.54% | Y594: 829 | Z594: 0
A595: `2025-03-01 08:04:50 | B595: `wxd1310896f2aa68bb | C595: `1636140745 | D595: `0 | E595: ` | F595: `4200002512202503015941526322 | G595: `QJ_XP_20250301_050865_ZF_01 | H595: `oHdTn5UlGkcqh_4WGE7AWwpeZVlA | I595: `JSAPI | J595: `SUCCESS | K595: `ICBC_DEBIT | L595: `CNY | M595: `829.00 | N595: `0.00 | O595: `0 | P595: `0 | Q595: `0.00 | R595: `0.00 | S595: ` | T595: ` | U595: `租赁 | V595: ` | W595: `4.48000 | X595: `0.54% | Y595: 829 | Z595: 0
A596: `2025-03-01 13:02:49 | B596: `wxd1310896f2aa68bb | C596: `1636140745 | D596: `0 | E596: ` | F596: `4200002512202503017305455564 | G596: `QJ_XP_20250301_050944_ZF_01 | H596: `oHdTn5RG9evg9OntJmi0Xr7ow9V8 | I596: `JSAPI | J596: `SUCCESS | K596: `BOC_DEBIT | L596: `CNY | M596: `480.00 | N596: `0.00 | O596: `0 | P596: `0 | Q596: `0.00 | R596: `0.00 | S596: ` | T596: ` | U596: `租赁 | V596: ` | W596: `2.59000 | X596: `0.54% | Y596: 480 | Z596: 0
A597: `2025-03-01 11:24:49 | B597: `wxd1310896f2aa68bb | C597: `1636140745 | D597: `0 | E597: ` | F597: `4200002513202503016900287282 | G597: `QJ_XP_20250301_050921_ZF_01 | H597: `oHdTn5dfyhe0vcX25H9WZKpZLV8Y | I597: `JSAPI | J597: `SUCCESS | K597: `CITIC_CREDIT | L597: `CNY | M597: `829.00 | N597: `0.00 | O597: `0 | P597: `0 | Q597: `0.00 | R597: `0.00 | S597: ` | T597: ` | U597: `租赁 | V597: ` | W597: `4.48000 | X597: `0.54% | Y597: 829 | Z597: 0
A598: `2025-03-01 08:38:42 | B598: `wxd1310896f2aa68bb | C598: `1636140745 | D598: `0 | E598: ` | F598: `4200002513202503019914555006 | G598: `QJ_XP_20250301_050871_ZF_01 | H598: `oHdTn5buQ1IWbDmu-HpwIbEHJ85s | I598: `JSAPI | J598: `SUCCESS | K598: `CMB_DEBIT | L598: `CNY | M598: `1043.00 | N598: `0.00 | O598: `0 | P598: `0 | Q598: `0.00 | R598: `0.00 | S598: ` | T598: ` | U598: `租赁 | V598: ` | W598: `5.63000 | X598: `0.54% | Y598: 1043 | Z598: 0
... A819: `2025-04-06 10:59:16 | B819: `wxd1310896f2aa68bb | C819: `1636140745 | D819: `0 | E819: ` | F819: `4200002611202504061267144780 | G819: `QJ_XP_20250406_055191_ZF_01 | H819: `oHdTn5cQQ7tqJijPHMPO00GmLwto | I819: `JSAPI | J819: `SUCCESS | K819: `OTHERS | L819: `CNY | M819: `335.00 | N819: `0.00 | O819: `0 | P819: `0 | Q819: `0.00 | R819: `0.00 | S819: ` | T819: ` | U819: `租赁 | V819: ` | W819: `1.81000 | X819: `0.54% | Y819: 335 | Z819: 0
Y820: ==SUM(Y2:Y819) -> 335726.85 | Z820: ==SUM(Z2:Z819) -> 66414.65 | AA820: ==Y820-Z820 -> 269312.2

Sheet 微信南山雪票
A1: 交易时间 | B1: 公众账号ID | C1: 商户号 | D1: 子商户号 | E1: 设备号 | F1: 微信订单号 | G1: 商户订单号 | H1: 用户标识 | I1: 交易类型 | J1: 交易状态 | K1: 付款银行 | L1: 货币种类 | M1: 总金额 | N1: 企业红包金额 | O1: 微信退款单号 | P1: 商户退款单号 | Q1: 退款金额 | R1: 企业红包退款金额 | S1: 退款类型 | T1: 退款状态 | U1: 商品名称 | V1: 商户数据包 | W1: 手续费 | X1: 费率
A2: `2024-12-10 11:30:37 | B2: `wxd1310896f2aa68bb | C2: `1618212799 | D2: `0 | E2: ` | F2: `4200002377202412107056124896 | G2: `042065165503801422229 | H2: `oHdTn5Wlwy37YA6kmJP6zE9AoTlI | I2: `JSAPI | J2: `SUCCESS | K2: `CMB_DEBIT | L2: `CNY | M2: `1.83 | N2: `0.00 | O2: `0 | P2: `0 | Q2: `0.00 | R2: `0.00 | S2: ` | T2: ` | U2: `租赁 | V2: ` | W2: `0.01000 | X2: `0.54% | Y2: 1.83 | Z2: 0
A3: `2024-12-10 11:29:18 | B3: `wxd1310896f2aa68bb | C3: `1618212799 | D3: `0 | E3: ` | F3: `4200002519202412102204391241 | G3: `042064165493801315809 | H3: `oHdTn5Wlwy37YA6kmJP6zE9AoTlI | I3: `JSAPI | J3: `SUCCESS | K3: `CMB_DEBIT | L3: `CNY | M3: `1.12 | N3: `0.00 | O3: `0 | P3: `0 | Q3: `0.00 | R3: `0.00 | S3: ` | T3: ` | U3: `租赁 | V3: ` | W3: `0.01000 | X3: `0.54% | Y3: 1.12 | Z3: 0
A4: `2024-12-11 21:44:10 | B4: `wxd1310896f2aa68bb | C4: `1618212799 | D4: `0 | E4: ` | F4: `4200002368202412116238016606 | G4: `NS_XP_20241211_042132_ZF_01 | H4: `oHdTn5enw9r05VeyOd5AnR4obmEA | I4: `JSAPI | J4: `SUCCESS | K4: `CMB_CREDIT | L4: `CNY | M4: `0.56 | N4: `0.00 | O4: `0 | P4: `0 | Q4: `0.00 | R4: `0.00 | S4: ` | T4: ` | U4: `租赁 | V4: ` | W4: `0.00000 | X4: `0.54% | Y4: 0.56 | Z4: 0
A5: `2024-12-12 17:21:25 | B5: `wxd1310896f2aa68bb | C5: `1618212799 | D5: `0 | E5: ` | F5: `4200002381202412121310958479 | G5: `NS_XP_20241212_042165_ZF_01 | H5: `oHdTn5cCLl-ZvUmC8CzzOfDXMxHo | I5: `JSAPI | J5: `SUCCESS | K5: `OTHERS | L5: `CNY | M5: `300.00 | N5: `0.00 | O5: `0 | P5: `0 | Q5: `0.00 | R5: `0.00 | S5: ` | T5: ` | U5: `租赁 | V5: ` | W5: `1.62000 | X5: `0.54% | Y5: 300 | Z5: 0
A6: `2024-12-12 17:23:08 | B6: `wxd1310896f2aa68bb | C6: `1618212799 | D6: `0 | E6: ` | F6: `4200002496202412122084334362 | G6: `NS_XP_20241212_042166_ZF_01 | H6: `oHdTn5cCLl-ZvUmC8CzzOfDXMxHo | I6: `JSAPI | J6: `SUCCESS | K6: `OTHERS | L6: `CNY | M6: `545.00 | N6: `0.00 | O6: `0 | P6: `0 | Q6: `0.00 | R6: `0.00 | S6: ` | T6: ` | U6: `租赁 | V6: ` | W6: `2.94000 | X6: `0.54% | Y6: 545 | Z6: 0
A7: `2024-12-13 19:53:58 | B7: `wxd1310896f2aa68bb | C7: `1618212799 | D7: `0 | E7: ` | F7: `4200002367202412135959832727 | G7: `NS_XP_20241213_042210_ZF_01 | H7: `oHdTn5fnSsdRQgTdPkoxJu59x1-E | I7: `JSAPI | J7: `SUCCESS | K7: `HXB_CREDIT | L7: `CNY | M7: `430.00 | N7: `0.00 | O7: `0 | P7: `0 | Q7: `0.00 | R7: `0.00 | S7: ` | T7: ` | U7: `租赁 | V7: ` | W7: `2.32000 | X7: `0.54% | Y7: 430 | Z7: 0
A8: `2024-12-13 21:17:18 | B8: `wxd1310896f2aa68bb | C8: `1618212799 | D8: `0 | E8: ` | F8: `4200002370202412130780600812 | G8: `NS_XP_20241213_042213_ZF_01 | H8: `oHdTn5Y8RCUri0o-7k8bkHeGK4fw | I8: `JSAPI | J8: `SUCCESS | K8: `BOC_CREDIT | L8: `CNY | M8: `430.00 | N8: `50.00 | O8: `0 | P8: `0 | Q8: `0.00 | R8: `0.00 | S8: ` | T8: ` | U8: `租赁 | V8: ` | W8: `2.32000 | X8: `0.54% | Y8: 430 | Z8: 0
A9: `2024-12-13 22:24:17 | B9: `wxd1310896f2aa68bb | C9: `1618212799 | D9: `0 | E9: ` | F9: `4200002381202412121310958479 | G9: `NS_XP_20241212_042165_ZF_01 | H9: `oHdTn5cCLl-ZvUmC8CzzOfDXMxHo | I9: `JSAPI | J9: `REFUND | K9: `OTHERS | L9: `CNY | M9: `0.00 | N9: `0.00 | O9: `50303901672024121334172810354 | P9: `NS_XP_20241212_042165_ZF_01_TK_01_20241213 | Q9: `100.00 | R9: `0.00 | S9: `ORIGINAL | T9: `SUCCESS | U9: `租赁 | V9: ` | W9: `-0.54000 | X9: `0.54% | Y9: 0 | Z9: 100
A10: `2024-12-13 12:14:10 | B10: `wxd1310896f2aa68bb | C10: `1618212799 | D10: `0 | E10: ` | F10: `4200002489202412136454074103 | G10: `NS_XP_20241213_042188_ZF_01 | H10: `oHdTn5dDjJdjM_Bx4iVPz4QZ_tqM | I10: `JSAPI | J10: `SUCCESS | K10: `CCB_DEBIT | L10: `CNY | M10: `750.00 | N10: `0.00 | O10: `0 | P10: `0 | Q10: `0.00 | R10: `0.00 | S10: ` | T10: ` | U10: `租赁 | V10: ` | W10: `4.05000 | X10: `0.54% | Y10: 750 | Z10: 0
A11: `2024-12-13 22:24:31 | B11: `wxd1310896f2aa68bb | C11: `1618212799 | D11: `0 | E11: ` | F11: `4200002496202412122084334362 | G11: `NS_XP_20241212_042166_ZF_01 | H11: `oHdTn5cCLl-ZvUmC8CzzOfDXMxHo | I11: `JSAPI | J11: `REFUND | K11: `OTHERS | L11: `CNY | M11: `0.00 | N11: `0.00 | O11: `50300201882024121301062665550 | P11: `NS_XP_20241212_042166_ZF_01_TK_01_20241213 | Q11: `400.00 | R11: `0.00 | S11: `ORIGINAL | T11: `SUCCESS | U11: `租赁 | V11: ` | W11: `-2.16000 | X11: `0.54% | Y11: 0 | Z11: 400
A12: `2024-12-13 21:32:28 | B12: `wxd1310896f2aa68bb | C12: `1618212799 | D12: `0 | E12: ` | F12: `4200002499202412137275603138 | G12: `NS_XP_20241213_042216_ZF_01 | H12: `oHdTn5f_vZUmBrBNN9CyS0mHBJoA | I12: `JSAPI | J12: `SUCCESS | K12: `CMB_DEBIT | L12: `CNY | M12: `430.00 | N12: `0.00 | O12: `0 | P12: `0 | Q12: `0.00 | R12: `0.00 | S12: ` | T12: ` | U12: `租赁 | V12: ` | W12: `2.32000 | X12: `0.54% | Y12: 430 | Z12: 0
A13: `2024-12-13 21:58:10 | B13: `wxd1310896f2aa68bb | C13: `1618212799 | D13: `0 | E13: ` | F13: `4200002501202412138741416230 | G13: `NS_XP_20241213_042217_ZF_01 | H13: `oHdTn5fOOF2ASyvHWCOBMmGlHGYE | I13: `JSAPI | J13: `SUCCESS | K13: `CITIC_CREDIT | L13: `CNY | M13: `1695.00 | N13: `0.00 | O13: `0 | P13: `0 | Q13: `0.00 | R13: `0.00 | S13: ` | T13: ` | U13: `租赁 | V13: ` | W13: `9.15000 | X13: `0.54% | Y13: 1695 | Z13: 0
... A1089: `2025-03-04 14:08:17 | B1089: `wxd1310896f2aa68bb | C1089: `1618212799 | D1089: `0 | E1089: ` | F1089: `4200002618202503049832037081 | G1089: `NS_XP_20250304_051162_ZF_01 | H1089: `oHdTn5Q-P4IgBxj2RyYk3MmSqHOA | I1089: `JSAPI | J1089: `SUCCESS | K1089: `OTHERS | L1089: `CNY | M1089: `480.00 | N1089: `0.00 | O1089: `0 | P1089: `0 | Q1089: `0.00 | R1089: `0.00 | S1089: ` | T1089: ` | U1089: `租赁 | V1089: ` | W1089: `2.59000 | X1089: `0.54% | Y1089: 480 | Z1089: 0
Y1090: ==SUM(Y2:Y1089) -> 240471.08 | Z1090: ==SUM(Z2:Z1089) -> 112610.25 | AA1090: ==Y1090-Z1090 -> 127860.83

Sheet 小程序万龙雪票
A1: 序号 | B1: 下单渠道 | C1: 自我游单号 | D1: 日期 | E1: 时间 | F1: 名称 | G1: 数量 | H1: 状态 | I1: 结算价 | J1: 收款 | K1: 退款 | L1: 利润 | M1: 联系人 | N1: 联系电话 | O1: 客服 | P1: 分账金额 | Q1: 分账状态 | R1: 分账日期 | S1: 分账时间 | T1: 分账单号 | U1: 收款单号1 | V1: 收款金额1 | W1: 收款日期1 | X1: 收款时间1 | Y1: 退款单号1 | Z1: 退款金额1 | AA1: 退款日期1 | AB1: 退款时间1
A2: 1 | B2: 小程序 | C2: 1010812293 | D2: 45753 | E2: 0.45819444 | F2: 【万龙】全雪区日场6小时雪票 | G2: 1 | H2: 已核销 | I2: -316 | J2: -335 | K2: 0 | L2: -19 | M2: 王安妮 | N2: 18612964688 | O2: 肖志强（工作号） | P2: -1 | Q2: 已分 | R2: 45753 | S2: 0.4743287 | T2: QJ_XP_20250406_055191_ZF_01_FZ_20250406_01 | U2: QJ_XP_20250406_055191_ZF_01 | V2: -335 | W2: 45753 | X2: 0.45773148 | Y2: 【-】 | Z2: 【-】 | AA2: 【-】 | AB2: 【-】
A3: 2 | B3: 小程序 | C3: 1010805470 | D3: 45753 | E3: 0.45770833 | F3: 【万龙】全雪区日场6小时雪票 | G3: 1 | H3: 已核销 | I3: -316 | J3: -335 | K3: 0 | L3: -19 | M3: 王安妮 | N3: 18612964688 | O3: 肖志强（工作号） | P3: -1 | Q3: 已分 | R3: 45753 | S3: 0.46045139 | T3: QJ_XP_20250406_055190_ZF_01_FZ_20250406_01 | U3: QJ_XP_20250406_055190_ZF_01 | V3: -335 | W3: 45753 | X3: 0.4571875 | Y3: 【-】 | Z3: 【-】 | AA3: 【-】 | AB3: 【-】
A4: 3 | B4: 小程序 | C4: 1010746002 | D4: 45753 | E4: 0.32612269 | F4: 【万龙】全雪区日场4小时雪票 | G4: 1 | H4: 已核销 | I4: -260 | J4: -275 | K4: 0 | L4: -15 | M4: 张磊 | N4: 13240478627 | O4: 肖志强（工作号） | P4: -1 | Q4: 未分 | R4: 【-】 | S4: 【-】 | T4: 【-】 | U4: QJ_XP_20250406_055182_ZF_01 | V4: -275 | W4: 45753 | X4: 0.32569444 | Y4: 【-】 | Z4: 【-】 | AA4: 【-】 | AB4: 【-】
A5: 4 | B5: 小程序 | C5: 1009428626 | D5: 45751 | E5: 0.31469907 | F5: 【万龙】全雪区日场4小时雪票 | G5: 1 | H5: 已核销 | I5: -232 | J5: -244 | K5: 0 | L5: -12 | M5: 丁丁 | N5: 17710488896 | O5: 布乖 | P5: -1 | Q5: 已分 | R5: 45751 | S5: 0.32295139 | T5: QJ_XP_20250404_055125_ZF_01_FZ_20250404_01 | U5: QJ_XP_20250404_055125_ZF_01 | V5: -244 | W5: 45751 | X5: 0.31424769 | Y5: 【-】 | Z5: 【-】 | AA5: 【-】 | AB5: 【-】
A6: 5 | B6: 小程序 | C6: 1007756670 | D6: 45746 | E6: 0.48201389 | F6: 【万龙】全雪区日场4小时雪票 | G6: 1 | H6: 已核销 | I6: -260 | J6: -275 | K6: 0 | L6: -15 | M6: 汪萌 | N6: 13910232858 | O6: 【-】 | P6: 【-】 | Q6: 【-】 | R6: 【-】 | S6: 【-】 | T6: 【-】 | U6: QJ_XP_20250330_054016_ZF_01 | V6: -275 | W6: 45746 | X6: 0.48149306 | Y6: 【-】 | Z6: 【-】 | AA6: 【-】 | AB6: 【-】
A7: 6 | B7: 小程序 | C7: 1007775070 | D7: 45746 | E7: 0.48150463 | F7: 【万龙】全雪区日场4小时雪票 | G7: 1 | H7: 已核销 | I7: -260 | J7: -275 | K7: 0 | L7: -15 | M7: 张叶 | N7: 18610276164 | O7: 【-】 | P7: 【-】 | Q7: 【-】 | R7: 【-】 | S7: 【-】 | T7: 【-】 | U7: QJ_XP_20250330_054015_ZF_01 | V7: -275 | W7: 45746 | X7: 0.48083333 | Y7: 【-】 | Z7: 【-】 | AA7: 【-】 | AB7: 【-】
A8: 7 | B8: 小程序 | C8: 1007705616 | D8: 45746 | E8: 0.37780093 | F8: 【万龙】全雪区日场1天雪票 | G8: 1 | H8: 已核销 | I8: -372 | J8: -392 | K8: 0 | L8: -20 | M8: 闫 | N8: 13164218855 | O8: 张小飞 | P8: -1 | Q8: 已分 | R8: 45746 | S8: 0.38127315 | T8: QJ_XP_20250330_053991_ZF_01_FZ_20250330_01 | U8: QJ_XP_20250330_053991_ZF_01 | V8: -392 | W8: 45746 | X8: 0.37704861 | Y8: 【-】 | Z8: 【-】 | AA8: 【-】 | AB8: 【-】
A9: 8 | B9: 小程序 | C9: 1007697567 | D9: 45746 | E9: 0.36510417 | F9: 【万龙】全雪区日场1天雪票 | G9: 1 | H9: 已取消 | I9: -372 | J9: -392 | K9: -392 | L9: 0 | M9: 秦冰玥 | N9: 13641298785 | O9: 【-】 | P9: 【-】 | Q9: 【-】 | R9: 【-】 | S9: 【-】 | T9: 【-】 | U9: QJ_XP_20250330_053989_ZF_01 | V9: -392 | W9: 45746 | X9: 0.36458333 | Y9: QJ_XP_20250330_053989_ZF_01_TK_01_20250330 | Z9: -392 | AA9: 45746 | AB9: 0.37646991
A10: 9 | B10: 小程序 | C10: 1007705412 | D10: 45746 | E10: 0.36248843 | F10: 【万龙】全雪区日场1天雪票 | G10: 1 | H10: 已取消 | I10: -372 | J10: -392 | K10: 0 | L10: 0 | M10: 秦冰玥 | N10: 13641298785 | O10: 【-】 | P10: 【-】 | Q10: 【-】 | R10: 【-】 | S10: 【-】 | T10: 【-】 | U10: QJ_XP_20250330_053988_ZF_01 | V10: -392 | W10: 45746 | X10: 0.36195602 | Y10: 【-】 | Z10: 【-】 | AA10: 【-】 | AB10: 【-】
A11: 10 | B11: 小程序 | C11: 1007583663 | D11: 45745 | E11: 0.7703125 | F11: 【万龙】旺季平日/周末夜场滑雪票(不含雪具) | G11: 1 | H11: 已核销 | I11: -175 | J11: -177 | K11: 0 | L11: -2 | M11: 高宇杰 | N11: 13141150210 | O11: 【-】 | P11: 【-】 | Q11: 【-】 | R11: 【-】 | S11: 【-】 | T11: 【-】 | U11: QJ_XP_20250329_053979_ZF_01 | V11: -177 | W11: 45745 | X11: 0.76983796 | Y11: 【-】 | Z11: 【-】 | AA11: 【-】 | AB11: 【-】
A12: 11 | B12: 小程序 | C12: 1007583659 | D12: 45745 | E12: 0.77012731 | F12: 【万龙】旺季平日/周末夜场滑雪票(不含雪具) | G12: 1 | H12: 已核销 | I12: -175 | J12: -177 | K12: 0 | L12: -2 | M12: 高宇杰 | N12: 13141150210 | O12: 【-】 | P12: 【-】 | Q12: 【-】 | R12: 【-】 | S12: 【-】 | T12: 【-】 | U12: QJ_XP_20250329_053978_ZF_01 | V12: -177 | W12: 45745 | X12: 0.76966435 | Y12: 【-】 | Z12: 【-】 | AA12: 【-】 | AB12: 【-】
A13: 12 | B13: 小程序 | C13: 1007440862 | D13: 45745 | E13: 0.4906713 | F13: 【万龙】平日/周末全雪区下午场+夜场雪票 | G13: 1 | H13: 已核销 | I13: -335 | J13: -345 | K13: 0 | L13: -10 | M13: 边子豪 | N13: 18817460587 | O13: 【-】 | P13: 【-】 | Q13: 【-】 | R13: 【-】 | S13: 【-】 | T13: 【-】 | U13: QJ_XP_20250329_053952_ZF_01 | V13: -345 | W13: 45745 | X13: 0.49013889 | Y13: 【-】 | Z13: 【-】 | AA13: 【-】 | AB13: 【-】
A14: 13 | B14: 小程序 | C14: 1007439923 | D14: 45745 | E14: 0.48883102 | F14: 【万龙】平日/周末全雪区下午场+夜场雪票 | G14: 1 | H14: 已核销 | I14: -335 | J14: -345 | K14: 0 | L14: -10 | M14: 李志龙 | N14: 17700081093 | O14: 【-】 | P14: 【-】 | Q14: 【-】 | R14: 【-】 | S14: 【-】 | T14: 【-】 | U14: QJ_XP_20250329_053951_ZF_01 | V14: -345 | W14: 45745 | X14: 0.48834491 | Y14: 【-】 | Z14: 【-】 | AA14: 【-】 | AB14: 【-】
A15: 14 | B15: 小程序 | C15: 1007413024 | D15: 45745 | E15: 0.39184028 | F15: 【万龙】旺季平日/周末夜场滑雪票(不含雪具) | G15: 1 | H15: 已取消 | I15: -175 | J15: -177 | K15: -177 | L15: 0 | M15: 苍杰（个人） | N15: 18601197897 | O15: 【-】 | P15: 【-】 | Q15: 【-】 | R15: 【-】 | S15: 【-】 | T15: 【-】 | U15: QJ_XP_20250329_053932_ZF_01 | V15: -177 | W15: 45745 | X15: 0.3912963 | Y15: QJ_XP_20250329_053932_ZF_01_TK_01_20250329 | Z15: -177 | AA15: 45745 | AB15: 0.3946875
A16: 15 | B16: 小程序 | C16: 1007384308 | D16: 45745 | E16: 0.32335648 | F16: 【万龙】全雪区日场2天雪票 | G16: 1 | H16: 已取消 | I16: -697 | J16: -717 | K16: -717 | L16: 0 | M16: 吴丹岑 | N16: 13918161450 | O16: 【-】 | P16: 【-】 | Q16: 【-】 | R16: 【-】 | S16: 【-】 | T16: 【-】 | U16: QJ_XP_20250329_053917_ZF_01 | V16: -717 | W16: 45745 | X16: 0.32287037 | Y16: QJ_XP_20250329_053917_ZF_01_TK_01_20250329 | Z16: -717 | AA16: 45745 | AB16: 0.33770833
A17: 16 | B17: 小程序 | C17: 1007381326 | D17: 45745 | E17: 0.32103009 | F17: 【万龙】全雪区日场2天雪票 | G17: 1 | H17: 已取消 | I17: -697 | J17: -717 | K17: -717 | L17: 0 | M17: 杨 | N17: 13918664281 | O17: 【-】 | P17: 【-】 | Q17: 【-】 | R17: 【-】 | S17: 【-】 | T17: 【-】 | U17: QJ_XP_20250329_053915_ZF_01 | V17: -717 | W17: 45745 | X17: 0.32056713 | Y17: QJ_XP_20250329_053915_ZF_01_TK_01_20250329 | Z17: -717 | AA17: 45745 | AB17: 0.33758102
A18: 17 | B18: 小程序 | C18: 1007099559 | D18: 45744 | E18: 0.45207176 | F18: 【万龙】全雪区日场4小时雪票 | G18: 1 | H18: 已核销 | I18: -232 | J18: -244 | K18: 0 | L18: -12 | M18: 高宇杰 | N18: 15733799977 | O18: 【-】 | P18: 【-】 | Q18: 【-】 | R18: 【-】 | S18: 【-】 | T18: 【-】 | U18: QJ_XP_20250328_053892_ZF_01 | V18: -244 | W18: 45744 | X18: 0.45164352 | Y18: 【-】 | Z18: 【-】 | AA18: 【-】 | AB18: 【-】
A19: 18 | B19: 小程序 | C19: 1007102496 | D19: 45744 | E19: 0.44755787 | F19: 【万龙】全雪区日场4小时雪票 | G19: 1 | H19: 已核销 | I19: -232 | J19: -244 | K19: 0 | L19: -12 | M19: 汪梓涵 | N19: 13141150210 | O19: 【-】 | P19: 【-】 | Q19: 【-】 | R19: 【-】 | S19: 【-】 | T19: 【-】 | U19: QJ_XP_20250328_053890_ZF_01 | V19: -244 | W19: 45744 | X19: 0.44711806 | Y19: 【-】 | Z19: 【-】 | AA19: 【-】 | AB19: 【-】
A20: 19 | B20: 小程序 | C20: 1007058634 | D20: 45744 | E20: 0.38518519 | F20: 【万龙】全雪区日场1天雪票 | G20: 1 | H20: 已核销 | I20: -279 | J20: -292 | K20: 0 | L20: -13 | M20: 俞 | N20: 13701681552 | O20: 【-】 | P20: 【-】 | Q20: 【-】 | R20: 【-】 | S20: 【-】 | T20: 【-】 | U20: QJ_XP_20250328_053885_ZF_01 | V20: -292 | W20: 45744 | X20: 0.38475694 | Y20: 【-】 | Z20: 【-】 | AA20: 【-】 | AB20: 【-】
A21: 20 | B21: 小程序 | C21: 1007058629 | D21: 45744 | E21: 0.38476852 | F21: 【万龙】全雪区日场1天雪票 | G21: 1 | H21: 已核销 | I21: -279 | J21: -292 | K21: 0 | L21: -13 | M21: 王超 | N21: 18601696716 | O21: 【-】 | P21: 【-】 | Q21: 【-】 | R21: 【-】 | S21: 【-】 | T21: 【-】 | U21: QJ_XP_20250328_053884_ZF_01 | V21: -292 | W21: 45744 | X21: 0.3843287 | Y21: 【-】 | Z21: 【-】 | AA21: 【-】 | AB21: 【-】
A22: 21 | B22: 小程序 | C22: 1007050631 | D22: 45744 | E22: 0.38465278 | F22: 【万龙】全雪区日场1天雪票 | G22: 1 | H22: 已核销 | I22: -279 | J22: -292 | K22: 0 | L22: -13 | M22: 李晓敏 | N22: 15618562616 | O22: 【-】 | P22: 【-】 | Q22: 【-】 | R22: 【-】 | S22: 【-】 | T22: 【-】 | U22: QJ_XP_20250328_053883_ZF_01 | V22: -292 | W22: 45744 | X22: 0.38420139 | Y22: 【-】 | Z22: 【-】 | AA22: 【-】 | AB22: 【-】
A23: 22 | B23: 小程序 | C23: 1006573648 | D23: 45742 | E23: 0.39990741 | F23: 【万龙】全雪区日场1天雪票 | G23: 1 | H23: 已核销 | I23: -279 | J23: -292 | K23: 0 | L23: -13 | M23: 孟清扬 | N23: 15110118046 | O23: 王政 | P23: -1 | Q23: 已分 | R23: 45742 | S23: 0.61189815 | T23: QJ_XP_20250326_053811_ZF_01_FZ_20250326_01 | U23: QJ_XP_20250326_053811_ZF_01 | V23: -292 | W23: 45742 | X23: 0.39939815 | Y23: 【-】 | Z23: 【-】 | AA23: 【-】 | AB23: 【-】
A24: 23 | B24: 小程序 | C24: 1006574659 | D24: 45742 | E24: 0.3996412 | F24: 【万龙】全雪区日场1天雪票 | G24: 1 | H24: 已核销 | I24: -279 | J24: -292 | K24: 0 | L24: -13 | M24: 孟清扬 | N24: 15110118046 | O24: 王政 | P24: -1 | Q24: 已分 | R24: 45742 | S24: 0.6119213 | T24: QJ_XP_20250326_053810_ZF_01_FZ_20250326_01 | U24: QJ_XP_20250326_053810_ZF_01 | V24: -292 | W24: 45742 | X24: 0.3991088 | Y24: 【-】 | Z24: 【-】 | AA24: 【-】 | AB24: 【-】
A25: 24 | B25: 小程序 | C25: 1006572671 | D25: 45742 | E25: 0.39916667 | F25: 【万龙】全雪区日场1天雪票 | G25: 1 | H25: 已核销 | I25: -279 | J25: -292 | K25: 0 | L25: -13 | M25: 孟清扬 | N25: 15110118046 | O25: 王政 | P25: -1 | Q25: 已分 | R25: 45742 | S25: 0.61194444 | T25: QJ_XP_20250326_053809_ZF_01_FZ_20250326_01 | U25: QJ_XP_20250326_053809_ZF_01 | V25: -292 | W25: 45742 | X25: 0.39872685 | Y25: 【-】 | Z25: 【-】 | AA25: 【-】 | AB25: 【-】
A26: 25 | B26: 小程序 | C26: 1005797716 | D26: 45739 | E26: 0.42153935 | F26: 【万龙】全雪区日场4小时雪票 | G26: 1 | H26: 已核销 | I26: -371 | J26: -386 | K26: 0 | L26: -15 | M26: 俞圣伦 | N26: 13911519673 | O26: 【-】 | P26: 【-】 | Q26: 【-】 | R26: 【-】 | S26: 【-】 | T26: 【-】 | U26: QJ_XP_20250323_053758_ZF_01 | V26: -386 | W26: 45739 | X26: 0.42108796 | Y26: 【-】 | Z26: 【-】 | AA26: 【-】 | AB26: 【-】
A27: 26 | B27: 小程序 | C27: 1005776360 | D27: 45739 | E27: 0.36811343 | F27: 【万龙】全雪区日场1天雪票 | G27: 1 | H27: 已核销 | I27: -464 | J27: -484 | K27: 0 | L27: -20 | M27: 闫 | N27: 13164218855 | O27: 张小飞 | P27: -1 | Q27: 已分 | R27: 45742 | S27: 0.61196759 | T27: QJ_XP_20250323_053749_ZF_01_FZ_20250323_01 | U27: QJ_XP_20250323_053749_ZF_01 | V27: -484 | W27: 45739 | X27: 0.36737269 | Y27: 【-】 | Z27: 【-】 | AA27: 【-】 | AB27: 【-】
A28: 27 | B28: 小程序 | C28: 1005425132 | D28: 45738 | E28: 0.41608796 | F28: 【万龙】全雪区日场6小时雪票 | G28: 1 | H28: 已核销 | I28: -418 | J28: -443 | K28: 0 | L28: -25 | M28: 、吴 | N28: 13370128818 | O28: 【-】 | P28: 【-】 | Q28: 【-】 | R28: 【-】 | S28: 【-】 | T28: 【-】 | U28: QJ_XP_20250322_053694_ZF_01 | V28: -443 | W28: 45738 | X28: 0.41563657 | Y28: 【-】 | Z28: 【-】 | AA28: 【-】 | AB28: 【-】
A29: 28 | B29: 小程序 | C29: 1005385873 | D29: 45738 | E29: 0.4022338 | F29: 【万龙】全雪区日场4小时雪票 | G29: 1 | H29: 已核销 | I29: -371 | J29: -386 | K29: 0 | L29: -15 | M29: 舒武新（个人） | N29: 15334011584 | O29: 布乖 | P29: -1 | Q29: 未分 | R29: 【-】 | S29: 【-】 | T29: 【-】 | U29: QJ_XP_20250322_053692_ZF_01 | V29: -386 | W29: 45738 | X29: 0.40179398 | Y29: 【-】 | Z29: 【-】 | AA29: 【-】 | AB29: 【-】
A30: 29 | B30: 小程序 | C30: 1005385366 | D30: 45738 | E30: 0.37497685 | F30: 【万龙】全雪区日场6小时雪票 | G30: 1 | H30: 已核销 | I30: -418 | J30: -443 | K30: 0 | L30: -25 | M30: 卢 | N30: 18611850301 | O30: 【-】 | P30: 【-】 | Q30: 【-】 | R30: 【-】 | S30: 【-】 | T30: 【-】 | U30: QJ_XP_20250322_053682_ZF_01 | V30: -443 | W30: 45738 | X30: 0.37416667 | Y30: 【-】 | Z30: 【-】 | AA30: 【-】 | AB30: 【-】
A31: 30 | B31: 小程序 | C31: 1005385353 | D31: 45738 | E31: 0.37435185 | F31: 【万龙】全雪区日场4小时雪票 | G31: 1 | H31: 已核销 | I31: -371 | J31: -386 | K31: 0 | L31: -15 | M31: 卢 | N31: 18611850301 | O31: 【-】 | P31: 【-】 | Q31: 【-】 | R31: 【-】 | S31: 【-】 | T31: 【-】 | U31: QJ_XP_20250322_053681_ZF_01 | V31: -386 | W31: 45738 | X31: 0.37388889 | Y31: 【-】 | Z31: 【-】 | AA31: 【-】 | AB31: 【-】
A32: 31 | B32: 小程序 | C32: 1005187722 | D32: 45737 | E32: 0.74480324 | F32: 【万龙】旺季平日/周末夜场滑雪票(不含雪具) | G32: 1 | H32: 已核销 | I32: -175 | J32: -177 | K32: 0 | L32: -2 | M32: 申 | N32: 18618335329 | O32: 布乖 | P32: -1 | Q32: 未分 | R32: 【-】 | S32: 【-】 | T32: 【-】 | U32: QJ_XP_20250321_053677_ZF_01 | V32: -177 | W32: 45737 | X32: 0.74430556 | Y32: 【-】 | Z32: 【-】 | AA32: 【-】 | AB32: 【-】
A33: 32 | B33: 小程序 | C33: 1004802392 | D33: 45736 | E33: 0.60769676 | F33: 【万龙】全雪区日场1天雪票 | G33: 1 | H33: 已核销 | I33: -372 | J33: -385 | K33: 0 | L33: -13 | M33: 于 | N33: 18611155851 | O33: 白雪景（工作号） | P33: -1 | Q33: 已分 | R33: 45742 | S33: 0.61202546 | T33: QJ_XP_20250320_053629_ZF_01_FZ_20250320_01 | U33: QJ_XP_20250320_053629_ZF_01 | V33: -385 | W33: 45736 | X33: 0.60724537 | Y33: 【-】 | Z33: 【-】 | AA33: 【-】 | AB33: 【-】
A34: 33 | B34: 小程序 | C34: 1004400109 | D34: 45735 | E34: 0.33984954 | F34: 【万龙】全雪区日场2天雪票（2.15-3.21） | G34: 1 | H34: 已核销 | I34: -697 | J34: -717 | K34: 0 | L34: -20 | M34: 谢 | N34: 13811981446 | O34: 张小飞 | P34: -1 | Q34: 已分 | R34: 45742 | S34: 0.61204861 | T34: QJ_XP_20250319_053574_ZF_01_FZ_20250319_01 | U34: QJ_XP_20250319_053574_ZF_01 | V34: -717 | W34: 45735 | X34: 0.33935185 | Y34: 【-】 | Z34: 【-】 | AA34: 【-】 | AB34: 【-】
A35: 34 | B35: 小程序 | C35: 1004330906 | D35: 45734 | E35: 0.86949074 | F35: 【万龙】全雪区日场1.5天雪票（2.15-3.21） | G35: 1 | H35: 已核销 | I35: -548 | J35: -568 | K35: 0 | L35: -20 | M35: 黄年祺 | N35: 18001370703 | O35: 布乖 | P35: -1 | Q35: 已分 | R35: 45742 | S35: 0.61206019 | T35: QJ_XP_20250318_053573_ZF_01_FZ_20250318_01 | U35: QJ_XP_20250318_053573_ZF_01 | V35: -568 | W35: 45734 | X35: 0.8690625 | Y35: 【-】 | Z35: 【-】 | AA35: 【-】 | AB35: 【-】
A36: 35 | B36: 小程序 | C36: 1004331872 | D36: 45734 | E36: 0.86853009 | F36: 【万龙】全雪区日场1天雪票（2.15-3.21） | G36: 1 | H36: 已取消 | I36: -372 | J36: -385 | K36: -385 | L36: 0 | M36: 黄年祺 | N36: 18001370703 | O36: 【-】 | P36: 【-】 | Q36: 【-】 | R36: 【-】 | S36: 【-】 | T36: 【-】 | U36: QJ_XP_20250318_053572_ZF_01 | V36: -385 | W36: 45734 | X36: 0.86809028 | Y36: QJ_XP_20250318_053572_ZF_01_TK_01_20250318 | Z36: -385 | AA36: 45734 | AB36: 0.90804398
A37: 36 | B37: 小程序 | C37: 1004163121 | D37: 45734 | E37: 0.33357639 | F37: 【万龙】全雪区日场1.5天雪票（2.15-3.21） | G37: 1 | H37: 已取消 | I37: -548 | J37: -568 | K37: -568 | L37: 0 | M37: 黄年祺 | N37: 18001370703 | O37: 【-】 | P37: 【-】 | Q37: 【-】 | R37: 【-】 | S37: 【-】 | T37: 【-】 | U37: QJ_XP_20250318_053542_ZF_01 | V37: -568 | W37: 45734 | X37: 0.33300926 | Y37: QJ_XP_20250318_053542_ZF_01_TK_01_20250318 | Z37: -568 | AA37: 45734 | AB37: 0.37405093
A38: 37 | B38: 小程序 | C38: 1004091081 | D38: 45733 | E38: 0.81385417 | F38: 【万龙】旺季平日/周末夜场滑雪票(不含雪具) | G38: 1 | H38: 已取消 | I38: -175 | J38: -177 | K38: -177 | L38: 0 | M38: 苍杰（个人） | N38: 18601197897 | O38: 【-】 | P38: 【-】 | Q38: 【-】 | R38: 【-】 | S38: 【-】 | T38: 【-】 | U38: QJ_XP_20250317_053538_ZF_01 | V38: -177 | W38: 45733 | X38: 0.81335648 | Y38: QJ_XP_20250317_053538_ZF_01_TK_01_20250317 | Z38: -177 | AA38: 45733 | AB38: 0.81533565
A39: 38 | B39: 小程序 | C39: 1004067909 | D39: 45733 | E39: 0.78625 | F39: 【万龙】旺季平日/周末夜场滑雪票(不含雪具) | G39: 1 | H39: 已取消 | I39: -175 | J39: -177 | K39: -177 | L39: 0 | M39: 苍杰（个人） | N39: 18601197897 | O39: 【-】 | P39: 【-】 | Q39: 【-】 | R39: 【-】 | S39: 【-】 | T39: 【-】 | U39: QJ_XP_20250317_053537_ZF_01 | V39: -177 | W39: 45733 | X39: 0.78575231 | Y39: QJ_XP_20250317_053537_ZF_01_TK_01_20250317 | Z39: -177 | AA39: 45733 | AB39: 0.80778935
A40: 39 | B40: 小程序 | C40: 1004064884 | D40: 45733 | E40: 0.7805787 | F40: 【万龙】旺季平日/周末夜场滑雪票(不含雪具) | G40: 1 | H40: 已取消 | I40: -175 | J40: -177 | K40: -177 | L40: 0 | M40: 苍杰（个人） | N40: 18601197897 | O40: 【-】 | P40: 【-】 | Q40: 【-】 | R40: 【-】 | S40: 【-】 | T40: 【-】 | U40: QJ_XP_20250317_053536_ZF_01 | V40: -177 | W40: 45733 | X40: 0.78006944 | Y40: QJ_XP_20250317_053536_ZF_01_TK_01_20250317 | Z40: -177 | AA40: 45733 | AB40: 0.80784722
A41: 40 | B41: 小程序 | C41: 1004064850 | D41: 45733 | E41: 0.77571759 | F41: 【万龙】旺季平日/周末夜场滑雪票(不含雪具) | G41: 1 | H41: 已取消 | I41: -175 | J41: -177 | K41: -177 | L41: 0 | M41: 苍杰（个人） | N41: 18601197897 | O41: 【-】 | P41: 【-】 | Q41: 【-】 | R41: 【-】 | S41: 【-】 | T41: 【-】 | U41: QJ_XP_20250317_053535_ZF_01 | V41: -177 | W41: 45733 | X41: 0.77521991 | Y41: QJ_XP_20250317_053535_ZF_01_TK_01_20250317 | Z41: -177 | AA41: 45733 | AB41: 0.78053241
A42: 41 | B42: 小程序 | C42: 1004064757 | D42: 45733 | E42: 0.76258102 | F42: 【万龙】旺季平日/周末夜场滑雪票(不含雪具) | G42: 1 | H42: 已取消 | I42: -175 | J42: -177 | K42: -177 | L42: 0 | M42: 苍杰（个人） | N42: 18601197897 | O42: 【-】 | P42: 【-】 | Q42: 【-】 | R42: 【-】 | S42: 【-】 | T42: 【-】 | U42: QJ_XP_20250317_053534_ZF_01 | V42: -177 | W42: 45733 | X42: 0.76206019 | Y42: QJ_XP_20250317_053534_ZF_01_TK_01_20250317 | Z42: -177 | AA42: 45733 | AB42: 0.78045139
A43: 42 | B43: 小程序 | C43: 1004041317 | D43: 45733 | E43: 0.65563657 | F43: 【万龙】旺季平日/周末夜场滑雪票(不含雪具) | G43: 1 | H43: 已取消 | I43: -175 | J43: -180 | K43: -180 | L43: 0 | M43: 苍杰（个人） | N43: 18601197897 | O43: 【-】 | P43: 【-】 | Q43: 【-】 | R43: 【-】 | S43: 【-】 | T43: 【-】 | U43: QJ_XP_20250317_053527_ZF_01 | V43: -180 | W43: 45733 | X43: 0.65510417 | Y43: QJ_XP_20250317_053527_ZF_01_TK_01_20250317 | Z43: -180 | AA43: 45733 | AB43: 0.76244213
A44: 43 | B44: 小程序 | C44: 1004039229 | D44: 45733 | E44: 0.65050926 | F44: 【万龙】旺季平日/周末夜场滑雪票(不含雪具) | G44: 1 | H44: 已取消 | I44: -175 | J44: -180 | K44: -180 | L44: 0 | M44: 苍杰（个人） | N44: 18601197897 | O44: 【-】 | P44: 【-】 | Q44: 【-】 | R44: 【-】 | S44: 【-】 | T44: 【-】 | U44: QJ_XP_20250317_053525_ZF_01 | V44: -180 | W44: 45733 | X44: 0.65005787 | Y44: QJ_XP_20250317_053525_ZF_01_TK_01_20250317 | Z44: -180 | AA44: 45733 | AB44: 0.65427083
A45: 44 | B45: 小程序 | C45: 1003964469 | D45: 45733 | E45: 0.41506944 | F45: 【万龙】全雪区日场6小时雪票（2.15-3.21） | G45: 1 | H45: 已核销 | I45: -334 | J45: -359 | K45: 0 | L45: -25 | M45: 依 | N45: 18600810076 | O45: 肖志强（工作号） | P45: -1 | Q45: 已分 | R45: 45742 | S45: 0.61207176 | T45: QJ_XP_20250317_053511_ZF_01_FZ_20250317_01 | U45: QJ_XP_20250317_053511_ZF_01 | V45: -359 | W45: 45733 | X45: 0.41497685 | Y45: 【-】 | Z45: 【-】 | AA45: 【-】 | AB45: 【-】
A46: 45 | B46: 小程序 | C46: 1003964464 | D46: 45733 | E46: 0.41487269 | F46: 【万龙】全雪区日场6小时雪票（2.15-3.21） | G46: 1 | H46: 已核销 | I46: -334 | J46: -359 | K46: 0 | L46: -25 | M46: 依 | N46: 18600810076 | O46: 肖志强（工作号） | P46: -1 | Q46: 已分 | R46: 45742 | S46: 0.61209491 | T46: QJ_XP_20250317_053510_ZF_01_FZ_20250317_01 | U46: QJ_XP_20250317_053510_ZF_01 | V46: -359 | W46: 45733 | X46: 0.41478009 | Y46: 【-】 | Z46: 【-】 | AA46: 【-】 | AB46: 【-】
A47: 46 | B47: 小程序 | C47: 1003902747 | D47: 45732 | E47: 0.93199074 | F47: 【万龙】全雪区日场4小时雪票 | G47: 1 | H47: 已取消 | I47: -288 | J47: -348 | K47: -348 | L47: 0 | M47: 苍杰（个人） | N47: 18601197897 | O47: 【-】 | P47: 【-】 | Q47: 【-】 | R47: 【-】 | S47: 【-】 | T47: 【-】 | U47: QJ_XP_20250316_053503_ZF_01 | V47: -348 | W47: 45732 | X47: 0.93184028 | Y47: QJ_XP_20250316_053503_ZF_01_TK_01_20250317 | Z47: -348 | AA47: 45733 | AB47: 0.53737269
A48: 47 | B48: 小程序 | C48: 1003899402 | D48: 45732 | E48: 0.90465278 | F48: 【万龙】全雪区日场4小时雪票 | G48: 1 | H48: 已取消 | I48: -288 | J48: -348 | K48: -348 | L48: 0 | M48: 苍杰（个人） | N48: 18601197897 | O48: 【-】 | P48: 【-】 | Q48: 【-】 | R48: 【-】 | S48: 【-】 | T48: 【-】 | U48: QJ_XP_20250316_053498_ZF_01 | V48: -348 | W48: 45732 | X48: 0.90451389 | Y48: QJ_XP_20250316_053498_ZF_01_TK_01_20250316 | Z48: -348 | AA48: 45732 | AB48: 0.9099537
A49: 48 | B49: 小程序 | C49: 1003898329 | D49: 45732 | E49: 0.88959491 | F49: 【万龙】全雪区日场4小时雪票 | G49: 1 | H49: 已取消 | I49: -288 | J49: -348 | K49: -348 | L49: 0 | M49: 苍杰（个人） | N49: 18601197897 | O49: 【-】 | P49: 【-】 | Q49: 【-】 | R49: 【-】 | S49: 【-】 | T49: 【-】 | U49: QJ_XP_20250316_053497_ZF_01 | V49: -348 | W49: 45732 | X49: 0.88946759 | Y49: QJ_XP_20250316_053497_ZF_01_TK_01_20250316 | Z49: -348 | AA49: 45732 | AB49: 0.91019676
A50: 49 | B50: 小程序 | C50: 1003898290 | D50: 45732 | E50: 0.88530093 | F50: 【万龙】全雪区日场4小时雪票 | G50: 1 | H50: 已取消 | I50: -288 | J50: -348 | K50: -348 | L50: 0 | M50: 苍杰（个人） | N50: 18601197897 | O50: 【-】 | P50: 【-】 | Q50: 【-】 | R50: 【-】 | S50: 【-】 | T50: 【-】 | U50: QJ_XP_20250316_053496_ZF_01 | V50: -348 | W50: 45732 | X50: 0.88516204 | Y50: QJ_XP_20250316_053496_ZF_01_TK_01_20250316 | Z50: -348 | AA50: 45732 | AB50: 0.88925926
A51: 50 | B51: 小程序 | C51: 1003901119 | D51: 45732 | E51: 0.87565972 | F51: 【万龙】全雪区日场4小时雪票 | G51: 1 | H51: 已取消 | I51: -288 | J51: -348 | K51: -348 | L51: 0 | M51: 苍杰（个人） | N51: 18601197897 | O51: 【-】 | P51: 【-】 | Q51: 【-】 | R51: 【-】 | S51: 【-】 | T51: 【-】 | U51: QJ_XP_20250316_053495_ZF_01 | V51: -348 | W51: 45732 | X51: 0.87553241 | Y51: QJ_XP_20250316_053495_ZF_01_TK_01_20250316 | Z51: -348 | AA51: 45732 | AB51: 0.88502315
A52: 51 | B52: 大好河山 | C52: 1003877909 | D52: 45732 | E52: 0.84773148 | F52: 【万龙】旺季平日/周末夜场滑雪票(不含雪具) | G52: 1 | H52: 已取消 | I52: -190 | J52: 0 | K52: 0 | L52: 0 | M52: 苍杰（个人） | N52: 18601197897 | O52: 【-】 | P52: 【-】 | Q52: 【-】 | R52: 【-】 | S52: 【-】 | T52: 【-】 | U52: 【-】 | V52: 【-】 | W52: 【-】 | X52: 【-】 | Y52: 【-】 | Z52: 【-】 | AA52: 【-】 | AB52: 【-】
A53: 52 | B53: 小程序 | C53: 1003882284 | D53: 45732 | E53: 0.7787963 | F53: 【万龙】旺季平日/周末夜场滑雪票(不含雪具) | G53: 1 | H53: 已取消 | I53: -190 | J53: -195 | K53: -195 | L53: 0 | M53: 苍杰（个人） | N53: 18601197897 | O53: 【-】 | P53: 【-】 | Q53: 【-】 | R53: 【-】 | S53: 【-】 | T53: 【-】 | U53: QJ_XP_20250316_053487_ZF_01 | V53: -195 | W53: 45732 | X53: 0.77865741 | Y53: QJ_XP_20250316_053487_ZF_01_TK_01_20250316 | Z53: -195 | AA53: 45732 | AB53: 0.87027778
A54: 53 | B54: 小程序 | C54: 1003882178 | D54: 45732 | E54: 0.76284722 | F54: 【万龙】旺季平日/周末夜场滑雪票(不含雪具) | G54: 1 | H54: 已取消 | I54: -190 | J54: -195 | K54: -195 | L54: 0 | M54: 苍杰（个人） | N54: 18601197897 | O54: 【-】 | P54: 【-】 | Q54: 【-】 | R54: 【-】 | S54: 【-】 | T54: 【-】 | U54: QJ_XP_20250316_053482_ZF_01 | V54: -195 | W54: 45732 | X54: 0.76270833 | Y54: QJ_XP_20250316_053482_ZF_01_TK_01_20250316 | Z54: -195 | AA54: 45732 | AB54: 0.77149306
A55: 54 | B55: 小程序 | C55: 1003827931 | D55: 45732 | E55: 0.6390625 | F55: 【万龙】旺季平日/周末夜场滑雪票(不含雪具) | G55: 1 | H55: 已取消 | I55: -190 | J55: -195 | K55: -195 | L55: 0 | M55: 苍杰（个人） | N55: 18800000000 | O55: 【-】 | P55: 【-】 | Q55: 【-】 | R55: 【-】 | S55: 【-】 | T55: 【-】 | U55: QJ_XP_20250316_053473_ZF_01 | V55: -195 | W55: 45732 | X55: 0.63891204 | Y55: QJ_XP_20250316_053473_ZF_01_TK_01_20250316 | Z55: -195 | AA55: 45732 | AB55: 0.66584491
A56: 55 | B56: 小程序 | C56: 1003795021 | D56: 45732 | E56: 0.53103009 | F56: 【万龙】全雪区日场4小时雪票 | G56: 1 | H56: 已核销 | I56: -381 | J56: -396 | K56: 0 | L56: -15 | M56: 王 | N56: 13810404291 | O56: 肖志强（工作号） | P56: -1 | Q56: 已分 | R56: 45732 | S56: 0.53268519 | T56: QJ_XP_20250316_052750_ZF_01_FZ_20250316_01 | U56: QJ_XP_20250316_052750_ZF_01 | V56: -396 | W56: 45732 | X56: 0.53090278 | Y56: 【-】 | Z56: 【-】 | AA56: 【-】 | AB56: 【-】
A57: 56 | B57: 小程序 | C57: 1003794061 | D57: 45732 | E57: 0.5305787 | F57: 【万龙】全雪区日场4小时雪票 | G57: 1 | H57: 已核销 | I57: -381 | J57: -396 | K57: 0 | L57: -15 | M57: 王 | N57: 13810404291 | O57: 肖志强（工作号） | P57: -1 | Q57: 已分 | R57: 45732 | S57: 0.53267361 | T57: QJ_XP_20250316_052748_ZF_01_FZ_20250316_01 | U57: QJ_XP_20250316_052748_ZF_01 | V57: -396 | W57: 45732 | X57: 0.53049769 | Y57: 【-】 | Z57: 【-】 | AA57: 【-】 | AB57: 【-】
A58: 57 | B58: 小程序 | C58: 1003765692 | D58: 45732 | E58: 0.50773148 | F58: 【万龙】平日/周末全雪区下午场+夜场雪票（2.15-3.7） | G58: 1 | H58: 已核销 | I58: -470 | J58: -480 | K58: 0 | L58: -10 | M58: 刘迈 | N58: 15510581719 | O58: 【-】 | P58: 【-】 | Q58: 【-】 | R58: 【-】 | S58: 【-】 | T58: 【-】 | U58: QJ_XP_20250316_052739_ZF_01 | V58: -480 | W58: 45732 | X58: 0.50765046 | Y58: 【-】 | Z58: 【-】 | AA58: 【-】 | AB58: 【-】
A59: 58 | B59: 小程序 | C59: 1003759196 | D59: 45732 | E59: 0.46773148 | F59: 【万龙】全雪区日场4小时雪票 | G59: 1 | H59: 已核销 | I59: -381 | J59: -396 | K59: 0 | L59: -15 | M59: charles | N59: 18600039086 | O59: 布乖 | P59: -1 | Q59: 未分 | R59: 【-】 | S59: 【-】 | T59: 【-】 | U59: QJ_XP_20250316_052727_ZF_01 | V59: -396 | W59: 45732 | X59: 0.46766204 | Y59: 【-】 | Z59: 【-】 | AA59: 【-】 | AB59: 【-】
A60: 59 | B60: 小程序 | C60: 1003763143 | D60: 45732 | E60: 0.46680556 | F60: 【万龙】全雪区日场4小时雪票 | G60: 1 | H60: 已核销 | I60: -381 | J60: -396 | K60: 0 | L60: -15 | M60: charles | N60: 18600039086 | O60: 布乖 | P60: -1 | Q60: 已分 | R60: 45732 | S60: 0.46878472 | T60: QJ_XP_20250316_052726_ZF_01_FZ_20250316_01 | U60: QJ_XP_20250316_052726_ZF_01 | V60: -396 | W60: 45732 | X60: 0.46672454 | Y60: 【-】 | Z60: 【-】 | AA60: 【-】 | AB60: 【-】
A61: 60 | B61: 小程序 | C61: 1003760130 | D61: 45732 | E61: 0.465625 | F61: 【万龙】全雪区日场4小时雪票 | G61: 1 | H61: 已核销 | I61: -381 | J61: -396 | K61: 0 | L61: -15 | M61: 李雨昂 | N61: 13651169622 | O61: 张小飞 | P61: -1 | Q61: 未分 | R61: 【-】 | S61: 【-】 | T61: 【-】 | U61: QJ_XP_20250316_052725_ZF_01 | V61: -396 | W61: 45732 | X61: 0.46554398 | Y61: 【-】 | Z61: 【-】 | AA61: 【-】 | AB61: 【-】
A62: 61 | B62: 小程序 | C62: 1003731957 | D62: 45732 | E62: 0.4553125 | F62: 【万龙】全雪区日场4小时雪票 | G62: 1 | H62: 已取消 | I62: -381 | J62: -396 | K62: -396 | L62: 0 | M62: 李雨昂 | N62: 13651169622 | O62: 【-】 | P62: 【-】 | Q62: 【-】 | R62: 【-】 | S62: 【-】 | T62: 【-】 | U62: QJ_XP_20250316_052723_ZF_01 | V62: -396 | W62: 45732 | X62: 0.45521991 | Y62: QJ_XP_20250316_052723_ZF_01_TK_01_20250316 | Z62: -396 | AA62: 45732 | AB62: 0.46541667
A63: 62 | B63: 小程序 | C63: 1003735911 | D63: 45732 | E63: 0.45505787 | F63: 【万龙】全雪区日场4小时雪票 | G63: 1 | H63: 已核销 | I63: -381 | J63: -396 | K63: 0 | L63: -15 | M63: 李雨昂 | N63: 13651169622 | O63: 张小飞 | P63: -1 | Q63: 已分 | R63: 45732 | S63: 0.46600694 | T63: QJ_XP_20250316_052722_ZF_01_FZ_20250316_01 | U63: QJ_XP_20250316_052722_ZF_01 | V63: -396 | W63: 45732 | X63: 0.45497685 | Y63: 【-】 | Z63: 【-】 | AA63: 【-】 | AB63: 【-】
A64: 63 | B64: 小程序 | C64: 1003702988 | D64: 45732 | E64: 0.39548611 | F64: 【万龙】全雪区日场4小时雪票 | G64: 1 | H64: 已核销 | I64: -381 | J64: -396 | K64: 0 | L64: -15 | M64: 依 | N64: 18600810076 | O64: 肖志强（工作号） | P64: -1 | Q64: 已分 | R64: 45732 | S64: 0.40349537 | T64: QJ_XP_20250316_052700_ZF_01_FZ_20250316_01 | U64: QJ_XP_20250316_052700_ZF_01 | V64: -396 | W64: 45732 | X64: 0.39540509 | Y64: 【-】 | Z64: 【-】 | AA64: 【-】 | AB64: 【-】
A65: 64 | B65: 小程序 | C65: 1003703618 | D65: 45732 | E65: 0.36582176 | F65: 【万龙】全雪区日场1天雪票（2.15-3.21） | G65: 1 | H65: 已核销 | I65: -539 | J65: -559 | K65: 0 | L65: -20 | M65: 魏 | N65: 13510660342 | O65: 张小飞 | P65: -1 | Q65: 已分 | R65: 45732 | S65: 0.3715625 | T65: QJ_XP_20250316_052692_ZF_01_FZ_20250316_01 | U65: QJ_XP_20250316_052692_ZF_01 | V65: -559 | W65: 45732 | X65: 0.36574074 | Y65: 【-】 | Z65: 【-】 | AA65: 【-】 | AB65: 【-】
A66: 65 | B66: 小程序 | C66: 1003702625 | D66: 45732 | E66: 0.36135417 | F66: 【万龙】全雪区日场4小时雪票 | G66: 1 | H66: 已核销 | I66: -381 | J66: -396 | K66: 0 | L66: -15 | M66: 申 | N66: 18618335329 | O66: 布乖 | P66: -1 | Q66: 已分 | R66: 45732 | S66: 0.36600694 | T66: QJ_XP_20250316_052690_ZF_01_FZ_20250316_01 | U66: QJ_XP_20250316_052690_ZF_01 | V66: -396 | W66: 45732 | X66: 0.36128472 | Y66: 【-】 | Z66: 【-】 | AA66: 【-】 | AB66: 【-】
A67: 66 | B67: 小程序 | C67: 1003700606 | D67: 45732 | E67: 0.35634259 | F67: 【万龙】全雪区日场4小时雪票 | G67: 1 | H67: 已核销 | I67: -381 | J67: -396 | K67: 0 | L67: -15 | M67: 吴 | N67: 18601361956 | O67: 布乖 | P67: -1 | Q67: 已分 | R67: 45732 | S67: 0.35769676 | T67: QJ_XP_20250316_052686_ZF_01_FZ_20250316_01 | U67: QJ_XP_20250316_052686_ZF_01 | V67: -396 | W67: 45732 | X67: 0.35621528 | Y67: 【-】 | Z67: 【-】 | AA67: 【-】 | AB67: 【-】
A68: 67 | B68: 小程序 | C68: 1003700603 | D68: 45732 | E68: 0.35613426 | F68: 【万龙】全雪区日场4小时雪票 | G68: 1 | H68: 已核销 | I68: -381 | J68: -396 | K68: 0 | L68: -15 | M68: 吴 | N68: 18601361956 | O68: 布乖 | P68: -1 | Q68: 已分 | R68: 45732 | S68: 0.35767361 | T68: QJ_XP_20250316_052684_ZF_01_FZ_20250316_01 | U68: QJ_XP_20250316_052684_ZF_01 | V68: -396 | W68: 45732 | X68: 0.35605324 | Y68: 【-】 | Z68: 【-】 | AA68: 【-】 | AB68: 【-】
A69: 68 | B69: 小程序 | C69: 1003703443 | D69: 45732 | E69: 0.35015046 | F69: 【万龙】全雪区日场4小时雪票 | G69: 1 | H69: 已核销 | I69: -381 | J69: -396 | K69: 0 | L69: -15 | M69: 张浩 | N69: 13810947565 | O69: 【-】 | P69: 【-】 | Q69: 【-】 | R69: 【-】 | S69: 【-】 | T69: 【-】 | U69: QJ_XP_20250316_052679_ZF_01 | V69: -396 | W69: 45732 | X69: 0.35005787 | Y69: 【-】 | Z69: 【-】 | AA69: 【-】 | AB69: 【-】
A70: 69 | B70: 小程序 | C70: 1003702467 | D70: 45732 | E70: 0.34805556 | F70: 【万龙】全雪区日场4小时雪票 | G70: 1 | H70: 已核销 | I70: -381 | J70: -396 | K70: 0 | L70: -15 | M70: 张浩 | N70: 13810947565 | O70: 【-】 | P70: 【-】 | Q70: 【-】 | R70: 【-】 | S70: 【-】 | T70: 【-】 | U70: QJ_XP_20250316_052677_ZF_01 | V70: -396 | W70: 45732 | X70: 0.34795139 | Y70: 【-】 | Z70: 【-】 | AA70: 【-】 | AB70: 【-】
A71: 70 | B71: 小程序 | C71: 1003700442 | D71: 45732 | E71: 0.33997685 | F71: 【万龙】全雪区日场4小时雪票 | G71: 1 | H71: 已核销 | I71: -381 | J71: -396 | K71: 0 | L71: -15 | M71: 古 | N71: 13764752798 | O71: 【-】 | P71: 【-】 | Q71: 【-】 | R71: 【-】 | S71: 【-】 | T71: 【-】 | U71: QJ_XP_20250316_052674_ZF_01 | V71: -396 | W71: 45732 | X71: 0.33984954 | Y71: 【-】 | Z71: 【-】 | AA71: 【-】 | AB71: 【-】
A72: 71 | B72: 小程序 | C72: 1003700440 | D72: 45732 | E72: 0.33975694 | F72: 【万龙】全雪区日场4小时雪票 | G72: 1 | H72: 已核销 | I72: -381 | J72: -396 | K72: 0 | L72: -15 | M72: 古 | N72: 13764752798 | O72: 【-】 | P72: 【-】 | Q72: 【-】 | R72: 【-】 | S72: 【-】 | T72: 【-】 | U72: QJ_XP_20250316_052673_ZF_01 | V72: -396 | W72: 45732 | X72: 0.33966435 | Y72: 【-】 | Z72: 【-】 | AA72: 【-】 | AB72: 【-】
A73: 72 | B73: 小程序 | C73: 1003703340 | D73: 45732 | E73: 0.33814815 | F73: 【万龙】全雪区日场4小时雪票 | G73: 1 | H73: 已核销 | I73: -381 | J73: -396 | K73: 0 | L73: -15 | M73: 石洋 | N73: 18518939600 | O73: 【-】 | P73: 【-】 | Q73: 【-】 | R73: 【-】 | S73: 【-】 | T73: 【-】 | U73: QJ_XP_20250316_052672_ZF_01 | V73: -396 | W73: 45732 | X73: 0.33787037 | Y73: 【-】 | Z73: 【-】 | AA73: 【-】 | AB73: 【-】
A74: 73 | B74: 小程序 | C74: 1003701408 | D74: 45732 | E74: 0.33674769 | F74: 【万龙】全雪区日场4小时雪票 | G74: 1 | H74: 已核销 | I74: -381 | J74: -396 | K74: 0 | L74: -15 | M74: 刘跃飞 | N74: 18600864997 | O74: 【-】 | P74: 【-】 | Q74: 【-】 | R74: 【-】 | S74: 【-】 | T74: 【-】 | U74: QJ_XP_20250316_052670_ZF_01 | V74: -396 | W74: 45732 | X74: 0.33663194 | Y74: 【-】 | Z74: 【-】 | AA74: 【-】 | AB74: 【-】
A75: 74 | B75: 小程序 | C75: 1003670589 | D75: 45731 | E75: 0.96354167 | F75: 【万龙】全雪区日场6小时雪票（2.15-3.21） | G75: 1 | H75: 已核销 | I75: -465 | J75: -490 | K75: 0 | L75: -25 | M75: 易 | N75: 15801324035 | O75: 【-】 | P75: 【-】 | Q75: 【-】 | R75: 【-】 | S75: 【-】 | T75: 【-】 | U75: QJ_XP_20250315_052667_ZF_01 | V75: -490 | W75: 45731 | X75: 0.96337963 | Y75: 【-】 | Z75: 【-】 | AA75: 【-】 | AB75: 【-】
A76: 75 | B76: 大好河山 | C76: 1003589858 | D76: 45731 | E76: 0.71988426 | F76: 【万龙】旺季平日/周末夜场滑雪票(不含雪具) | G76: 1 | H76: 已取消 | I76: -190 | J76: 0 | K76: 0 | L76: 0 | M76: 苍杰 | N76: 18601197897 | O76: 【-】 | P76: 【-】 | Q76: 【-】 | R76: 【-】 | S76: 【-】 | T76: 【-】 | U76: 【-】 | V76: 【-】 | W76: 【-】 | X76: 【-】 | Y76: 【-】 | Z76: 【-】 | AA76: 【-】 | AB76: 【-】
A77: 76 | B77: 大好河山 | C77: 1003587316 | D77: 45731 | E77: 0.66748843 | F77: 【万龙】旺季平日/周末夜场滑雪票(不含雪具) | G77: 1 | H77: 已取消 | I77: -190 | J77: 0 | K77: 0 | L77: 0 | M77: 苍杰 | N77: 18800000000 | O77: 【-】 | P77: 【-】 | Q77: 【-】 | R77: 【-】 | S77: 【-】 | T77: 【-】 | U77: 【-】 | V77: 【-】 | W77: 【-】 | X77: 【-】 | Y77: 【-】 | Z77: 【-】 | AA77: 【-】 | AB77: 【-】
A78: 77 | B78: 小程序 | C78: 1003490300 | D78: 45731 | E78: 0.43988426 | F78: 【万龙】全雪区日场1.5天雪票（2.15-3.21） | G78: 1 | H78: 已核销 | I78: -809 | J78: -829 | K78: 0 | L78: -20 | M78: 姬 | N78: 17611411175 | O78: 肖志强（工作号） | P78: -1 | Q78: 已分 | R78: 45731 | S78: 0.44378472 | T78: QJ_XP_20250315_052538_ZF_01_FZ_20250315_01 | U78: QJ_XP_20250315_052538_ZF_01 | V78: -829 | W78: 45731 | X78: 0.43978009 | Y78: 【-】 | Z78: 【-】 | AA78: 【-】 | AB78: 【-】
A79: 78 | B79: 小程序 | C79: 1003487379 | D79: 45731 | E79: 0.4387963 | F79: 【万龙】全雪区日场1.5天雪票（2.15-3.21） | G79: 1 | H79: 已核销 | I79: -809 | J79: -829 | K79: 0 | L79: -20 | M79: 陈 | N79: 13522107060 | O79: 肖志强（工作号） | P79: -1 | Q79: 已分 | R79: 45731 | S79: 0.44239583 | T79: QJ_XP_20250315_052537_ZF_01_FZ_20250315_01 | U79: QJ_XP_20250315_052537_ZF_01 | V79: -829 | W79: 45731 | X79: 0.43862269 | Y79: 【-】 | Z79: 【-】 | AA79: 【-】 | AB79: 【-】
A80: 79 | B80: 小程序 | C80: 1003468931 | D80: 45731 | E80: 0.41670139 | F80: 【万龙】全雪区日场6小时雪票（2.15-3.21） | G80: 1 | H80: 已核销 | I80: -465 | J80: -490 | K80: 0 | L80: -25 | M80: 古 | N80: 13764752798 | O80: 【-】 | P80: 【-】 | Q80: 【-】 | R80: 【-】 | S80: 【-】 | T80: 【-】 | U80: QJ_XP_20250315_052529_ZF_01 | V80: -490 | W80: 45731 | X80: 0.41662037 | Y80: 【-】 | Z80: 【-】 | AA80: 【-】 | AB80: 【-】
A81: 80 | B81: 小程序 | C81: 1003468910 | D81: 45731 | E81: 0.41556713 | F81: 【万龙】全雪区日场6小时雪票（2.15-3.21） | G81: 1 | H81: 已核销 | I81: -465 | J81: -490 | K81: 0 | L81: -25 | M81: 古 | N81: 13764752798 | O81: 【-】 | P81: 【-】 | Q81: 【-】 | R81: 【-】 | S81: 【-】 | T81: 【-】 | U81: QJ_XP_20250315_052528_ZF_01 | V81: -490 | W81: 45731 | X81: 0.41542824 | Y81: 【-】 | Z81: 【-】 | AA81: 【-】 | AB81: 【-】
A82: 81 | B82: 小程序 | C82: 1003466933 | D82: 45731 | E82: 0.41013889 | F82: 【万龙】全雪区日场6小时雪票（2.15-3.21） | G82: 1 | H82: 已核销 | I82: -465 | J82: -490 | K82: 0 | L82: -25 | M82: 吴 | N82: 18601361956 | O82: 布乖 | P82: -1 | Q82: 已分 | R82: 45731 | S82: 0.42158565 | T82: QJ_XP_20250315_052525_ZF_01_FZ_20250315_01 | U82: QJ_XP_20250315_052525_ZF_01 | V82: -490 | W82: 45731 | X82: 0.41003472 | Y82: 【-】 | Z82: 【-】 | AA82: 【-】 | AB82: 【-】
A83: 82 | B83: 小程序 | C83: 1003469815 | D83: 45731 | E83: 0.4099537 | F83: 【万龙】全雪区日场6小时雪票（2.15-3.21） | G83: 1 | H83: 已核销 | I83: -465 | J83: -490 | K83: 0 | L83: -25 | M83: 吴 | N83: 18601361956 | O83: 布乖 | P83: -1 | Q83: 已分 | R83: 45731 | S83: 0.4215625 | T83: QJ_XP_20250315_052524_ZF_01_FZ_20250315_01 | U83: QJ_XP_20250315_052524_ZF_01 | V83: -490 | W83: 45731 | X83: 0.40988426 | Y83: 【-】 | Z83: 【-】 | AA83: 【-】 | AB83: 【-】
A84: 83 | B84: 小程序 | C84: 1003466724 | D84: 45731 | E84: 0.39677083 | F84: 【万龙】全雪区日场2天雪票（2.15-3.21） | G84: 1 | H84: 已核销 | I84: -1023 | J84: -1043 | K84: 0 | L84: -20 | M84: 谢 | N84: 13811981446 | O84: 张小飞 | P84: -1 | Q84: 已分 | R84: 45731 | S84: 0.39795139 | T84: QJ_XP_20250315_052511_ZF_01_FZ_20250315_01 | U84: QJ_XP_20250315_052511_ZF_01 | V84: -1043 | W84: 45731 | X84: 0.39668981 | Y84: 【-】 | Z84: 【-】 | AA84: 【-】 | AB84: 【-】
A85: 84 | B85: 小程序 | C85: 1003468276 | D85: 45731 | E85: 0.37271991 | F85: 【万龙】全雪区日场6小时雪票（2.15-3.21） | G85: 1 | H85: 已核销 | I85: -465 | J85: -490 | K85: 0 | L85: -25 | M85: 依 | N85: 18600810076 | O85: 肖志强（工作号） | P85: -1 | Q85: 已分 | R85: 45731 | S85: 0.38684028 | T85: QJ_XP_20250315_052498_ZF_01_FZ_20250315_01 | U85: QJ_XP_20250315_052498_ZF_01 | V85: -490 | W85: 45731 | X85: 0.37259259 | Y85: 【-】 | Z85: 【-】 | AA85: 【-】 | AB85: 【-】
A86: 85 | B86: 小程序 | C86: 1003466236 | D86: 45731 | E86: 0.36520833 | F86: 【万龙】全雪区日场1天雪票（2.15-3.21） | G86: 1 | H86: 已核销 | I86: -539 | J86: -559 | K86: 0 | L86: -20 | M86: 陈 | N86: 13601388350 | O86: 张小飞 | P86: -1 | Q86: 已分 | R86: 45731 | S86: 0.36877315 | T86: QJ_XP_20250315_052492_ZF_01_FZ_20250315_01 | U86: QJ_XP_20250315_052492_ZF_01 | V86: -559 | W86: 45731 | X86: 0.36502315 | Y86: 【-】 | Z86: 【-】 | AA86: 【-】 | AB86: 【-】
A87: 86 | B87: 小程序 | C87: 1003467228 | D87: 45731 | E87: 0.3640625 | F87: 【万龙】全雪区日场1天雪票（2.15-3.21） | G87: 1 | H87: 已核销 | I87: -539 | J87: -559 | K87: 0 | L87: -20 | M87: 季波 | N87: 15629002877 | O87: 崔洋（个人） | P87: -1 | Q87: 已分 | R87: 45731 | S87: 0.36600694 | T87: QJ_XP_20250315_052491_ZF_01_FZ_20250315_01 | U87: QJ_XP_20250315_052491_ZF_01 | V87: -559 | W87: 45731 | X87: 0.36398148 | Y87: 【-】 | Z87: 【-】 | AA87: 【-】 | AB87: 【-】
A88: 87 | B88: 小程序 | C88: 1003468159 | D88: 45731 | E88: 0.36356481 | F88: 【万龙】全雪区日场1天雪票（2.15-3.21） | G88: 1 | H88: 已核销 | I88: -539 | J88: -559 | K88: 0 | L88: -20 | M88: 林书 | N88: 18811451068 | O88: 【-】 | P88: 【-】 | Q88: 【-】 | R88: 【-】 | S88: 【-】 | T88: 【-】 | U88: QJ_XP_20250315_052489_ZF_01 | V88: -559 | W88: 45731 | X88: 0.3634838 | Y88: 【-】 | Z88: 【-】 | AA88: 【-】 | AB88: 【-】
A89: 88 | B89: 小程序 | C89: 1003469111 | D89: 45731 | E89: 0.36258102 | F89: 【万龙】全雪区日场1天雪票（2.15-3.21） | G89: 1 | H89: 已取消 | I89: -539 | J89: -559 | K89: -559 | L89: 0 | M89: 崔洋（个人） | N89: 13910231129 | O89: 【-】 | P89: 【-】 | Q89: 【-】 | R89: 【-】 | S89: 【-】 | T89: 【-】 | U89: QJ_XP_20250315_052488_ZF_01 | V89: -559 | W89: 45731 | X89: 0.36246528 | Y89: QJ_XP_20250315_052488_ZF_01_TK_01_20250315 | Z89: -559 | AA89: 45731 | AB89: 0.36872685
A90: 89 | B90: 小程序 | C90: 1003287598 | D90: 45730 | E90: 0.56979167 | F90: 【万龙】平日/周末全雪区下午场+夜场雪票（2.15-3.7） | G90: 1 | H90: 已取消 | I90: -410 | J90: -420 | K90: -420 | L90: 0 | M90: 颜雨薇 | N90: 15110133454 | O90: 【-】 | P90: 【-】 | Q90: 【-】 | R90: 【-】 | S90: 【-】 | T90: 【-】 | U90: QJ_XP_20250314_051580_ZF_01 | V90: -420 | W90: 45730 | X90: 0.56958333 | Y90: QJ_XP_20250314_051580_ZF_01_TK_01_20250314 | Z90: -420 | AA90: 45730 | AB90: 0.71497685
A91: 90 | B91: 小程序 | C91: 1003216934 | D91: 45730 | E91: 0.41679398 | F91: 【万龙】全雪区日场4小时雪票 | G91: 1 | H91: 已核销 | I91: -333 | J91: -348 | K91: 0 | L91: -15 | M91: 古 | N91: 13764752798 | O91: 【-】 | P91: 【-】 | Q91: 【-】 | R91: 【-】 | S91: 【-】 | T91: 【-】 | U91: QJ_XP_20250314_051565_ZF_01 | V91: -348 | W91: 45730 | X91: 0.41666667 | Y91: 【-】 | Z91: 【-】 | AA91: 【-】 | AB91: 【-】
A92: 91 | B92: 小程序 | C92: 1003217879 | D92: 45730 | E92: 0.41630787 | F92: 【万龙】全雪区日场4小时雪票 | G92: 1 | H92: 已核销 | I92: -333 | J92: -348 | K92: 0 | L92: -15 | M92: 古 | N92: 13764752798 | O92: 【-】 | P92: 【-】 | Q92: 【-】 | R92: 【-】 | S92: 【-】 | T92: 【-】 | U92: QJ_XP_20250314_051564_ZF_01 | V92: -348 | W92: 45730 | X92: 0.41621528 | Y92: 【-】 | Z92: 【-】 | AA92: 【-】 | AB92: 【-】
A93: 92 | B93: 小程序 | C93: 1003215421 | D93: 45730 | E93: 0.3744213 | F93: 【万龙】全雪区日场1天雪票（2.15-3.16） | G93: 1 | H93: 已核销 | I93: -427 | J93: -447 | K93: 0 | L93: -20 | M93: 方 | N93: 15757791032 | O93: 张小飞 | P93: -1 | Q93: 已分 | R93: 45730 | S93: 0.3840625 | T93: QJ_XP_20250314_051562_ZF_01_FZ_20250314_01 | U93: QJ_XP_20250314_051562_ZF_01 | V93: -447 | W93: 45730 | X93: 0.37435185 | Y93: 【-】 | Z93: 【-】 | AA93: 【-】 | AB93: 【-】
A94: 93 | B94: 小程序 | C94: 1003216387 | D94: 45730 | E94: 0.36673611 | F94: 【万龙】全雪区日场1天雪票（2.15-3.16） | G94: 1 | H94: 已核销 | I94: -427 | J94: -447 | K94: 0 | L94: -20 | M94: 李 | N94: 18526424075 | O94: 【-】 | P94: 【-】 | Q94: 【-】 | R94: 【-】 | S94: 【-】 | T94: 【-】 | U94: QJ_XP_20250314_051560_ZF_01 | V94: -447 | W94: 45730 | X94: 0.3666088 | Y94: 【-】 | Z94: 【-】 | AA94: 【-】 | AB94: 【-】
A95: 94 | B95: 小程序 | C95: 1002738829 | D95: 45727 | E95: 0.9478588 | F95: 【万龙】全雪区日场1天雪票（2.15-3.16） | G95: 1 | H95: 已核销 | I95: -539 | J95: -559 | K95: 0 | L95: -20 | M95: 林纾琳 | N95: 18959229966 | O95: 【-】 | P95: 【-】 | Q95: 【-】 | R95: 【-】 | S95: 【-】 | T95: 【-】 | U95: QJ_XP_20250311_051511_ZF_01 | V95: -559 | W95: 45727 | X95: 0.9477662 | Y95: 【-】 | Z95: 【-】 | AA95: 【-】 | AB95: 【-】
A96: 95 | B96: 小程序 | C96: 1002738810 | D96: 45727 | E96: 0.94663194 | F96: 【万龙】全雪区日场1.5天雪票（2.15-3.16） | G96: 1 | H96: 已核销 | I96: -809 | J96: -829 | K96: 0 | L96: -20 | M96: 林纾琳 | N96: 18959229966 | O96: 【-】 | P96: 【-】 | Q96: 【-】 | R96: 【-】 | S96: 【-】 | T96: 【-】 | U96: QJ_XP_20250311_051510_ZF_01 | V96: -829 | W96: 45727 | X96: 0.94633102 | Y96: 【-】 | Z96: 【-】 | AA96: 【-】 | AB96: 【-】
A97: 96 | B97: 小程序 | C97: 1002712352 | D97: 45727 | E97: 0.76847222 | F97: 【万龙】全雪区日场2天雪票（2.15-3.16） | G97: 1 | H97: 已核销 | I97: -818 | J97: -838 | K97: 0 | L97: -20 | M97: 方 | N97: 15757791032 | O97: 张小飞 | P97: -1 | Q97: 已分 | R97: 45728 | S97: 0.37989583 | T97: QJ_XP_20250311_051508_ZF_01_FZ_20250311_01 | U97: QJ_XP_20250311_051508_ZF_01 | V97: -838 | W97: 45727 | X97: 0.76833333 | Y97: 【-】 | Z97: 【-】 | AA97: 【-】 | AB97: 【-】
A98: 97 | B98: 小程序 | C98: 1002562369 | D98: 45727 | E98: 0.37638889 | F98: 【万龙】全雪区日场6小时雪票（2.15-3.16） | G98: 1 | H98: 已核销 | I98: -390 | J98: -415 | K98: 0 | L98: -25 | M98: 马 | N98: 18601011785 | O98: 【-】 | P98: 【-】 | Q98: 【-】 | R98: 【-】 | S98: 【-】 | T98: 【-】 | U98: QJ_XP_20250311_051484_ZF_01 | V98: -415 | W98: 45727 | X98: 0.37628472 | Y98: 【-】 | Z98: 【-】 | AA98: 【-】 | AB98: 【-】
A99: 98 | B99: 小程序 | C99: 1002403656 | D99: 45726 | E99: 0.59868056 | F99: 【万龙】全雪区日场1.5天雪票（2.15-3.16） | G99: 1 | H99: 已核销 | I99: -641 | J99: -661 | K99: 0 | L99: -20 | M99: 于丰畅 | N99: 13391977187 | O99: 【-】 | P99: 【-】 | Q99: 【-】 | R99: 【-】 | S99: 【-】 | T99: 【-】 | U99: QJ_XP_20250310_051455_ZF_01 | V99: -661 | W99: 45726 | X99: 0.59840278 | Y99: 【-】 | Z99: 【-】 | AA99: 【-】 | AB99: 【-】
A100: 99 | B100: 小程序 | C100: 1002403658 | D100: 45726 | E100: 0.59868056 | F100: 【万龙】全雪区日场1.5天雪票（2.15-3.16） | G100: 1 | H100: 已核销 | I100: -641 | J100: -661 | K100: 0 | L100: -20 | M100: 张冠群 | N100: 13581769117 | O100: 布乖 | P100: -1 | Q100: 已分 | R100: 45726 | S100: 0.60072917 | T100: QJ_XP_20250310_051454_ZF_01_FZ_20250310_01 | U100: QJ_XP_20250310_051454_ZF_01 | V100: -661 | W100: 45726 | X100: 0.59831019 | Y100: 【-】 | Z100: 【-】 | AA100: 【-】 | AB100: 【-】
...

Sheet 25-26雪季预定
A2: 序号 | B2: 姓名 | C2: 电话 | D2: 购买金额 | E2: 储值金额 | F2: 储值来源 | G2: 有效期 | H2: 七色米销售单 | I2: 可用业务
A3: 1 | B3: 赵永志 | C3: 18910072993 | D3: 5499 | E3: 2000 | F3: 预定25-26 | G3: 2027.3.31 | H3: XSD20250208002I | I3: 修刃、打蜡、租赁、非雪季养护寄存（无增值包） | J3: 万龙店
A4: 2 | B4: 朱智 | C4: 13811515813 | D4: 5699 | E4: 2000 | F4: 预定25-26 | G4: 2027.3.31 | H4: XSD20250206023I | I4: 修刃、打蜡、租赁、非雪季养护寄存（无增值包） | J4: 万龙店
A5: 3 | B5: 汪先生 | C5: 13683137883 | D5: 5499 | E5: 2000 | F5: 预定25-26 | G5: 2027.3.31 | H5: XSD20250204025I | I5: 修刃、打蜡、租赁、非雪季养护寄存（无增值包） | J5: XSD20250204025I
A6: 4 | B6: 翟剑南 | C6: 18621709399 | D6: 5499 | E6: 1000 | F6: 预定25-26 | G6: 2027.3.31 | H6: XSD20250204003A | I6: 修刃、打蜡、租赁、非雪季养护寄存（无增值包）
A7: 5 | B7: 袁兆谦 | C7: 18612859355 | D7: 6599 | E7: 2000 | F7: 预定25-26 | G7: 2027.3.31 | H7: XSD20250203013I | I7: 修刃、打蜡、租赁、非雪季养护寄存（无增值包）
A8: 6 | B8: 力梦伦 | C8: 13691204434 | D8: 6599 | E8: 2000 | F8: 预定25-26 | G8: 2027.3.31 | H8: XSD20250202003I | I8: 修刃、打蜡、租赁、非雪季养护寄存（无增值包）
A9: 7 | B9: 刘琰 | C9: 13801361262 | D9: 4300 | E9: 1000 | F9: 预定25-26 | G9: 2027.3.31 | H9: XSD20250130022A | I9: 修刃、打蜡、租赁、非雪季养护寄存（无增值包）
A10: 8 | B10: 李霄凯 | C10: 18611667889 | D10: 5199 | E10: 2000 | F10: 预定25-26 | G10: 2027.3.31 | H10: XSD20250130015I | I10: 修刃、打蜡、租赁、非雪季养护寄存（无增值包）
A11: 9 | B11: hanha | C11: 13311200117 | D11: 5499 | E11: 2000 | F11: 预定25-26 | G11: 2027.3.31 | H11: XSD20250125007I | I11: 修刃、打蜡、租赁、非雪季养护寄存（无增值包）
A12: 10 | B12: 马先生 | C12: 13621228009 | D12: 6899 | E12: 2000 | F12: 预定25-26 | G12: 2027.3.31 | H12: XSD20250121006I | I12: 修刃、打蜡、租赁、非雪季养护寄存（无增值包）
A13: 11 | B13: 孙先生 | C13: 13070943844 | D13: 5300 | E13: 1000 | F13: 现货雪板送 | G13: 2027.3.31 | H13: XSD20250204031I | I13: 修刃、打蜡、租赁、非雪季养护寄存（无增值包）
A14: 12 | B14: 秦先生 | C14: 18810808830 | D14: 5500 | E14: 1000 | F14: 现货雪板送 | G14: 2027.3.31 | H14: XSD20250203027A | I14: 修刃、打蜡、租赁、非雪季养护寄存（无增值包）
A15: 13 | B15: 王先生 | C15: 13911834369 | D15: 5500 | E15: 2000 | F15: 现货雪板送 | G15: 2027.3.31 | H15: XSD20250202009A | I15: 修刃、打蜡、租赁、非雪季养护寄存（无增值包）
A16: 14 | B16: 刘女士 | C16: 13512003878 | D16: 6000 | E16: 6000 | F16: 储值送雪板 | G16: 2027.3.31 | H16: XSD20250209013A | I16: 修刃、打蜡、租赁、非雪季养护寄存（无增值包）
D17: ==SUM(D3:D16) -> 79591

Sheet 七色米南山雪票
A1: 业务日期 | B1: 单据编号 | C1: 所属门店 | D1: 仓库 | E1: 客户名称 | F1: 销售商品 | G1: 销售数量 | H1: 总计金额 | I1: 实收金额 | J1: 结算方式 | K1: 转给南山票款 | L1: 转款方式 | M1: 备注
A2: 45635 | B2: XSD20241209004A | C2: 【北京】【南山店】 | D2: 【南山】固定资产仓 | E2: 雪票客户 | F2: 南山雪票/自带平日/下午加夜场/200、南山雪票/租板平日/下午加夜场/220 | G2: 4 | H2: 820 | I2: 820 | J2: 银行转账-ZB | K2: 820 | L2: 工作号 | M2: 南山客服号微信转账
A3: 45636 | B3: XSD20241210004A | C3: 【北京】【南山店】 | D3: 【南山】固定资产仓 | E3: 雪票客户 | F3: 南山雪票/自带平日/下午加夜场/200、南山雪票/自带平日/四小时/170 | G3: 3 | H3: 540 | I3: 540 | J3: 银行转账-ZB | K3: 540 | L3: 工作号 | M3: 南山客服微信转
A4: 45636 | B4: XSD20241211001A | C4: 【北京】【南山店】 | D4: 【南山】固定资产仓 | E4: 雪票客户 | F4: 南山雪票/自带平日/夜场/135 | G4: 2 | H4: 270 | I4: 270 | J4: 银行转账-ZB | K4: 270 | L4: 工作号 | M4: 南山客服微信转账
A5: 45637 | B5: XSD20241220014A | C5: 【北京】【南山店】 | D5: 【南山】固定资产仓 | E5: 雪票客户 | F5: 南山雪票/自带平日/夜场/135、南山雪票/租板平日/夜场/145 | G5: 4 | H5: 560 | I5: 560 | J5: 银行转账-ZB | K5: 620 | L5: 工作号 | M5: 客服号微信转（多转60。12.12少转60）
A6: 45637 | B6: XSD20241211005A | C6: 【北京】【南山店】 | D6: 【南山】固定资产仓 | E6: 雪票客户 | F6: 南山雪票/自带平日/下午加夜场/200、南山雪票/租板平日/下午加夜场/220 | G6: 5 | H6: 1040 | I6: 1040 | J6: 银行转账-ZB | K6: 1040 | L6: 工作号 | M6: 南山客服微信转
A7: 45638 | B7: XSD20241212009A | C7: 【北京】【南山店】 | D7: 【南山】固定资产仓 | E7: 雪票客户 | F7: 南山雪票/自带平日/全天/190 | G7: 1 | H7: 190 | I7: 190 | J7: 银行转账-NS | K7: 130 | L7: 工作号 | M7: 客服微信转，少转60
A8: 45639 | B8: XSD20241214026A | C8: 【北京】【南山店】 | D8: 【南山】固定资产仓 | E8: 雪票客户 | F8: 南山雪票/自带平日/全天/190、南山雪票/租板平日/夜场/145 | G8: 3 | H8: 525 | I8: 870 | J8: 银行转账-ZB | K8: ==290+580 -> 870 | L8: 工作号 | M8: 工作号微信转账（现加2张全天自带平日1张夜场租板525）
A9: 45640 | B9: XSD20241220002A | C9: 【北京】【南山店】 | D9: 【南山】固定资产仓 | E9: 雪票客户 | F9: 南山雪票/租板周末/全天/350、南山雪票/租板周末/下午加夜场/335、南山雪票/自带周六/夜场/155 | G9: 7 | H9: 2195 | I9: 2195 | J9: 银行转账-ZB | K9: ==1745+5360 -> 7105 | L9: 王倩个人微信 | M9: 客服微信号收款
A10: 45640 | B10: XSD20241218001A | C10: 【北京】【南山店】 | D10: 【南山】固定资产仓 | E10: 雪票客户 | F10: 南山雪票/租板周末/全天/350、南山雪票/自带周末/四小时/285、南山雪票/自带周末/全天/330、南山雪票/租板周末/下午加夜场/335、南山雪票/租板周六/夜场/165、南山雪票/租板周六/夜场/165、南山雪票/自带周六/夜场/155 | G10: 20 | H10: 4910 | I10: 4910 | J10: 【小程序】微信-NS | N10: 5360
A11: 45641 | B11: XSD20241220005A | C11: 【北京】【南山店】 | D11: 【南山】固定资产仓 | E11: 雪票客户 | F11: 南山雪票/自带周末/四小时/285 | G11: 2 | H11: 570 | I11: 570 | J11: 银行转账-ZB | K11: 1815 | L11: 招行8997 | M11: 客服微信号收款 | N11: 1745
A12: 45641 | B12: XSD20241220004A | C12: 【北京】【南山店】 | D12: 【南山】固定资产仓 | E12: 雪票客户 | F12: 南山雪票/租板周末/四小时/305 | G12: 2 | H12: 610 | I12: 610 | J12: 现金-NS
A13: 45641 | B13: XSD20241220003A | C13: 【北京】【南山店】 | D13: 【南山】固定资产仓 | E13: 雪票客户 | F13: 南山雪票/自带周末/全天/330、南山雪票/租板周末/四小时/305 | G13: 2 | H13: 635 | I13: 635 | J13: 【小程序】微信-NS
A14: 45642 | B14: XSD20241216008A | C14: 【北京】【南山店】 | D14: 【南山】固定资产仓 | E14: 雪票客户 | F14: 南山雪票/自带平日/夜场/135、南山雪票/租板平日/夜场/145 | G14: 2 | H14: 280 | I14: 280 | J14: 【小程序】微信-NS | K14: 280 | L14: 招行8997
A15: 45642 | B15: XSD20241216005A | C15: 【北京】【南山店】 | D15: 【南山】固定资产仓 | E15: 雪票客户 | F15: 南山雪票/自带平日/下午加夜场/200 | G15: 4 | H15: 800 | I15: 800 | J15: 【小程序】微信-NS | K15: 800 | L15: 招行8997
A16: 45643 | B16: XSD20241218000A | C16: 【北京】【南山店】 | D16: 【南山】固定资产仓 | E16: 雪票客户 | F16: 南山雪票/自带平日/全天/190 | G16: 2 | H16: 380 | I16: 380 | J16: 【小程序】微信-NS | K16: 380 | L16: 招行8997
A17: 45644 | B17: XSD20241220007A | C17: 【北京】【南山店】 | D17: 【南山】固定资产仓 | E17: 雪票客户 | F17: 南山雪票/自带平日/下午加夜场/200、南山雪票/自带平日/全天/190、南山雪票/自带平日/四小时/170 | G17: 3 | H17: 560 | I17: 560 | J17: 银行转账-ZB | K17: 560 | L17: 招行8997 | M17: 微信客服号收
A18: 45645 | B18: XSD20241219014A | C18: 【北京】【南山店】 | D18: 【南山】固定资产仓 | E18: 雪票客户 | F18: 南山雪票/自带平日/夜场/135 | G18: 1 | H18: 135 | I18: 135 | J18: 【小程序】微信-NS | K18: 135 | L18: 邮储9978
A19: 45645 | B19: XSD20241219011A | C19: 【北京】【南山店】 | D19: 【南山】固定资产仓 | E19: 雪票客户 | F19: 南山雪票/自带平日/全天/190、南山雪票/租板平日/全天/210 | G19: 3 | H19: 610 | I19: 610 | J19: 银行转账-NS | K19: 1560 | L19: 邮储9978 | M19: 客服号微信收
A20: 45645 | B20: XSD20241219010A | C20: 【北京】【南山店】 | D20: 【南山】固定资产仓 | E20: 雪票客户 | F20: 南山雪票/自带平日/全天/190 | G20: 5 | H20: 950 | I20: 950 | J20: 【小程序】微信-NS
K21: 640 | L21: 邮储9978
A23: 南山雪票收款付款明细
A24: 七色米收款 | E24: 南山付款
A25: 业务日期 | B25: 单据编号 | C25: 实收金额 | D25: 结算方式 | E25: 付南山票款 | F25: 付款方式
A26: 45635 | B26: XSD20241209004A | C26: 820 | D26: 银行转账-ZB | E26: 820 | F26: 工作号
A27: 45636 | B27: XSD20241210004A | C27: 540 | D27: 银行转账-ZB | E27: 540
A28: 45636 | B28: XSD20241211001A | C28: 270 | D28: 银行转账-ZB | E28: 270
A29: 45637 | B29: XSD20241220014A | C29: 560 | D29: 银行转账-ZB | E29: 620
A30: 45637 | B30: XSD20241211005A | C30: 1040 | D30: 银行转账-ZB | E30: 1040
A31: 45638 | B31: XSD20241212009A | C31: 190 | D31: 银行转账-NS | E31: 130
A32: 45638 | B32: XSD20241221006A | C32: 270 | D32: 银行转账-ZB | E32: 270
A33: 45639 | B33: XSD20241220006A | C33: 345 | D33: 【小程序】微信-NS | E33: 870
A34: 45639 | B34: XSD20241214026A | C34: 525 | D34: 银行转账-ZB
A35: 45640 | B35: XSD20241220002A | C35: 2195 | D35: 银行转账-ZB | E35: 7105 | F35: 王倩个人微信
A36: 45640 | B36: XSD20241218001A | C36: 4910 | D36: 【小程序】微信-NS
A37: 45641 | B37: XSD20241220005A | C37: 570 | D37: 银行转账-ZB | E37: 1815 | F37: 招行8997
A38: 45641 | B38: XSD20241220004A | C38: 610 | D38: 现金-NS
A39: 45641 | B39: XSD20241220003A | C39: 635 | D39: 【小程序】微信-NS
A40: 45642 | B40: XSD20241216008A | C40: 280 | D40: 【小程序】微信-NS | E40: 280 | F40: 招行8997
A41: 45642 | B41: XSD20241216005A | C41: 800 | D41: 【小程序】微信-NS | E41: 800 | F41: 招行8997
A42: 45643 | B42: XSD20241218000A | C42: 380 | D42: 【小程序】微信-NS | E42: 380 | F42: 招行8997
A43: 45644 | B43: XSD20241220007A | C43: 560 | D43: 银行转账-ZB | E43: 560 | F43: 招行8997
A44: 45645 | B44: XSD20241219014A | C44: 135 | D44: 【小程序】微信-NS | E44: 135 | F44: 邮储9978
A45: 45645 | B45: XSD20241219011A | C45: 610 | D45: 银行转账-NS | E45: 1560 | F45: 邮储9978
A46: 45645 | B46: XSD20241219010A | C46: 950 | D46: 【小程序】微信-NS
A47: 45647 | B47: XSD20241221021A | C47: 4180 | D47: 银行转账-ZB | E47: 640 | F47: 邮储9978

Sheet 付南山雪票款
